Workbook

Sheet DocPages
A1: ServiceName | B1: ServiceShortName | C1: Page | D1: SpanPrefix
A2: Account access manager | B2: account-access | C2: list_account-access.html
A3: Alexa for Business | B3: a4b | C3: list_a4b.html
A4: Amazon AI Operations | B4: aiops | C4: list_aiops.html
A5: Amazon API Gateway | B5: execute-api | C5: list_apigatewaymanagementapi.html | D5: list_apigatewaymanagementapi-action-
A6: Amazon API Gateway Management | B6: apigateway | C6: list_apigateway.html
A7: Amazon API Gateway Management V2 | B7: apigateway | C7: list_apigatewayv2.html | D7: list_apigatewayv2-action-
A8: Amazon AppFlow | B8: appflow | C8: list_appflow.html
A9: Amazon AppIntegrations | B9: app-integrations | C9: list_appintegrations.html | D9: list_appintegrations-action-
A10: Amazon Application Recovery Controller - Zonal Shift | B10: arc-zonal-shift | C10: list_arc-zonal-shift.html
A11: Amazon AppStream 2.0 | B11: appstream | C11: list_appstream.html
A12: Amazon ARC Region switch | B12: arc-region-switch | C12: list_arc-region-switch.html
A13: Amazon Athena | B13: athena | C13: list_athena.html
A14: Amazon Aurora DSQL | B14: dsql | C14: list_dsql.html
A15: Amazon Bedrock | B15: bedrock | C15: list_bedrock.html
A16: Amazon Bedrock Agentcore | B16: bedrock-agentcore | C16: list_bedrock-agentcore.html
A17: Amazon Bedrock Powered by AWS Mantle | B17: bedrock-mantle | C17: list_bedrock-mantle.html
A18: Amazon Bedrock Web Search | B18: bedrock-websearch | C18: list_bedrock-websearch.html
A19: Amazon Bio Discovery | B19: researchstudio | C19: list_researchstudio.html
A20: Amazon Braket | B20: braket | C20: list_braket.html
A21: Amazon Chime | B21: chime | C21: list_chime.html
... A26: Amazon CloudWatch | B26: cloudwatch | C26: list_cloudwatch.html
A27: Amazon CloudWatch Application Insights | B27: applicationinsights | C27: list_application-insights.html | D27: list_application-insights-action-
A28: Amazon CloudWatch Application Signals | B28: application-signals | C28: list_application-signals.html
A29: Amazon CloudWatch Application Signals MCP Server | B29: application-signals-mcp | C29: list_application-signals-mcp.html
A30: Amazon CloudWatch Evidently | B30: evidently | C30: list_evidently.html
A31: Amazon CloudWatch Internet Monitor | B31: internetmonitor | C31: list_internetmonitor.html
A32: Amazon CloudWatch Logs | B32: logs | C32: list_logs.html
A33: Amazon CloudWatch Network Synthetic Monitor | B33: networkmonitor | C33: list_networkmonitor.html
A34: Amazon CloudWatch Observability Access Manager | B34: oam | C34: list_oam.html
A35: Amazon CloudWatch Observability Admin Service | B35: observabilityadmin | C35: list_observabilityadmin.html
A36: Amazon CloudWatch Synthetics | B36: synthetics | C36: list_synthetics.html
A37: Amazon CodeCatalyst | B37: codecatalyst | C37: list_codecatalyst.html
A38: Amazon CodeGuru | B38: codeguru | C38: list_codeguru.html
A39: Amazon CodeGuru Profiler | B39: codeguru-profiler | C39: list_codeguruprofiler.html | D39: list_codeguruprofiler-action-
A40: Amazon CodeGuru Reviewer | B40: codeguru-reviewer | C40: list_codeguru-reviewer.html
A41: Amazon CodeGuru Security | B41: codeguru-security | C41: list_codeguru-security.html
A42: Amazon CodeWhisperer | B42: codewhisperer | C42: list_codewhisperer.html
A43: Amazon Cognito Identity | B43: cognito-identity | C43: list_cognito-identity.html
A44: Amazon Cognito Sync | B44: cognito-sync | C44: list_cognito-sync.html
A45: Amazon Cognito User Pools | B45: cognito-idp | C45: list_cognito-idp.html
A46: Amazon Comprehend | B46: comprehend | C46: list_comprehend.html
A47: Amazon Comprehend Medical | B47: comprehendmedical | C47: list_comprehendmedical.html
A48: Amazon Connect | B48: connect | C48: list_connect.html | D48: list_connect-action-
A49: Amazon Connect Cases | B49: cases | C49: list_connectcases.html | D49: list_connectcases-action-
A50: Amazon Connect Customer Profiles | B50: profile | C50: list_customer-profiles.html | D50: list_customer-profiles-action-
A51: Amazon Connect Health | B51: health-agent | C51: list_connecthealth.html | D51: list_connecthealth-action-
A52: Amazon Connect Outbound Campaigns | B52: connect-campaigns | C52: list_connect-outbound-campaigns.html | D52: list_connect-outbound-campaigns-action-
A53: Amazon Connect Voice ID | B53: voiceid | C53: list_voice-id.html | D53: list_voice-id-action-
A54: Amazon Data Lifecycle Manager | B54: dlm | C54: list_dlm.html
A55: Amazon DataZone | B55: datazone | C55: list_datazone.html
A56: Amazon Detective | B56: detective | C56: list_detective.html
A57: Amazon DevOps Guru | B57: devops-guru | C57: list_devops-guru.html
A58: Amazon DocumentDB Elastic Clusters | B58: docdb-elastic | C58: list_docdb-elastic.html
A59: Amazon DynamoDB | B59: dynamodb | C59: list_dynamodb.html
A60: Amazon DynamoDB Accelerator (DAX) | B60: dax | C60: list_dax.html
A61: Amazon EC2 | B61: ec2 | C61: list_ec2.html | D61: list_ec2-action-
A62: Amazon EC2 Auto Scaling | B62: autoscaling | C62: list_autoscaling.html
A63: Amazon EC2 Image Builder | B63: imagebuilder | C63: list_imagebuilder.html
A64: Amazon EC2 Instance Connect | B64: ec2-instance-connect | C64: list_ec2-instance-connect.html
A65: Amazon ECS MCP Service | B65: ecs-mcp | C65: list_ecs-mcp.html
A66: Amazon EKS Auth | B66: eks-auth | C66: list_eks-auth.html
A67: Amazon EKS MCP Server | B67: eks-mcp | C67: list_eks-mcp.html
A68: Amazon Elastic Block Store | B68: ebs | C68: list_ebs.html
A69: Amazon Elastic Container Registry | B69: ecr | C69: list_ecr.html
A70: Amazon Elastic Container Registry Public | B70: ecr-public | C70: list_ecr-public.html
A71: Amazon Elastic Container Service | B71: ecs | C71: list_ecs.html
A72: Amazon Elastic File System | B72: elasticfilesystem | C72: list_efs.html | D72: list_efs-action-
A73: Amazon Elastic Kubernetes Service | B73: eks | C73: list_eks.html
A74: Amazon Elastic MapReduce | B74: elasticmapreduce | C74: list_emr.html | D74: list_emr-action-
A75: Amazon Elastic Transcoder | B75: elastictranscoder | C75: list_elastictranscoder.html
A76: Amazon Elastic VMware Service | B76: evs | C76: list_evs.html
A77: Amazon ElastiCache | B77: elasticache | C77: list_elasticache.html
A78: Amazon EMR on EKS (EMR Containers) | B78: emr-containers | C78: list_emr-containers.html
A79: Amazon EMR Serverless | B79: emr-serverless | C79: list_emr-serverless.html
A80: Amazon EventBridge | B80: events | C80: list_eventbridge.html | D80: list_eventbridge-action-
A81: Amazon EventBridge Pipes | B81: pipes | C81: list_pipes.html
A82: Amazon EventBridge Scheduler | B82: scheduler | C82: list_scheduler.html
A83: Amazon EventBridge Schemas | B83: schemas | C83: list_schemas.html
A84: Amazon FinSpace | B84: finspace | C84: list_finspace.html
A85: Amazon FinSpace API | B85: finspace-api | C85: list_finspace-data.html | D85: list_finspace-data-action-
A86: Amazon Forecast | B86: forecast | C86: list_forecast.html
A87: Amazon Fraud Detector | B87: frauddetector | C87: list_frauddetector.html
A88: Amazon FreeRTOS | B88: freertos | C88: list_freertos.html
A89: Amazon FSx | B89: fsx | C89: list_fsx.html
A90: Amazon GameLift Servers | B90: gamelift | C90: list_gamelift.html
A91: Amazon GameLift Streams | B91: gameliftstreams | C91: list_gameliftstreams.html
A92: Amazon GroundTruth Labeling | B92: groundtruthlabeling | C92: list_groundtruthlabeling.html
A93: Amazon GuardDuty | B93: guardduty | C93: list_guardduty.html
A94: Amazon Honeycode | B94: honeycode | C94: list_honeycode.html
A95: Amazon Inspector | B95: inspector | C95: list_inspector.html
A96: Amazon Inspector2 | B96: inspector2 | C96: list_inspector2.html
A97: Amazon Inspector2 Telemetry Channel | B97: inspector2-telemetry | C97: list_inspector2-telemetry.html
A98: Amazon InspectorScan | B98: inspector-scan | C98: list_inspector-scan.html
A99: Amazon Interactive Video Service | B99: ivs | C99: list_interactive-video-service.html | D99: list_interactive-video-service-action-
A100: Amazon Interactive Video Service Chat | B100: ivschat | C100: list_ivschat.html
A101: Amazon Kendra | B101: kendra | C101: list_kendra.html
A102: Amazon Kendra Intelligent Ranking | B102: kendra-ranking | C102: list_kendra-ranking.html
A103: Amazon Keyspaces (for Apache Cassandra) | B103: cassandra | C103: list_keyspaces.html | D103: list_keyspaces-action-
A104: Amazon Kinesis Analytics | B104: kinesisanalytics | C104: list_kinesisanalytics.html
...

Sheet DocPages (DEV)
A1: ServiceName | B1: ServiceShortName | C1: Page | D1: SpanPrefix | E1: Link | F1: ExampleAction
A2: Account access manager | B2: account-access | C2: list_account-access.html
A3: Alexa for Business | B3: a4b | C3: list_a4b.html
A4: Amazon AI Operations | B4: aiops | C4: list_aiops.html
A5: Amazon API Gateway | B5: execute-api | C5: list_apigatewaymanagementapi.html | D5: ="list_" & MID($C5,6,LEN($C5)-10) & "-action-" -> list_apigatewaymanagementapi-action- | E5: =HYPERLINK("https://docs.aws.amazon.com/service-authorization/latest/reference/" & $C5,"link") -> link | F5: =B5 & ":" & MID($H5,3,FIND(CHAR(34),$H5,3)-3) -> execute-api:InvalidateCache | H5: =INDEX('AwsServices-Temp'!$C$2:$C$478,MATCH($A5,'AwsServices-Temp'!$B$2:$B$478,0)) -> ["InvalidateCache","Invoke","ManageConnections"]
A6: Amazon API Gateway Management | B6: apigateway | C6: list_apigateway.html | E6: =HYPERLINK("https://docs.aws.amazon.com/service-authorization/latest/reference/" & $C6,"link") -> link
A7: Amazon API Gateway Management V2 | B7: apigateway | C7: list_apigatewayv2.html | D7: list_apigatewayv2-action- | E7: =HYPERLINK("https://docs.aws.amazon.com/service-authorization/latest/reference/" & $C7,"link") -> link | F7: =B7 & ":" & MID($H7,3,FIND(CHAR(34),$H7,3)-3) -> apigateway:CreatePortal | G7: X | H7: =INDEX('AwsServices-Temp'!$C$2:$C$478,MATCH($A7,'AwsServices-Temp'!$B$2:$B$478,0)) -> ["CreatePortal","CreatePortalProduct","CreateProductPage","CreateProductRestEndpointPage","CreateRoutingRule","DELETE","DeletePortal","DeletePortalProduct","DeletePortalProductSharingPolicy","DeleteProductPage","DeleteProductRestEndpointPage","DeleteRoutingRule","DisablePortal","GET","GetPortal","GetPortalProduct","GetPortalProductSharingPolicy","GetProductPage","GetProductRestEndpointPage","GetRoutingRule","ListPortalProducts","ListPortals","ListProductPages","ListProductRestEndpointPages","ListRoutingRules","PATCH","POST","PUT","PreviewPortal","PublishPortal","PutPortalProductSharingPolicy","UpdatePortal","UpdatePortalProduct","UpdateProductPage","UpdateProductRestEndpointPage","UpdateRoutingRule"]
A8: Amazon AppFlow | B8: appflow | C8: list_appflow.html
A9: Amazon AppIntegrations | B9: app-integrations | C9: list_appintegrations.html | D9: ="list_" & MID($C9,6,LEN($C9)-10) & "-action-" -> list_appintegrations-action- | E9: =HYPERLINK("https://docs.aws.amazon.com/service-authorization/latest/reference/" & $C9,"link") -> link | F9: =B9 & ":" & MID($H9,3,FIND(CHAR(34),$H9,3)-3) -> app-integrations:CreateApplication | H9: =INDEX('AwsServices-Temp'!$C$2:$C$478,MATCH($A9,'AwsServices-Temp'!$B$2:$B$478,0)) -> ["CreateApplication","CreateApplicationAssociation","CreateDataIntegration","CreateDataIntegrationAssociation","CreateDataIntegrationSchedule","CreateEventIntegration","CreateEventIntegrationAssociation","DeleteApplication","DeleteApplicationAssociation","DeleteDataIntegration","DeleteDataIntegrationAssociation","DeleteEventIntegration","DeleteEventIntegrationAssociation","GetApplication","GetDataIntegration","GetDataIntegrationExecution","GetDataIntegrationSchedule","GetEventIntegration","ListApplicationAssociations","ListApplications","ListDataIntegrationAssociations","ListDataIntegrationExecutions","ListDataIntegrationSchedules","ListDataIntegrations","ListEventIntegrationAssociations","ListEventIntegrations","ListTagsForResource","StartDataIntegrationExecution","TagResource","UntagResource","UpdateApplication","UpdateDataIntegration","UpdateDataIntegrationAssociation","UpdateDataIntegrationSchedule","UpdateEventIntegration"]
A10: Amazon Application Recovery Controller - Zonal Shift | B10: arc-zonal-shift | C10: list_arc-zonal-shift.html
A11: Amazon AppStream 2.0 | B11: appstream | C11: list_appstream.html
A12: Amazon ARC Region switch | B12: arc-region-switch | C12: list_arc-region-switch.html
A13: Amazon Athena | B13: athena | C13: list_athena.html
A14: Amazon Aurora DSQL | B14: dsql | C14: list_dsql.html
A15: Amazon Bedrock | B15: bedrock | C15: list_bedrock.html
A16: Amazon Bedrock Agentcore | B16: bedrock-agentcore | C16: list_bedrock-agentcore.html
A17: Amazon Bedrock Powered by AWS Mantle | B17: bedrock-mantle | C17: list_bedrock-mantle.html
A18: Amazon Bedrock Web Search | B18: bedrock-websearch | C18: list_bedrock-websearch.html
A19: Amazon Bio Discovery | B19: researchstudio | C19: list_researchstudio.html
A20: Amazon Braket | B20: braket | C20: list_braket.html
A21: Amazon Chime | B21: chime | C21: list_chime.html
... A26: Amazon CloudWatch | B26: cloudwatch | C26: list_cloudwatch.html
A27: Amazon CloudWatch Application Insights | B27: applicationinsights | C27: list_application-insights.html | D27: ="list_" & MID($C27,6,LEN($C27)-10) & "-action-" -> list_application-insights-action- | E27: =HYPERLINK("https://docs.aws.amazon.com/service-authorization/latest/reference/" & $C27,"link") -> link | F27: =B27 & ":" & MID($H27,3,FIND(CHAR(34),$H27,3)-3) -> applicationinsights:AddWorkload | H27: =INDEX('AwsServices-Temp'!$C$2:$C$478,MATCH($A27,'AwsServices-Temp'!$B$2:$B$478,0)) -> ["AddWorkload","CreateApplication","CreateComponent","CreateLogPattern","DeleteApplication","DeleteComponent","DeleteLogPattern","DescribeApplication","DescribeComponent","DescribeComponentConfiguration","DescribeComponentConfigurationRecommendation","DescribeLogPattern","DescribeObservation","DescribeProblem","DescribeProblemObservations","DescribeWorkload","Link","ListApplications","ListComponents","ListConfigurationHistory","ListLogPatternSets","ListLogPatterns","ListProblems","ListTagsForResource","ListWorkloads","RemoveWorkload","TagResource","UntagResource","UpdateApplication","UpdateComponent","UpdateComponentConfiguration","UpdateLogPattern","UpdateProblem","UpdateWorkload"]
A28: Amazon CloudWatch Application Signals | B28: application-signals | C28: list_application-signals.html
A29: Amazon CloudWatch Application Signals MCP Server | B29: application-signals-mcp | C29: list_application-signals-mcp.html
A30: Amazon CloudWatch Evidently | B30: evidently | C30: list_evidently.html
A31: Amazon CloudWatch Internet Monitor | B31: internetmonitor | C31: list_internetmonitor.html
A32: Amazon CloudWatch Logs | B32: logs | C32: list_logs.html
A33: Amazon CloudWatch Network Synthetic Monitor | B33: networkmonitor | C33: list_networkmonitor.html
A34: Amazon CloudWatch Observability Access Manager | B34: oam | C34: list_oam.html
A35: Amazon CloudWatch Observability Admin Service | B35: observabilityadmin | C35: list_observabilityadmin.html
A36: Amazon CloudWatch Synthetics | B36: synthetics | C36: list_synthetics.html
A37: Amazon CodeCatalyst | B37: codecatalyst | C37: list_codecatalyst.html
A38: Amazon CodeGuru | B38: codeguru | C38: list_codeguru.html
A39: Amazon CodeGuru Profiler | B39: codeguru-profiler | C39: list_codeguruprofiler.html | D39: ="list_" & MID($C39,6,LEN($C39)-10) & "-action-" -> list_codeguruprofiler-action- | E39: =HYPERLINK("https://docs.aws.amazon.com/service-authorization/latest/reference/" & $C39,"link") -> link | F39: =B39 & ":" & MID($H39,3,FIND(CHAR(34),$H39,3)-3) -> codeguru-profiler:AddNotificationChannels | H39: =INDEX('AwsServices-Temp'!$C$2:$C$478,MATCH($A39,'AwsServices-Temp'!$B$2:$B$478,0)) -> ["AddNotificationChannels","BatchGetFrameMetricData","ConfigureAgent","CreateProfilingGroup","DeleteProfilingGroup","DescribeProfilingGroup","GetFindingsReportAccountSummary","GetNotificationConfiguration","GetPolicy","GetProfile","GetRecommendations","ListFindingsReports","ListProfileTimes","ListProfilingGroups","ListTagsForResource","PostAgentProfile","PutPermission","RemoveNotificationChannel","RemovePermission","SubmitFeedback","TagResource","UntagResource","UpdateProfilingGroup"]
A40: Amazon CodeGuru Reviewer | B40: codeguru-reviewer | C40: list_codeguru-reviewer.html
A41: Amazon CodeGuru Security | B41: codeguru-security | C41: list_codeguru-security.html
A42: Amazon CodeWhisperer | B42: codewhisperer | C42: list_codewhisperer.html
A43: Amazon Cognito Identity | B43: cognito-identity | C43: list_cognito-identity.html
A44: Amazon Cognito Sync | B44: cognito-sync | C44: list_cognito-sync.html
A45: Amazon Cognito User Pools | B45: cognito-idp | C45: list_cognito-idp.html
A46: Amazon Comprehend | B46: comprehend | C46: list_comprehend.html
A47: Amazon Comprehend Medical | B47: comprehendmedical | C47: list_comprehendmedical.html
A48: Amazon Connect | B48: connect | C48: list_connect.html | D48: ="list_" & MID($C48,6,LEN($C48)-10) & "-action-" -> list_connect-action- | E48: =HYPERLINK("https://docs.aws.amazon.com/service-authorization/latest/reference/" & $C48,"link") -> link | F48: =B48 & ":" & MID($H48,3,FIND(CHAR(34),$H48,3)-3) -> connect:ActivateEvaluationForm | G48: X | H48: =INDEX('AwsServices-Temp'!$C$2:$C$478,MATCH($A48,'AwsServices-Temp'!$B$2:$B$478,0)) -> ["ActivateEvaluationForm","AdminGetEmergencyAccessToken","AssociateAnalyticsDataSet","AssociateApprovedOrigin","AssociateBot","AssociateContactWithUser","AssociateCustomerProfilesDomain","AssociateDefaultVocabulary","AssociateEmailAddressAlias","AssociateFlow","AssociateInstanceStorageConfig","AssociateLambdaFunction","AssociateLexBot","AssociatePhoneNumberContactFlow","AssociateQueueEmailAddresses","AssociateQueueQuickConnects","AssociateRoutingProfileQueues","AssociateSecurityKey","AssociateSecurityProfiles","AssociateTrafficDistributionGroupUser","AssociateUserProficiencies","AssociateWorkspace","BatchAssociateAnalyticsDataSet","BatchCreateDataTableValue","BatchDeleteDataTableValue","BatchDescribeDataTableValue","BatchDisassociateAnalyticsDataSet","BatchGetAttachedFileMetadata","BatchGetFlowAssociation","BatchPutContact","BatchUpdateDataTableValue","ClaimPhoneNumber","CompleteAttachedFileUpload","CreateAgentStatus","CreateAttachedFile","CreateAuthenticationProfile","CreateContact","CreateContactFlow","CreateContactFlowModule","CreateContactFlowModuleAlias","CreateContactFlowModuleVersion","CreateContactFlowVersion","CreateDataTable","CreateDataTableAttribute","CreateEmailAddress","CreateEvaluationForm","CreateExtractionDefinition","CreateHoursOfOperation","CreateHoursOfOperationOverride","CreateInstance","CreateIntegrationAssociation","CreateMetric","CreateNotification","CreateParticipant","CreatePersistentContactAssociation","CreatePredefinedAttribute","CreatePrompt","CreatePushNotificationRegistration","CreateQueue","CreateQuickConnect","CreateRoutingProfile","CreateRule","CreateSecurityProfile","CreateTaskTemplate","CreateTrafficDistributionGroup","CreateUseCase","CreateUser","CreateUserHierarchyGroup","CreateView","CreateViewVersion","CreateVocabulary","CreateWorkspace","CreateWorkspacePage","DeactivateEvaluationForm","DeleteAttachedFile","DeleteContactEvaluation","DeleteContactFlow","DeleteContactFlowModule","DeleteContactFlowModuleAlias","DeleteContactFlowModuleVersion","DeleteContactFlowVersion","DeleteDataTable","DeleteDataTableAttribute","DeleteEmailAddress","DeleteEvaluationForm","DeleteExtractionDefinition","DeleteHoursOfOperation","DeleteHoursOfOperationOverride","DeleteInstance","DeleteIntegrationAssociation","DeleteMetric","DeleteNotification","DeletePredefinedAttribute","DeletePrompt","DeletePushNotificationRegistration","DeleteQueue","DeleteQuickConnect","DeleteRoutingProfile","DeleteRule","DeleteSecurityProfile","DeleteTaskTemplate","DeleteTrafficDistributionGroup","DeleteUseCase","DeleteUser","DeleteUserHierarchyGroup","DeleteView","DeleteViewVersion","DeleteVocabulary","DeleteWorkspace","DeleteWorkspaceMedia","DeleteWorkspacePage","DescribeAgentStatus","DescribeAttachedFilesConfiguration","DescribeAuthenticationProfile","DescribeContact","DescribeContactEvaluation","DescribeContactFlow","DescribeContactFlowModule","DescribeContactFlowModuleAlias","DescribeDataTable","DescribeDataTableAttribute","DescribeEmailAddress","DescribeEvaluationForm","DescribeExtractionDefinition","DescribeForecastingPlanningSchedulingIntegration","DescribeHoursOfOperation","DescribeHoursOfOperationOverride","DescribeInstance","DescribeInstanceAttribute","DescribeInstanceStorageConfig","DescribeMetric","DescribeNotification","DescribePhoneNumber","DescribePredefinedAttribute","DescribePrompt","DescribeQueue","DescribeQuickConnect","DescribeRoutingProfile","DescribeRule","DescribeSecurityProfile","DescribeTrafficDistributionGroup","DescribeUser","DescribeUserHierarchyGroup","DescribeUserHierarchyStructure","DescribeView","DescribeVocabulary","DescribeWorkspace","DisassociateAnalyticsDataSet","DisassociateApprovedOrigin","DisassociateBot","DisassociateCustomerProfilesDomain","DisassociateEmailAddressAlias","DisassociateFlow","DisassociateInstanceStorageConfig","DisassociateLambdaFunction","DisassociateLexBot","DisassociatePhoneNumberContactFlow","DisassociateQueueEmailAddresses","DisassociateQueueQuickConnects","DisassociateRoutingProfileQueues","DisassociateSecurityKey","DisassociateSecurityProfiles","DisassociateTrafficDistributionGroupUser","DisassociateUserProficiencies","DisassociateWorkspace","DismissUserContact","EvaluateDataTableValues","GetAttachedFile","GetContactAttributes","GetContactMetrics","GetCrossRegionRouting","GetCurrentMetricData","GetCurrentUserData","GetEffectiveHoursOfOperations","GetEvaluationFormValidation","GetFederationToken","GetFlowAssociation","GetMetricData","GetMetricDataV2","GetPromptFile","GetTaskTemplate","GetTrafficDistribution","ImportPhoneNumber","ImportWorkspaceMedia","ListAgentStatuses","ListAnalyticsDataAssociations","ListAnalyticsDataLakeDataSets","ListApprovedOrigins","ListAssociatedContacts","ListAttachedFilesConfigurations","ListAuthenticationProfiles","ListBots","ListContactEvaluations","ListContactFlowModuleAliases","ListContactFlowModuleVersions","ListContactFlowModules","ListContactFlowVersions","ListContactFlows","ListContactReferences","ListDataTableAttributes","ListDataTablePrimaryValues","ListDataTableValues","ListDataTables","ListDefaultVocabularies","ListEntitySecurityProfiles","ListEvaluationFormAIVersions","ListEvaluationFormVersions","ListEvaluationForms","ListExtractionDefinitions","ListFlowAssociations","ListHoursOfOperationOverrides","ListHoursOfOperations","ListInstanceAttributes","ListInstanceStorageConfigs","ListInstances","ListIntegrationAssociations","ListLambdaFunctions","ListLexBots","ListMetrics","ListNotifications","ListPhoneNumbers","ListPhoneNumbersV2","ListPredefinedAttributes","ListPrompts","ListQueueEmailAddresses","ListQueueQuickConnects","ListQueues","ListQuickConnects","ListRealtimeContactAnalysisSegments","ListRealtimeContactAnalysisSegmentsV2","ListRoutingProfileManualAssignmentQueues","ListRoutingProfileQueues","ListRoutingProfiles","ListRules","ListSecurityKeys","ListSecurityProfileAIAgents","ListSecurityProfileApplications","ListSecurityProfileFlowModules","ListSecurityProfilePermissions","ListSecurityProfiles","ListTagsForResource","ListTaskTemplates","ListTrafficDistributionGroupUsers","ListTrafficDistributionGroups","ListUseCases","ListUserHierarchyGroups","ListUserNotifications","ListUserProficiencies","ListUsers","ListViewVersions","ListViews","ListWorkspaceMedia","ListWorkspacePages","ListWorkspaces","MonitorContact","PauseContact","PutUserStatus","ReleasePhoneNumber","ReplicateInstance","ResumeContact","ResumeContactRecording","SearchAgentStatuses","SearchAvailablePhoneNumbers","SearchContactEvaluations","SearchContactFlowModules","SearchContactFlows","SearchContacts","SearchDataTables","SearchEmailAddresses","SearchEvaluationForms","SearchHoursOfOperationOverrides","SearchHoursOfOperations","SearchMetrics","SearchNotifications","SearchPredefinedAttributes","SearchPrompts","SearchQueues","SearchQuickConnects","SearchResourceTags","SearchRoutingProfiles","SearchRules","SearchSecurityProfiles","SearchUserHierarchyGroups","SearchUsers","SearchViews","SearchVocabularies","SearchWorkspaceAssociations","SearchWorkspaces","SendChatIntegrationEvent","SendIntegrationEvent","SendOutboundChatMessage","SendOutboundEmail","SendOutboundWebNotification","StartAttachedFileUpload","StartChatContact","StartContactConversationalAnalyticsJob","StartContactEvaluation","StartContactMediaProcessing","StartContactRecording","StartContactStreaming","StartEmailContact","StartEvaluationFormValidation","StartForecastingPlanningSchedulingIntegration","StartOutboundChatContact","StartOutboundEmailContact","StartOutboundVoiceContact","StartScreenSharing","StartTaskContact","StartWebRTCContact","StopContact","StopContactMediaProcessing","StopContactRecording","StopContactStreaming","StopForecastingPlanningSchedulingIntegration","SubmitContactEvaluation","SuspendContactRecording","TagContact","TagResource","TransferContact","UntagContact","UntagResource","UpdateAgentStatus","UpdateAttachedFilesConfiguration","UpdateAuthenticationProfile","UpdateContact","UpdateContactAttributes","UpdateContactEvaluation","UpdateContactFlowContent","UpdateContactFlowMetadata","UpdateContactFlowModuleAlias","UpdateContactFlowModuleContent","UpdateContactFlowModuleMetadata","UpdateContactFlowName","UpdateContactRoutingData","UpdateContactSchedule","UpdateCrossRegionRouting","UpdateDataTableAttribute","UpdateDataTableMetadata","UpdateDataTablePrimaryValues","UpdateEmailAddressMetadata","UpdateEvaluationForm","UpdateExtractionDefinition","UpdateHoursOfOperation","UpdateHoursOfOperationOverride","UpdateInstanceAttribute","UpdateInstanceStorageConfig","UpdateMetricContent","UpdateMetricMetadata","UpdateNotificationContent","UpdateParticipantAuthentication","UpdateParticipantRoleConfig","UpdatePhoneNumber","UpdatePhoneNumberMetadata","UpdatePredefinedAttribute","UpdatePrompt","UpdateQueueHoursOfOperation","UpdateQueueMaxContacts","UpdateQueueName","UpdateQueueOutboundCallerConfig","UpdateQueueOutboundEmailConfig","UpdateQueueStatus","UpdateQuickConnectConfig","UpdateQuickConnectName","UpdateRoutingProfileAgentAvailabilityTimer","UpdateRoutingProfileConcurrency","UpdateRoutingProfileDefaultOutboundQueue","UpdateRoutingProfileName","UpdateRoutingProfileQueues","UpdateRule","UpdateSecurityProfile","UpdateTaskTemplate","UpdateTrafficDistribution","UpdateUserHierarchy","UpdateUserHierarchyGroupName","UpdateUserHierarchyStructure","UpdateUserIdentityInfo","UpdateUserNotificationStatus","UpdateUserPhoneConfig","UpdateUserProficiencies","UpdateUserRoutingProfile","UpdateUserSecurityProfiles","UpdateViewContent","UpdateViewMetadata","UpdateWorkspaceMetadata","UpdateWorkspacePage","UpdateWorkspaceTheme","UpdateWorkspaceVisibility"]
A49: Amazon Connect Cases | B49: cases | C49: list_connectcases.html | D49: list_connectcases-action- | E49: =HYPERLINK("https://docs.aws.amazon.com/service-authorization/latest/reference/" & $C49,"link") -> link | H49: =INDEX('AwsServices-Temp'!$C$2:$C$478,MATCH($A49,'AwsServices-Temp'!$B$2:$B$478,0)) -> ["BatchGetCaseRule","BatchGetField","BatchPutFieldOptions","CreateCase","CreateCaseRule","CreateDomain","CreateField","CreateLayout","CreateRelatedItem","CreateTemplate","DeleteCase","DeleteCaseRule","DeleteDomain","DeleteField","DeleteLayout","DeleteRelatedItem","DeleteTemplate","GetCase","GetCaseAuditEvents","GetCaseEventConfiguration","GetDomain","GetLayout","GetTemplate","ListCaseRules","ListCasesForContact","ListDomains","ListFieldOptions","ListFields","ListLayouts","ListTagsForResource","ListTemplates","PutCaseEventConfiguration","SearchAllRelatedItems","SearchCases","SearchRelatedItems","TagResource","UntagResource","UpdateCase","UpdateCaseRule","UpdateField","UpdateLayout","UpdateRelatedItem","UpdateTemplate"]
A50: Amazon Connect Customer Profiles | B50: profile | C50: list_customer-profiles.html | D50: ="list_" & MID($C50,6,LEN($C50)-10) & "-action-" -> list_customer-profiles-action- | E50: =HYPERLINK("https://docs.aws.amazon.com/service-authorization/latest/reference/" & $C50,"link") -> link | F50: =B50 & ":" & MID($H50,3,FIND(CHAR(34),$H50,3)-3) -> profile:AddProfileKey | G50: X | H50: =INDEX('AwsServices-Temp'!$C$2:$C$478,MATCH($A50,'AwsServices-Temp'!$B$2:$B$478,0)) -> ["AddProfileKey","AssociateStreamForSegments","BatchGetCalculatedAttributeForProfile","BatchGetProfile","CreateCalculatedAttributeDefinition","CreateDomain","CreateDomainLayout","CreateEventStream","CreateEventTrigger","CreateIntegrationWorkflow","CreateProfile","CreateRecommender","CreateRecommenderFilter","CreateRecommenderSchema","CreateSegmentDefinition","CreateSegmentEstimate","CreateSegmentSnapshot","CreateSnapshot","CreateUploadJob","DeleteCalculatedAttributeDefinition","DeleteDomain","DeleteDomainLayout","DeleteDomainObjectType","DeleteEventStream","DeleteEventTrigger","DeleteIntegration","DeleteProfile","DeleteProfileKey","DeleteProfileObject","DeleteProfileObjectType","DeleteRecommender","DeleteRecommenderFilter","DeleteRecommenderSchema","DeleteSegmentDefinition","DeleteSegmentSubscription","DeleteWorkflow","DetectProfileObjectType","DisassociateStreamForSegments","GetAutoMergingPreview","GetCalculatedAttributeDefinition","GetCalculatedAttributeForProfile","GetDomain","GetDomainLayout","GetDomainObjectType","GetEventStream","GetEventTrigger","GetIdentityResolutionJob","GetIntegration","GetMatches","GetObjectTypeAttributeStatistics","GetProfileHistoryRecord","GetProfileInsights","GetProfileObjectType","GetProfileObjectTypeTemplate","GetProfileRecommendations","GetRecommender","GetRecommenderFilter","GetRecommenderSchema","GetSegmentDefinition","GetSegmentEstimate","GetSegmentMembership","GetSegmentSnapshot","GetSegmentSubscription","GetSimilarProfiles","GetSnapshot","GetStreamForSegments","GetUploadJob","GetUploadJobPath","GetWorkflow","GetWorkflowSteps","ListAccountIntegrations","ListCalculatedAttributeDefinitions","ListCalculatedAttributesForProfile","ListDomainLayouts","ListDomainObjectTypes","ListDomainObjects","ListDomains","ListEventStreams","ListEventTriggers","ListIdentityResolutionJobs","ListIntegrations","ListObjectTypeAttributeValues","ListObjectTypeAttributes","ListProfileAttributeValues","ListProfileHistoryRecords","ListProfileObjectTypeTemplates","ListProfileObjectTypes","ListProfileObjects","ListRecommenderFilters","ListRecommenderRecipes","ListRecommenderSchemas","ListRecommenders","ListRuleBasedMatches","ListSegmentDefinitions","ListSegmentSubscriptionEvents","ListTagsForResource","ListUploadJobs","ListWorkflows","MergeProfiles","PutDomainObjectType","PutIntegration","PutProfileObject","PutProfileObjectType","PutSegmentSubscription","SearchProfiles","StartRecommender","StartUploadJob","StopRecommender","StopUploadJob","TagResource","UntagResource","UpdateCalculatedAttributeDefinition","UpdateDomain","UpdateDomainLayout","UpdateEventTrigger","UpdateProfile","UpdateRecommender"]
A51: Amazon Connect Health | B51: health-agent | C51: list_connecthealth.html | D51: ="list_" & MID($C51,6,LEN($C51)-10) & "-action-" -> list_connecthealth-action- | E51: =HYPERLINK("https://docs.aws.amazon.com/service-authorization/latest/reference/" & $C51,"link") -> link | F51: =B51 & ":" & MID($H51,3,FIND(CHAR(34),$H51,3)-3) -> health-agent:ActivateSubscription | G51: X | H51: =INDEX('AwsServices-Temp'!$C$2:$C$478,MATCH($A51,'AwsServices-Temp'!$B$2:$B$478,0)) -> ["ActivateSubscription","CancelAppointment","CreateAgent","CreateDomain","CreateIntegration","CreateSession","CreateSubscription","DeactivateSubscription","DeleteAgent","DeleteDomain","DeleteIntegration","GetAgent","GetCareTeamProvider","GetDomain","GetDomainAnalytics","GetIntegration","GetMedicalScribeListeningSession","GetPatient","GetPatientInsightsJob","GetPractitioner","GetSessionContext","GetSubscription","InvokeAgent","ListAgents","ListAppointmentSlots","ListDomains","ListIntegrations","ListPatientAppointments","ListPatientInsuranceCoverages","ListPatientMedications","ListProviders","ListSessionRecords","ListSubscriptions","ListTagsForResource","MatchPatient","PublishAgent","RescheduleAppointment","ResetPassword","ScheduleAppointment","StartMedicalScribeListeningSession","StartPatientInsightsJob","SubmitMedicationRenewal","TagResource","UntagResource","UpdateAgent","UpdateIntegration","UpdateSession"]
A52: Amazon Connect Outbound Campaigns | B52: connect-campaigns | C52: list_connect-outbound-campaigns.html | D52: ="list_" & MID($C52,6,LEN($C52)-10) & "-action-" -> list_connect-outbound-campaigns-action- | E52: =HYPERLINK("https://docs.aws.amazon.com/service-authorization/latest/reference/" & $C52,"link") -> link | F52: =B52 & ":" & MID($H52,3,FIND(CHAR(34),$H52,3)-3) -> connect-campaigns:CreateCampaign | G52: X | H52: =INDEX('AwsServices-Temp'!$C$2:$C$478,MATCH($A52,'AwsServices-Temp'!$B$2:$B$478,0)) -> ["CreateCampaign","DeleteCampaign","DeleteCampaignChannelSubtypeConfig","DeleteCampaignCommunicationLimits","DeleteCampaignCommunicationTime","DeleteCampaignEntryLimits","DeleteConnectInstanceConfig","DeleteConnectInstanceIntegration","DeleteInstanceOnboardingJob","DescribeCampaign","GetCampaignState","GetCampaignStateBatch","GetConnectInstanceConfig","GetInstanceCommunicationLimits","GetInstanceOnboardingJobStatus","ListCampaigns","ListConnectInstanceIntegrations","ListTagsForResource","PauseCampaign","PutConnectInstanceIntegration","PutDialRequestBatch","PutInstanceCommunicationLimits","PutOutboundRequestBatch","PutProfileOutboundRequestBatch","ResumeCampaign","StartCampaign","StartInstanceOnboardingJob","StopCampaign","TagResource","UntagResource","UpdateCampaignChannelSubtypeConfig","UpdateCampaignCommunicationLimits","UpdateCampaignCommunicationTime","UpdateCampaignDialerConfig","UpdateCampaignEntryLimits","UpdateCampaignFlowAssociation","UpdateCampaignName","UpdateCampaignOutboundCallConfig","UpdateCampaignSchedule","UpdateCampaignSource"]
A53: Amazon Connect Voice ID | B53: voiceid | C53: list_voice-id.html | D53: ="list_" & MID($C53,6,LEN($C53)-10) & "-action-" -> list_voice-id-action- | E53: =HYPERLINK("https://docs.aws.amazon.com/service-authorization/latest/reference/" & $C53,"link") -> link | F53: =B53 & ":" & MID($H53,3,FIND(CHAR(34),$H53,3)-3) -> voiceid:AssociateFraudster | H53: =INDEX('AwsServices-Temp'!$C$2:$C$478,MATCH($A53,'AwsServices-Temp'!$B$2:$B$478,0)) -> ["AssociateFraudster","CreateDomain","CreateWatchlist","DeleteDomain","DeleteFraudster","DeleteSpeaker","DeleteWatchlist","DescribeComplianceConsent","DescribeDomain","DescribeFraudster","DescribeFraudsterRegistrationJob","DescribeSpeaker","DescribeSpeakerEnrollmentJob","DescribeWatchlist","DisassociateFraudster","EvaluateSession","ListDomains","ListFraudsterRegistrationJobs","ListFraudsters","ListSpeakerEnrollmentJobs","ListSpeakers","ListTagsForResource","ListWatchlists","OptOutSpeaker","RegisterComplianceConsent","StartFraudsterRegistrationJob","StartSpeakerEnrollmentJob","TagResource","UntagResource","UpdateDomain","UpdateWatchlist"]
A54: Amazon Data Lifecycle Manager | B54: dlm | C54: list_dlm.html
A55: Amazon DataZone | B55: datazone | C55: list_datazone.html
A56: Amazon Detective | B56: detective | C56: list_detective.html
A57: Amazon DevOps Guru | B57: devops-guru | C57: list_devops-guru.html
A58: Amazon DocumentDB Elastic Clusters | B58: docdb-elastic | C58: list_docdb-elastic.html
A59: Amazon DynamoDB | B59: dynamodb | C59: list_dynamodb.html
A60: Amazon DynamoDB Accelerator (DAX) | B60: dax | C60: list_dax.html
A61: Amazon EC2 | B61: ec2 | C61: list_ec2.html | D61: ="list_" & MID($C61,6,LEN($C61)-10) & "-action-" -> list_ec2-action- | E61: =HYPERLINK("https://docs.aws.amazon.com/service-authorization/latest/reference/" & $C61,"link") -> link | F61: =B61 & ":" & MID($H61,3,FIND(CHAR(34),$H61,3)-3) -> ec2:AcceptAddressTransfer | H61: =INDEX('AwsServices-Temp'!$C$2:$C$478,MATCH($A61,'AwsServices-Temp'!$B$2:$B$478,0)) -> ["AcceptAddressTransfer","AcceptCapacityReservationBillingOwnership","AcceptReservedInstancesExchangeQuote","AcceptTransitGatewayClientVpnAttachment","AcceptTransitGatewayMulticastDomainAssociations","AcceptTransitGatewayPeeringAttachment","AcceptTransitGatewayVpcAttachment","AcceptVpcEndpointConnections","AcceptVpcPeeringConnection","AdvertiseByoipCidr","AllocateAddress","AllocateHosts","AllocateIpamPoolCidr","ApplySecurityGroupsToClientVpnTargetNetwork","AssignIpv6Addresses","AssignPrivateIpAddresses","AssignPrivateNatGatewayAddress","AssociateAddress","AssociateApplicationStatusCheck","AssociateCapacityReservationBillingOwner","AssociateClientVpnTargetNetwork","AssociateDhcpOptions","AssociateEnclaveCertificateIamRole","AssociateIamInstanceProfile","AssociateInstanceEventWindow","AssociateIpamByoasn","AssociateIpamResourceDiscovery","AssociateNatGatewayAddress","AssociateRouteServer","AssociateRouteTable","AssociateSecurityGroupVpc","AssociateSubnetCidrBlock","AssociateTransitGatewayMulticastDomain","AssociateTransitGatewayPolicyTable","AssociateTransitGatewayRouteTable","AssociateTrunkInterface","AssociateVerifiedAccessInstanceWebAcl","AssociateVpcCidrBlock","AttachApplianceToNatGateway","AttachClassicLinkVpc","AttachImageWatermark","AttachInternetGateway","AttachNetworkInterface","AttachResourcesToPlacementGroup","AttachVerifiedAccessTrustProvider","AttachVolume","AttachVpnGateway","AuthorizeClientVpnIngress","AuthorizeSecurityGroupEgress","AuthorizeSecurityGroupIngress","BatchModifyIpamRoutingPolicyRegistrations","BundleInstance","CancelBundleTask","CancelCapacityReservation","CancelCapacityReservationFleets","CancelConversionTask","CancelDeclarativePoliciesReport","CancelExportTask","CancelImageLaunchPermission","CancelImportTask","CancelReservedInstancesListing","CancelSpotFleetRequests","CancelSpotInstanceRequests","ConfirmProductInstance","CopyFpgaImage","CopyImage","CopySnapshot","CopyVolumes","CreateApplicationStatusCheck","CreateCapacityManagerDataExport","CreateCapacityReservation","CreateCapacityReservationBySplitting","CreateCapacityReservationCancellationQuote","CreateCapacityReservationFleet","CreateCarrierGateway","CreateClientVpnEndpoint","CreateClientVpnRoute","CreateCoipCidr","CreateCoipPool","CreateCoipPoolPermission","CreateCustomerGateway","CreateDefaultSubnet","CreateDefaultVpc","CreateDelegateMacVolumeOwnershipTask","CreateDhcpOptions","CreateEgressOnlyInternetGateway","CreateFleet","CreateFlowLogs","CreateFpgaImage","CreateImage","CreateImageUsageReport","CreateInstanceConnectEndpoint","CreateInstanceEventWindow","CreateInstanceExportTask","CreateInternetGateway","CreateInterruptibleCapacityReservationAllocation","CreateIpam","CreateIpamExternalResourceVerificationToken","CreateIpamInternetRegistryAssociation","CreateIpamPolicy","CreateIpamPool","CreateIpamPrefixListResolver","CreateIpamPrefixListResolverTarget","CreateIpamResourceDiscovery","CreateIpamRoutingPolicyRegistration","CreateIpamScope","CreateKeyPair","CreateLaunchTemplate","CreateLaunchTemplateVersion","CreateLocalGatewayRoute","CreateLocalGatewayRouteTable","CreateLocalGatewayRouteTablePermission","CreateLocalGatewayRouteTableVirtualInterfaceGroupAssociation","CreateLocalGatewayRouteTableVpcAssociation","CreateLocalGatewayVirtualInterface","CreateLocalGatewayVirtualInterfaceGroup","CreateMacSystemIntegrityProtectionModificationTask","CreateManagedPrefixList","CreateNatGateway","CreateNetworkAcl","CreateNetworkAclEntry","CreateNetworkInsightsAccessScope","CreateNetworkInsightsPath","CreateNetworkInterface","CreateNetworkInterfacePermission","CreateOdbNetworkPeering","CreatePlacementGroup","CreatePublicIpv4Pool","CreateReplaceRootVolumeTask","CreateReservedInstancesListing","CreateRestoreImageTask","CreateRoute","CreateRouteServer","CreateRouteServerEndpoint","CreateRouteServerPeer","CreateRouteTable","CreateSecondaryNetwork","CreateSecondarySubnet","CreateSecurityGroup","CreateSnapshot","CreateSnapshots","CreateSpotDatafeedSubscription","CreateStoreImageTask","CreateSubnet","CreateSubnetCidrReservation","CreateTags","CreateTrafficMirrorFilter","CreateTrafficMirrorFilterRule","CreateTrafficMirrorSession","CreateTrafficMirrorTarget","CreateTransitGateway","CreateTransitGatewayConnect","CreateTransitGatewayConnectPeer","CreateTransitGatewayMeteringPolicy","CreateTransitGatewayMeteringPolicyEntry","CreateTransitGatewayMulticastDomain","CreateTransitGatewayPeeringAttachment","CreateTransitGatewayPolicyTable","CreateTransitGatewayPolicyTableEntry","CreateTransitGatewayPrefixListReference","CreateTransitGatewayRoute","CreateTransitGatewayRouteTable","CreateTransitGatewayRouteTableAnnouncement","CreateTransitGatewayVpcAttachment","CreateVerifiedAccessEndpoint","CreateVerifiedAccessGroup","CreateVerifiedAccessInstance","CreateVerifiedAccessTrustProvider","CreateVolume","CreateVpc","CreateVpcBlockPublicAccessExclusion","CreateVpcEncryptionControl","CreateVpcEndpoint","CreateVpcEndpointConnectionNotification","CreateVpcEndpointServiceConfiguration","CreateVpcPeeringConnection","CreateVpnConcentrator","CreateVpnConnection","CreateVpnConnectionRoute","CreateVpnGateway","DeleteApplicationStatusCheck","DeleteCapacityManagerDataExport","DeleteCarrierGateway","DeleteClientVpnEndpoint","DeleteClientVpnRoute","DeleteCoipCidr","DeleteCoipPool","DeleteCoipPoolPermission","DeleteCustomerGateway","DeleteDhcpOptions","DeleteEgressOnlyInternetGateway","DeleteFleets","DeleteFlowLogs","DeleteFpgaImage","DeleteImageUsageReport","DeleteInstanceConnectEndpoint","DeleteInstanceEventWindow","DeleteInternetGateway","DeleteIpam","DeleteIpamExternalResourceVerificationToken","DeleteIpamInternetRegistryAssociation","DeleteIpamPolicy","DeleteIpamPool","DeleteIpamPrefixListResolver","DeleteIpamPrefixListResolverTarget","DeleteIpamResourceDiscovery","DeleteIpamRoutingPolicyRegistration","DeleteIpamScope","DeleteKeyPair","DeleteLaunchTemplate","DeleteLaunchTemplateVersions","DeleteLocalGatewayRoute","DeleteLocalGatewayRouteTable","DeleteLocalGatewayRouteTablePermission","DeleteLocalGatewayRouteTableVirtualInterfaceGroupAssociation","DeleteLocalGatewayRouteTableVpcAssociation","DeleteLocalGatewayVirtualInterface","DeleteLocalGatewayVirtualInterfaceGroup","DeleteManagedPrefixList","DeleteNatGateway","DeleteNetworkAcl","DeleteNetworkAclEntry","DeleteNetworkInsightsAccessScope","DeleteNetworkInsightsAccessScopeAnalysis","DeleteNetworkInsightsAnalysis","DeleteNetworkInsightsPath","DeleteNetworkInterface","DeleteNetworkInterfacePermission","DeleteOdbNetworkPeering","DeletePlacementGroup","DeletePublicIpv4Pool","DeleteQueuedReservedInstances","DeleteResourcePolicy","DeleteRoute","DeleteRouteServer","DeleteRouteServerEndpoint","DeleteRouteServerPeer","DeleteRouteTable","DeleteSecondaryNetwork","DeleteSecondarySubnet","DeleteSecurityGroup","DeleteSnapshot","DeleteSpotDatafeedSubscription","DeleteSubnet","DeleteSubnetCidrReservation","DeleteTags","DeleteTrafficMirrorFilter","DeleteTrafficMirrorFilterRule","DeleteTrafficMirrorSession","DeleteTrafficMirrorTarget","DeleteTransitGateway","DeleteTransitGatewayClientVpnAttachment","DeleteTransitGatewayConnect","DeleteTransitGatewayConnectPeer","DeleteTransitGatewayMeteringPolicy","DeleteTransitGatewayMeteringPolicyEntry","DeleteTransitGatewayMulticastDomain","DeleteTransitGatewayPeeringAttachment","DeleteTransitGatewayPolicyTable","DeleteTransitGatewayPolicyTableEntry","DeleteTransitGatewayPrefixListReference","DeleteTransitGatewayRoute","DeleteTransitGatewayRouteTable","DeleteTransitGatewayRouteTableAnnouncement","DeleteTransitGatewayVpcAttachment","DeleteVerifiedAccessEndpoint","DeleteVerifiedAccessGroup","DeleteVerifiedAccessInstance","DeleteVerifiedAccessTrustProvider","DeleteVolume","DeleteVpc","DeleteVpcBlockPublicAccessExclusion","DeleteVpcEncryptionControl","DeleteVpcEndpointConnectionNotifications","DeleteVpcEndpointServiceConfigurations","DeleteVpcEndpoints","DeleteVpcPeeringConnection","DeleteVpnConcentrator","DeleteVpnConnection","DeleteVpnConnectionRoute","DeleteVpnGateway","DeprovisionByoipCidr","DeprovisionIpamByoasn","DeprovisionIpamPoolCidr","DeprovisionPublicIpv4PoolCidr","DeregisterImage","DeregisterInstanceEventNotificationAttributes","DeregisterTransitGatewayMulticastGroupMembers","DeregisterTransitGatewayMulticastGroupSources","DescribeAccountAttributes","DescribeAccountVpcEncryptionControl","DescribeAddressTransfers","DescribeAddresses","DescribeAddressesAttribute","DescribeAggregateIdFormat","DescribeApplicationStatus","DescribeApplicationStatusCheckAssociations","DescribeApplicationStatusChecks","DescribeAvailabilityZones","DescribeAwsNetworkPerformanceMetricSubscriptions","DescribeBundleTasks","DescribeByoipCidrs","DescribeCapacityBlockExtensionHistory","DescribeCapacityBlockExtensionOfferings","DescribeCapacityBlockOfferings","DescribeCapacityBlockStatus","DescribeCapacityBlocks","DescribeCapacityManagerDataExports","DescribeCapacityReservationBillingRequests","DescribeCapacityReservationCancellationQuotes","DescribeCapacityReservationFleets","DescribeCapacityReservationTopology","DescribeCapacityReservations","DescribeCarrierGateways","DescribeClassicLinkInstances","DescribeClientVpnAuthorizationRules","DescribeClientVpnConnections","DescribeClientVpnEndpoints","DescribeClientVpnRoutes","DescribeClientVpnTargetNetworks","DescribeCoipPools","DescribeConversionTasks","DescribeCustomerGateways","DescribeDeclarativePoliciesReports","DescribeDhcpOptions","DescribeEgressOnlyInternetGateways","DescribeElasticGpus","DescribeExportImageTasks","DescribeExportTasks","DescribeFastLaunchImages","DescribeFastSnapshotRestores","DescribeFleetHistory","DescribeFleetInstances","DescribeFleets","DescribeFlowLogs","DescribeFpgaImageAttribute","DescribeFpgaImages","DescribeHostReservationOfferings","DescribeHostReservations","DescribeHosts","DescribeIamInstanceProfileAssociations","DescribeIdFormat","DescribeIdentityIdFormat","DescribeImageAttribute","DescribeImageReferences","DescribeImageUsageReportEntries","DescribeImageUsageReports","DescribeImages","DescribeImportImageTasks","DescribeImportSnapshotTasks","DescribeInstanceAttribute","DescribeInstanceConnectEndpoints","DescribeInstanceCreditSpecifications","DescribeInstanceEventNotificationAttributes","DescribeInstanceEventWindows","DescribeInstanceImageMetadata","DescribeInstanceSqlHaHistoryStates","DescribeInstanceSqlHaStates","DescribeInstanceStatus","DescribeInstanceTopology","DescribeInstanceTypeOfferings","DescribeInstanceTypes","DescribeInstances","DescribeInternetGateways","DescribeIpamByoasn","DescribeIpamExternalResourceVerificationTokens","DescribeIpamInternetRegistryAssociations","DescribeIpamPolicies","DescribeIpamPoolAllocations","DescribeIpamPools","DescribeIpamPrefixListResolverTargets","DescribeIpamPrefixListResolvers","DescribeIpamResourceDiscoveries","DescribeIpamResourceDiscoveryAssociations","DescribeIpamScopes","DescribeIpams","DescribeIpv6Pools","DescribeKeyPairs","DescribeLaunchTemplateVersions","DescribeLaunchTemplates","DescribeLocalGatewayRouteTablePermissions","DescribeLocalGatewayRouteTableVirtualInterfaceGroupAssociations","DescribeLocalGatewayRouteTableVpcAssociations","DescribeLocalGatewayRouteTables","DescribeLocalGatewayVirtualInterfaceGroups","DescribeLocalGatewayVirtualInterfaces","DescribeLocalGateways","DescribeLockedSnapshots","DescribeMacHosts","DescribeMacModificationTasks","DescribeManagedPrefixLists","DescribeMovingAddresses","DescribeNatGateways","DescribeNetworkAcls","DescribeNetworkInsightsAccessScopeAnalyses","DescribeNetworkInsightsAccessScopes","DescribeNetworkInsightsAnalyses","DescribeNetworkInsightsPaths","DescribeNetworkInterfaceAttribute","DescribeNetworkInterfacePermissions","DescribeNetworkInterfaces","DescribeOutpostLags","DescribePlacementGroups","DescribePrefixLists","DescribePrincipalIdFormat","DescribePublicIpv4Pools","DescribeRegions","DescribeReplaceRootVolumeTasks","DescribeReservedInstances","DescribeReservedInstancesListings","DescribeReservedInstancesModifications","DescribeReservedInstancesOfferings","DescribeRouteServerEndpoints","DescribeRouteServerPeers","DescribeRouteServers","DescribeRouteTables","DescribeScheduledInstanceAvailability","DescribeScheduledInstances","DescribeSecondaryInterfaces","DescribeSecondaryNetworks","DescribeSecondarySubnets","DescribeSecurityGroupReferences","DescribeSecurityGroupRules","DescribeSecurityGroupVpcAssociations","DescribeSecurityGroups","DescribeServiceLinkVirtualInterfaces","DescribeSnapshotAttribute","DescribeSnapshotTierStatus","DescribeSnapshots","DescribeSpotDatafeedSubscription","DescribeSpotFleetInstances","DescribeSpotFleetRequestHistory","DescribeSpotFleetRequests","DescribeSpotInstanceRequests","DescribeSpotPriceHistory","DescribeStaleSecurityGroups","DescribeStoreImageTasks","DescribeSubnets","DescribeTags","DescribeTrafficMirrorFilterRules","DescribeTrafficMirrorFilters","DescribeTrafficMirrorSessions","DescribeTrafficMirrorTargets","DescribeTransitGatewayAttachments","DescribeTransitGatewayConnectPeers","DescribeTransitGatewayConnects","DescribeTransitGatewayMeteringPolicies","DescribeTransitGatewayMulticastDomains","DescribeTransitGatewayPeeringAttachments","DescribeTransitGatewayPolicyTables","DescribeTransitGatewayRouteTableAnnouncements","DescribeTransitGatewayRouteTables","DescribeTransitGatewayVpcAttachments","DescribeTransitGateways","DescribeTrunkInterfaceAssociations","DescribeVerifiedAccessEndpoints","DescribeVerifiedAccessGroups","DescribeVerifiedAccessInstanceLoggingConfigurations","DescribeVerifiedAccessInstanceWebAclAssociations","DescribeVerifiedAccessInstances","DescribeVerifiedAccessTrustProviders","DescribeVolumeAttribute","DescribeVolumeStatus","DescribeVolumes","DescribeVolumesModifications","DescribeVpcAttribute","DescribeVpcBlockPublicAccessExclusions","DescribeVpcBlockPublicAccessOptions","DescribeVpcClassicLink","DescribeVpcClassicLinkDnsSupport","DescribeVpcEncryptionControls","DescribeVpcEndpointAssociations","DescribeVpcEndpointConnectionNotifications","DescribeVpcEndpointConnections","DescribeVpcEndpointServiceConfigurations","DescribeVpcEndpointServicePermissions","DescribeVpcEndpointServices","DescribeVpcEndpoints","DescribeVpcPeeringConnections","DescribeVpcs","DescribeVpnConcentrators","DescribeVpnConnections","DescribeVpnGateways","DetachApplianceFromNatGateway","DetachClassicLinkVpc","DetachImageWatermark","DetachInternetGateway","DetachNetworkInterface","DetachResourcesFromPlacementGroup","DetachVerifiedAccessTrustProvider","DetachVolume","DetachVpnGateway","DisableAddressTransfer","DisableAllowedImagesSettings","DisableApplicationStatusCheckSuppression","DisableAwsNetworkPerformanceMetricSubscription","DisableCapacityManager","DisableEbsEncryptionByDefault","DisableFastLaunch","DisableFastSnapshotRestores","DisableImage","DisableImageBlockPublicAccess","DisableImageDeprecation","DisableImageDeregistrationProtection","DisableInstanceSqlHaStandbyDetections","DisableIpamOrganizationAdminAccount","DisableIpamPolicy","DisableRouteServerPropagation","DisableSerialConsoleAccess","DisableSnapshotBlockPublicAccess","DisableTransitGatewayRouteTablePropagation","DisableVgwRoutePropagation","DisableVpcClassicLink","DisableVpcClassicLinkDnsSupport","DisassociateAddress","DisassociateApplicationStatusCheck","DisassociateCapacityReservationBillingOwner","DisassociateClientVpnTargetNetwork","DisassociateEnclaveCertificateIamRole","DisassociateIamInstanceProfile","DisassociateInstanceEventWindow","DisassociateIpamByoasn","DisassociateIpamResourceDiscovery","DisassociateNatGatewayAddress","DisassociateRouteServer","DisassociateRouteTable","DisassociateSecurityGroupVpc","DisassociateSubnetCidrBlock","DisassociateTransitGatewayMulticastDomain","DisassociateTransitGatewayPolicyTable","DisassociateTransitGatewayRouteTable","DisassociateTrunkInterface","DisassociateVerifiedAccessInstanceWebAcl","DisassociateVpcCidrBlock","EnableAddressTransfer","EnableAllowedImagesSettings","EnableApplicationStatusCheckSuppression","EnableAwsNetworkPerformanceMetricSubscription","EnableCapacityManager","EnableEbsEncryptionByDefault","EnableFastLaunch","EnableFastSnapshotRestores","EnableImage","EnableImageBlockPublicAccess","EnableImageDeprecation","EnableImageDeregistrationProtection","EnableInstanceSqlHaStandbyDetections","EnableIpamInternetRegistryAssociation","EnableIpamOrganizationAdminAccount","EnableIpamPolicy","EnableReachabilityAnalyzerOrganizationSharing","EnableRouteServerPropagation","EnableSerialConsoleAccess","EnableSnapshotBlockPublicAccess","EnableTransitGatewayRouteTablePropagation","EnableVgwRoutePropagation","EnableVolumeIO","EnableVpcClassicLink","EnableVpcClassicLinkDnsSupport","ExportClientVpnClientCertificateRevocationList","ExportClientVpnClientConfiguration","ExportImage","ExportTransitGatewayRoutes","ExportVerifiedAccessInstanceClientConfiguration","GetActiveVpnTunnelStatus","GetAllowedImagesSettings","GetAssociatedEnclaveCertificateIamRoles","GetAssociatedIpv6PoolCidrs","GetAwsNetworkPerformanceData","GetCapacityManagerAttributes","GetCapacityManagerMetricData","GetCapacityManagerMetricDimensions","GetCapacityManagerMonitoredTagKeys","GetCapacityReservationUsage","GetCoipPoolUsage","GetConsoleOutput","GetConsoleScreenshot","GetDeclarativePoliciesReportSummary","GetDefaultCreditSpecification","GetEbsDefaultKmsKeyId","GetEbsEncryptionByDefault","GetEnabledIpamPolicy","GetFlowLogsIntegrationTemplate","GetGroupsForCapacityReservation","GetHostReservationPurchasePreview","GetImageAncestry","GetImageBlockPublicAccessState","GetInstanceMetadataDefaults","GetInstanceTpmEkPub","GetInstanceTypesFromInstanceRequirements","GetInstanceUefiData","GetIpamAddressHistory","GetIpamDiscoveredAccounts","GetIpamDiscoveredPublicAddresses","GetIpamDiscoveredResourceCidrs","GetIpamDiscoveredRoutes","GetIpamInternetRegistryAssociationAsns","GetIpamInternetRegistryAssociationCidrs","GetIpamPolicyAllocationRules","GetIpamPolicyOrganizationTargets","GetIpamPoolAllocations","GetIpamPoolCidrs","GetIpamPrefixListResolverRules","GetIpamPrefixListResolverVersionEntries","GetIpamPrefixListResolverVersions","GetIpamResourceCidrs","GetIpamRouteOriginAuthorizations","GetIpamRouteProtectionFindings","GetIpamRoutingPolicyRegistrationDeltas","GetIpamRoutingPolicyRegistrations","GetLaunchTemplateData","GetManagedPrefixListAssociations","GetManagedPrefixListEntries","GetManagedResourceVisibility","GetNetworkInsightsAccessScopeAnalysisFindings","GetNetworkInsightsAccessScopeContent","GetPasswordData","GetReservedInstancesExchangeQuote","GetResourcePolicy","GetRouteServerAssociations","GetRouteServerPropagations","GetRouteServerRoutingDatabase","GetSecurityGroupsForVpc","GetSerialConsoleAccessStatus","GetSnapshotBlockPublicAccessState","GetSpotPlacementScores","GetSubnetCidrReservations","GetTransitGatewayAttachmentPropagations","GetTransitGatewayMeteringPolicyEntries","GetTransitGatewayMulticastDomainAssociations","GetTransitGatewayPolicyTableAssociations","GetTransitGatewayPolicyTableEntries","GetTransitGatewayPrefixListReferences","GetTransitGatewayRouteTableAssociations","GetTransitGatewayRouteTablePropagations","GetVerifiedAccessEndpointPolicy","GetVerifiedAccessEndpointTargets","GetVerifiedAccessGroupPolicy","GetVerifiedAccessInstanceWebAcl","GetVpcResourcesBlockingEncryptionEnforcement","GetVpnConnectionDeviceSampleConfiguration","GetVpnConnectionDeviceTypes","GetVpnTunnelReplacementStatus","ImportByoipCidrToIpam","ImportClientVpnClientCertificateRevocationList","ImportImage","ImportInstance","ImportKeyPair","ImportSnapshot","ImportVolume","InjectApiError","InjectVolumeIOLatency","ListImagesInRecycleBin","ListSnapshotsInRecycleBin","ListVolumesInRecycleBin","LockSnapshot","ModifyAccountVpcEncryptionControl","ModifyAddressAttribute","ModifyApplicationStatusCheck","ModifyAvailabilityZoneGroup","ModifyCapacityReservation","ModifyCapacityReservationFleet","ModifyClientVpnEndpoint","ModifyDefaultCreditSpecification","ModifyEbsDefaultKmsKeyId","ModifyFleet","ModifyFpgaImageAttribute","ModifyHosts","ModifyIdFormat","ModifyIdentityIdFormat","ModifyImageAttribute","ModifyInstanceAttribute","ModifyInstanceCapacityReservationAttributes","ModifyInstanceConnectEndpoint","ModifyInstanceCpuOptions","ModifyInstanceCreditSpecification","ModifyInstanceEventStartTime","ModifyInstanceEventWindow","ModifyInstanceMaintenanceOptions","ModifyInstanceMetadataDefaults","ModifyInstanceMetadataOptions","ModifyInstanceNetworkPerformanceOptions","ModifyInstancePlacement","ModifyIpam","ModifyIpamPolicyAllocationRules","ModifyIpamPool","ModifyIpamPoolAllocation","ModifyIpamPrefixListResolver","ModifyIpamPrefixListResolverTarget","ModifyIpamResourceCidr","ModifyIpamResourceDiscovery","ModifyIpamRoutingPolicyRegistration","ModifyIpamScope","ModifyLaunchTemplate","ModifyLocalGatewayRoute","ModifyManagedPrefixList","ModifyManagedResourceVisibility","ModifyNetworkInterfaceAttribute","ModifyOdbNetworkPeering","ModifyPrivateDnsNameOptions","ModifyPublicIpDnsNameOptions","ModifyReservedInstances","ModifyRouteServer","ModifySecurityGroupRules","ModifySnapshotAttribute","ModifySnapshotTier","ModifySpotFleetRequest","ModifySubnetAttribute","ModifyTrafficMirrorFilterNetworkServices","ModifyTrafficMirrorFilterRule","ModifyTrafficMirrorSession","ModifyTransitGateway","ModifyTransitGatewayMeteringPolicy","ModifyTransitGatewayPolicyTableEntry","ModifyTransitGatewayPrefixListReference","ModifyTransitGatewayVpcAttachment","ModifyVerifiedAccessEndpoint","ModifyVerifiedAccessEndpointPolicy","ModifyVerifiedAccessGroup","ModifyVerifiedAccessGroupPolicy","ModifyVerifiedAccessInstance","ModifyVerifiedAccessInstanceLoggingConfiguration","ModifyVerifiedAccessTrustProvider","ModifyVolume","ModifyVolumeAttribute","ModifyVpcAttribute","ModifyVpcBlockPublicAccessExclusion","ModifyVpcBlockPublicAccessOptions","ModifyVpcEncryptionControl","ModifyVpcEndpoint","ModifyVpcEndpointConnectionNotification","ModifyVpcEndpointPayerResponsibility","ModifyVpcEndpointServiceConfiguration","ModifyVpcEndpointServicePayerResponsibility","ModifyVpcEndpointServicePermissions","ModifyVpcPeeringConnectionOptions","ModifyVpcTenancy","ModifyVpnConnection","ModifyVpnConnectionOptions","ModifyVpnTunnelCertificate","ModifyVpnTunnelOptions","MonitorInstances","MoveAddressToVpc","MoveByoipCidrToIpam","MoveCapacityReservationInstances","PauseVolumeIO","ProvisionByoipCidr","ProvisionIpamByoasn","ProvisionIpamPoolCidr","ProvisionPublicIpv4PoolCidr","PurchaseCapacityBlock","PurchaseCapacityBlockExtension","PurchaseHostReservation","PurchaseReservedInstancesOffering","PurchaseScheduledInstances","PutResourcePolicy","RebootInstances","RegisterImage","RegisterInstanceEventNotificationAttributes","RegisterTransitGatewayMulticastGroupMembers","RegisterTransitGatewayMulticastGroupSources","RejectCapacityReservationBillingOwnership","RejectTransitGatewayClientVpnAttachment","RejectTransitGatewayMulticastDomainAssociations","RejectTransitGatewayPeeringAttachment","RejectTransitGatewayVpcAttachment","RejectVpcEndpointConnections","RejectVpcPeeringConnection","ReleaseAddress","ReleaseHosts","ReleaseIpamPoolAllocation","ReplaceIamInstanceProfileAssociation","ReplaceImageCriteriaInAllowedImagesSettings","ReplaceImageInstanceTypeSpecification","ReplaceNetworkAclAssociation","ReplaceNetworkAclEntry","ReplaceRoute","ReplaceRouteTableAssociation","ReplaceTransitGatewayRoute","ReplaceVpnTunnel","ReportInstanceStatus","RequestSpotFleet","RequestSpotInstances","ResetAddressAttribute","ResetEbsDefaultKmsKeyId","ResetFpgaImageAttribute","ResetImageAttribute","ResetInstanceAttribute","ResetNetworkInterfaceAttribute","ResetSnapshotAttribute","RestoreAddressToClassic","RestoreImageFromRecycleBin","RestoreManagedPrefixListVersion","RestoreSnapshotFromRecycleBin","RestoreSnapshotTier","RestoreVolumeFromRecycleBin","RevokeClientVpnIngress","RevokeSecurityGroupEgress","RevokeSecurityGroupIngress","RunInstances","RunScheduledInstances","SearchLocalGatewayRoutes","SearchTransitGatewayMulticastGroups","SearchTransitGatewayRoutes","SendDiagnosticInterrupt","SendSpotInstanceInterruptions","StartDeclarativePoliciesReport","StartInstances","StartNetworkInsightsAccessScopeAnalysis","StartNetworkInsightsAnalysis","StartVpcEndpointServicePrivateDnsVerification","StopInstances","TerminateClientVpnConnections","TerminateInstances","UnassignIpv6Addresses","UnassignPrivateIpAddresses","UnassignPrivateNatGatewayAddress","UnlockSnapshot","UnmonitorInstances","UpdateCapacityManagerMonitoredTagKeys","UpdateCapacityManagerOrganizationsAccess","UpdateInterruptibleCapacityReservationAllocation","UpdateSecurityGroupRuleDescriptionsEgress","UpdateSecurityGroupRuleDescriptionsIngress","ValidateSecurityGroupQuotasForInterface","WithdrawByoipCidr"]
A62: Amazon EC2 Auto Scaling | B62: autoscaling | C62: list_autoscaling.html
A63: Amazon EC2 Image Builder | B63: imagebuilder | C63: list_imagebuilder.html
A64: Amazon EC2 Instance Connect | B64: ec2-instance-connect | C64: list_ec2-instance-connect.html
A65: Amazon ECS MCP Service | B65: ecs-mcp | C65: list_ecs-mcp.html
A66: Amazon EKS Auth | B66: eks-auth | C66: list_eks-auth.html
A67: Amazon EKS MCP Server | B67: eks-mcp | C67: list_eks-mcp.html
A68: Amazon Elastic Block Store | B68: ebs | C68: list_ebs.html
A69: Amazon Elastic Container Registry | B69: ecr | C69: list_ecr.html
A70: Amazon Elastic Container Registry Public | B70: ecr-public | C70: list_ecr-public.html
A71: Amazon Elastic Container Service | B71: ecs | C71: list_ecs.html
A72: Amazon Elastic File System | B72: elasticfilesystem | C72: list_efs.html | D72: ="list_" & MID($C72,6,LEN($C72)-10) & "-action-" -> list_efs-action- | E72: =HYPERLINK("https://docs.aws.amazon.com/service-authorization/latest/reference/" & $C72,"link") -> link | F72: =B72 & ":" & MID($H72,3,FIND(CHAR(34),$H72,3)-3) -> elasticfilesystem:Backup | G72: X | H72: =INDEX('AwsServices-Temp'!$C$2:$C$478,MATCH($A72,'AwsServices-Temp'!$B$2:$B$478,0)) -> ["Backup","ClientMount","ClientRootAccess","ClientWrite","CreateAccessPoint","CreateFileSystem","CreateMountTarget","CreateReplicationConfiguration","CreateTags","DeleteAccessPoint","DeleteFileSystem","DeleteFileSystemPolicy","DeleteMountTarget","DeleteReplicationConfiguration","DeleteTags","DescribeAccessPoints","DescribeAccountPreferences","DescribeBackupPolicy","DescribeFileSystemPolicy","DescribeFileSystems","DescribeLifecycleConfiguration","DescribeMountTargetSecurityGroups","DescribeMountTargets","DescribeReplicationConfigurations","DescribeTags","ListTagsForResource","ModifyMountTargetSecurityGroups","PutAccountPreferences","PutBackupPolicy","PutFileSystemPolicy","PutLifecycleConfiguration","ReplicationRead","ReplicationWrite","Restore","TagResource","UntagResource","UpdateFileSystem","UpdateFileSystemProtection"]
A73: Amazon Elastic Kubernetes Service | B73: eks | C73: list_eks.html
A74: Amazon Elastic MapReduce | B74: elasticmapreduce | C74: list_emr.html | D74: ="list_" & MID($C74,6,LEN($C74)-10) & "-action-" -> list_emr-action- | E74: =HYPERLINK("https://docs.aws.amazon.com/service-authorization/latest/reference/" & $C74,"link") -> link | F74: =B74 & ":" & MID($H74,3,FIND(CHAR(34),$H74,3)-3) -> elasticmapreduce:AccessAllEventLogs | G74: X | H74: =INDEX('AwsServices-Temp'!$C$2:$C$478,MATCH($A74,'AwsServices-Temp'!$B$2:$B$478,0)) -> ["AccessAllEventLogs","AddInstanceFleet","AddInstanceGroups","AddJobFlowSteps","AddTags","AttachEditor","CancelSteps","CreateEditor","CreatePersistentAppUI","CreateRepository","CreateSecurityConfiguration","CreateStudio","CreateStudioPresignedUrl","CreateStudioSessionMapping","DeleteEditor","DeleteRepository","DeleteSecurityConfiguration","DeleteStudio","DeleteStudioSessionMapping","DeleteWorkspaceAccess","DescribeCluster","DescribeEditor","DescribeJobFlows","DescribeNotebookExecution","DescribePersistentAppUI","DescribeReleaseLabel","DescribeRepository","DescribeSecurityConfiguration","DescribeStep","DescribeStudio","DetachEditor","GetAutoTerminationPolicy","GetBlockPublicAccessConfiguration","GetClusterSessionCredentials","GetManagedScalingPolicy","GetOnClusterAppUIPresignedURL","GetPersistentAppUIPresignedURL","GetSession","GetSessionEndpoint","GetStudioSessionMapping","LinkRepository","ListBootstrapActions","ListClusters","ListEditors","ListInstanceFleets","ListInstanceGroups","ListInstances","ListNotebookExecutions","ListReleaseLabels","ListRepositories","ListSecurityConfigurations","ListSessions","ListSteps","ListStudioSessionMappings","ListStudios","ListSupportedInstanceTypes","ListWorkspaceAccessIdentities","ModifyCluster","ModifyInstanceFleet","ModifyInstanceGroups","OpenEditorInConsole","PutAutoScalingPolicy","PutAutoTerminationPolicy","PutBlockPublicAccessConfiguration","PutManagedScalingPolicy","PutWorkspaceAccess","RemoveAutoScalingPolicy","RemoveAutoTerminationPolicy","RemoveManagedScalingPolicy","RemoveTags","RunJobFlow","SetKeepJobFlowAliveWhenNoSteps","SetTerminationProtection","SetUnhealthyNodeReplacement","SetVisibleToAllUsers","StartEditor","StartNotebookExecution","StartSession","StopEditor","StopNotebookExecution","TerminateJobFlows","TerminateSession","UnlinkRepository","UpdateEditor","UpdateRepository","UpdateStudio","UpdateStudioSessionMapping","ViewEventsFromAllClustersInConsole"]
A75: Amazon Elastic Transcoder | B75: elastictranscoder | C75: list_elastictranscoder.html
A76: Amazon Elastic VMware Service | B76: evs | C76: list_evs.html
A77: Amazon ElastiCache | B77: elasticache | C77: list_elasticache.html
A78: Amazon EMR on EKS (EMR Containers) | B78: emr-containers | C78: list_emr-containers.html
A79: Amazon EMR Serverless | B79: emr-serverless | C79: list_emr-serverless.html
A80: Amazon EventBridge | B80: events | C80: list_eventbridge.html | D80: ="list_" & MID($C80,6,LEN($C80)-10) & "-action-" -> list_eventbridge-action- | E80: =HYPERLINK("https://docs.aws.amazon.com/service-authorization/latest/reference/" & $C80,"link") -> link | F80: =B80 & ":" & MID($H80,3,FIND(CHAR(34),$H80,3)-3) -> events:ActivateEventSource | G80: X | H80: =INDEX('AwsServices-Temp'!$C$2:$C$478,MATCH($A80,'AwsServices-Temp'!$B$2:$B$478,0)) -> ["ActivateEventSource","AllowVendedLogDeliveryForResource","CancelReplay","CreateApiDestination","CreateArchive","CreateConnection","CreateEndpoint","CreateEventBus","CreateEventSource","CreatePartnerEventSource","CreateSubscriber","DeactivateEventSource","DeauthorizeConnection","DeleteApiDestination","DeleteArchive","DeleteConnection","DeleteEndpoint","DeleteEventBus","DeleteEventSource","DeletePartnerEventSource","DeleteResourcePolicy","DeleteRule","DeleteSubscriber","DescribeApiDestination","DescribeArchive","DescribeConnection","DescribeEndpoint","DescribeEventBus","DescribeEventSource","DescribePartnerEventSource","DescribeReplay","DescribeRule","DescribeSubscriber","DisableRule","EnableRule","GetResourcePolicy","InvokeApiDestination","ListApiDestinations","ListArchives","ListConnections","ListEndpoints","ListEventBuses","ListEventSources","ListPartnerEventSourceAccounts","ListPartnerEventSources","ListReplays","ListResourcePolicies","ListRuleNamesByTarget","ListRules","ListSubscribers","ListTagsForResource","ListTargetsByRule","PutEvents","PutPartnerEvents","PutPermission","PutRawEvents","PutResourcePolicy","PutRule","PutTargets","RemovePermission","RemoveTargets","RetrieveConnectionCredentials","RevokeResource","StartReplay","TagResource","TestEventPattern","UntagResource","UpdateApiDestination","UpdateArchive","UpdateConnection","UpdateEndpoint","UpdateEventBus","UpdateEventSource","UpdateSubscriber"]
A81: Amazon EventBridge Pipes | B81: pipes | C81: list_pipes.html
A82: Amazon EventBridge Scheduler | B82: scheduler | C82: list_scheduler.html
A83: Amazon EventBridge Schemas | B83: schemas | C83: list_schemas.html
A84: Amazon FinSpace | B84: finspace | C84: list_finspace.html
A85: Amazon FinSpace API | B85: finspace-api | C85: list_finspace-data.html | D85: ="list_" & MID($C85,6,LEN($C85)-10) & "-action-" -> list_finspace-data-action- | E85: =HYPERLINK("https://docs.aws.amazon.com/service-authorization/latest/reference/" & $C85,"link") -> link | F85: =B85 & ":" & MID($H85,3,FIND(CHAR(34),$H85,3)-3) -> finspace-api:etProgrammaticAccessCredentials | G85: X | H85: =INDEX('AwsServices-Temp'!$C$2:$C$478,MATCH($A85,'AwsServices-Temp'!$B$2:$B$478,0)) -> "GetProgrammaticAccessCredentials"
A86: Amazon Forecast | B86: forecast | C86: list_forecast.html
A87: Amazon Fraud Detector | B87: frauddetector | C87: list_frauddetector.html
A88: Amazon FreeRTOS | B88: freertos | C88: list_freertos.html
A89: Amazon FSx | B89: fsx | C89: list_fsx.html
A90: Amazon GameLift Servers | B90: gamelift | C90: list_gamelift.html
A91: Amazon GameLift Streams | B91: gameliftstreams | C91: list_gameliftstreams.html
A92: Amazon GroundTruth Labeling | B92: groundtruthlabeling | C92: list_groundtruthlabeling.html
A93: Amazon GuardDuty | B93: guardduty | C93: list_guardduty.html
A94: Amazon Honeycode | B94: honeycode | C94: list_honeycode.html
A95: Amazon Inspector | B95: inspector | C95: list_inspector.html
A96: Amazon Inspector2 | B96: inspector2 | C96: list_inspector2.html
A97: Amazon Inspector2 Telemetry Channel | B97: inspector2-telemetry | C97: list_inspector2-telemetry.html
A98: Amazon InspectorScan | B98: inspector-scan | C98: list_inspector-scan.html
A99: Amazon Interactive Video Service | B99: ivs | C99: list_interactive-video-service.html | D99: list_interactive-video-service-action- | E99: =HYPERLINK("https://docs.aws.amazon.com/service-authorization/latest/reference/" & $C99,"link") -> link | F99: =B99 & ":" & MID($H99,3,FIND(CHAR(34),$H99,3)-3) -> ivs:BatchGetChannel | H99: =INDEX('AwsServices-Temp'!$C$2:$C$478,MATCH($A99,'AwsServices-Temp'!$B$2:$B$478,0)) -> ["BatchGetChannel","BatchGetStreamKey","BatchStartViewerSessionRevocation","CreateAdConfiguration","CreateChannel","CreateEncoderConfiguration","CreateIngestConfiguration","CreateParticipantToken","CreatePlaybackRestrictionPolicy","CreateRecordingConfiguration","CreateStage","CreateStorageConfiguration","CreateStreamKey","DeleteAdConfiguration","DeleteChannel","DeleteEncoderConfiguration","DeleteIngestConfiguration","DeletePlaybackKeyPair","DeletePlaybackRestrictionPolicy","DeletePublicKey","DeleteRecordingConfiguration","DeleteStage","DeleteStorageConfiguration","DeleteStreamKey","DisconnectParticipant","GetAdConfiguration","GetChannel","GetComposition","GetEncoderConfiguration","GetIngestConfiguration","GetParticipant","GetPlaybackKeyPair","GetPlaybackRestrictionPolicy","GetPublicKey","GetRecordingConfiguration","GetStage","GetStageSession","GetStorageConfiguration","GetStream","GetStreamKey","GetStreamSession","ImportPlaybackKeyPair","ImportPublicKey","InsertAdBreak","ListAdConfigurations","ListChannels","ListCompositions","ListEncoderConfigurations","ListIngestConfigurations","ListParticipantEvents","ListParticipantReplicas","ListParticipants","ListPlaybackKeyPairs","ListPlaybackRestrictionPolicies","ListPublicKeys","ListRecordingConfigurations","ListStageSessions","ListStages","ListStorageConfigurations","ListStreamKeys","ListStreamSessions","ListStreams","ListTagsForResource","PutMetadata","StartComposition","StartParticipantReplication","StartViewerSessionRevocation","StopComposition","StopParticipantReplication","StopStream","TagResource","UntagResource","UpdateAdConfiguration","UpdateChannel","UpdateIngestConfiguration","UpdatePlaybackRestrictionPolicy","UpdateStage"]
A100: Amazon Interactive Video Service Chat | B100: ivschat | C100: list_ivschat.html
A101: Amazon Kendra | B101: kendra | C101: list_kendra.html
A102: Amazon Kendra Intelligent Ranking | B102: kendra-ranking | C102: list_kendra-ranking.html
A103: Amazon Keyspaces (for Apache Cassandra) | B103: cassandra | C103: list_keyspaces.html | D103: ="list_" & MID($C103,6,LEN($C103)-10) & "-action-" -> list_keyspaces-action- | E103: =HYPERLINK("https://docs.aws.amazon.com/service-authorization/latest/reference/" & $C103,"link") -> link | F103: =B103 & ":" & MID($H103,3,FIND(CHAR(34),$H103,3)-3) -> cassandra:Alter | G103: X | H103: =INDEX('AwsServices-Temp'!$C$2:$C$478,MATCH($A103,'AwsServices-Temp'!$B$2:$B$478,0)) -> ["Alter","AlterMultiRegionResource","Create","CreateMultiRegionResource","Drop","DropMultiRegionResource","GetRecords","GetShardIterator","GetStream","ListStreams","Modify","ModifyMultiRegionResource","Restore","RestoreMultiRegionTable","Select","SelectMultiRegionResource","TagMultiRegionResource","TagResource","UnTagMultiRegionResource","UntagResource","UpdatePartitioner"]
A104: Amazon Kinesis Analytics | B104: kinesisanalytics | C104: list_kinesisanalytics.html
...

Sheet Sheet2
A1: list_apigatewaymanagementapi.html
A2: list_appintegrations.html
A3: list_application-insights.html
A4: list_codeguruprofiler.html
A5: list_voice-id.html
A6: list_ec2.html
A7: list_interactive-video-service.html
A8: list_keyspaces.html | G8: list_keyspaces.html
A9: list_kinesisanalyticsv2.html
A10: list_kinesis-video-streams.html
A11: list_lex-v2.html
A12: list_location.html
A13: list_amp.html
A14: list_mwaa.html
A15: list_mturk.html
A16: list_neptunedata.html
A17: list_opensearchserverless.html
A18: list_pinpoint.html
A19: list_pinpoint-email.html | G19: list_pinpoint-email.html
A20: list_q-in-connect.html
A21: list_resourcegroupstaggingapi.html
A22: list_s3outposts.html
A23: list_mailmanager.html | G23: list_mailmanager.html
A24: list_sesv2.html | G24: list_sesv2.html
A25: list_simpledb.html
A26: list_workspaces-thin-client.html
A27: list_backupsearch.html
A28: list_cloudcontrol.html | G28: list_cloudcontrol.html
A29: list_compute-optimizer-automation.html
A30: list_devops-agent.html
A31: list_elb.html | G31: list_elb.html
A32: list_elementalinference.html
A33: list_pinpoint-sms-voice-v2.html
A34: list_accessanalyzer.html
A35: list_iam-identity-center.html
A36: list_sso-oidc.html
A37: list_greengrassv2.html | G37: list_greengrassv2.html
A38: list_iot-jobs-data.html
A39: list_iot-managed-integrations.html
A40: list_launch-wizard.html
A41: list_marketplace-agreement.html | G41: list_marketplace-agreement.html
A42: list_marketplace-deployment.html | G42: list_marketplace-deployment.html
A43: list_marketplace-discovery.html | G43: list_marketplace-discovery.html
A44: list_marketplace-image-build.html | G44: list_marketplace-image-build.html
A45: list_meteringmarketplace.html | G45: list_meteringmarketplace.html
A46: list_private-marketplace.html | G46: list_private-marketplace.html
A47: list_marketplace-procurement-integration.html | G47: list_marketplace-procurement-integration.html
A48: list_marketplace-reporting.html | G48: list_marketplace-reporting.html
A49: list_marketplace-seller-reporting.html | G49: list_marketplace-seller-reporting.html
A50: list_migration-hub.html
A51: list_migrationhuborchestrator.html
A52: list_migration-hub-refactor-spaces.html
A53: list_migrationhubstrategy.html
A54: list_mwaa-serverless.html
A55: list_network-security-manager.html
A56: list_partner-central.html
A57: list_pricing-plan-manager.html
A58: list_resilience-hub.html
A59: list_service-catalog.html
A60: list_startups.html
A61: list_stepfunctions.html
... A80: list_connect.html
A81: list_customer-profiles.html | G81: list_connect.html
A82: list_connecthealth.html
A83: list_connect-outbound-campaigns.html
A84: list_efs.html
A85: list_amazonelasticmapreduce.html
A86: list_eventbridge.html
A87: list_amazonfinspaceapi.html
A88: list_keyspaces.html
A89: list_cleanroomsml.html
A90: list_consoleapp.html
A91: list_socialmessaging.html
A92: list_service-quotas.html

Sheet AwsServices-Temp
A1: ServiceShortName | B1: ServiceName | C1: Actions | D1: ARNFormat | E1: ARNRegex | F1: conditionKeys | G1: HasResource | H1: DocLink
A2: account-access | B2: Account access manager | C2: ["CreateApplication","CreateEntitlement","DeleteApplication","DeleteEntitlement","GetApplication","GetEntitlement","ListApplications","ListEntitlements","ListTagsForResource","TagResource","UntagResource"] | D2: arn:aws:account-access:${Region}:${Account}:${ResourceType}/${ResourceId} | E2: ^arn:aws:account-access:.+ | F2: ["aws:RequestTag/${TagKey}","aws:ResourceTag/${TagKey}","aws:TagKeys"] | G2: TRUE | H2: https://docs.aws.amazon.com/service-authorization/latest/UserGuide/list_accountaccessmanager.html
A3: a4b | B3: Alexa for Business | C3: ["ApproveSkill","AssociateContactWithAddressBook","AssociateDeviceWithNetworkProfile","AssociateDeviceWithRoom","AssociateSkillGroupWithRoom","AssociateSkillWithSkillGroup","AssociateSkillWithUsers","CompleteRegistration","CreateAddressBook","CreateBusinessReportSchedule","CreateConferenceProvider","CreateContact","CreateGatewayGroup","CreateNetworkProfile","CreateProfile","CreateRoom","CreateSkillGroup","CreateUser","DeleteAddressBook","DeleteBusinessReportSchedule","DeleteConferenceProvider","DeleteContact","DeleteDevice","DeleteDeviceUsageData","DeleteGatewayGroup","DeleteNetworkProfile","DeleteProfile","DeleteRoom","DeleteRoomSkillParameter","DeleteSkillAuthorization","DeleteSkillGroup","DeleteUser","DisassociateContactFromAddressBook","DisassociateDeviceFromRoom","DisassociateSkillFromSkillGroup","DisassociateSkillFromUsers","DisassociateSkillGroupFromRoom","ForgetSmartHomeAppliances","GetAddressBook","GetConferencePreference","GetConferenceProvider","GetContact","GetDevice","GetGateway","GetGatewayGroup","GetInvitationConfiguration","GetNetworkProfile","GetProfile","GetRoom","GetRoomSkillParameter","GetSkillGroup","ListBusinessReportSchedules","ListConferenceProviders","ListDeviceEvents","ListGatewayGroups","ListGateways","ListSkills","ListSkillsStoreCategories","ListSkillsStoreSkillsByCategory","ListSmartHomeAppliances","ListTags","PutConferencePreference","PutDeviceSetupEvents","PutInvitationConfiguration","PutRoomSkillParameter","PutSkillAuthorization","RegisterAVSDevice","RegisterDevice","RejectSkill","ResolveRoom","RevokeInvitation","SearchAddressBooks","SearchContacts","SearchDevices","SearchNetworkProfiles","SearchProfiles","SearchRooms","SearchSkillGroups","SearchUsers","SendAnnouncement","SendInvitation","StartDeviceSync","StartSmartHomeApplianceDiscovery","TagResource","UntagResource","UpdateAddressBook","UpdateBusinessReportSchedule","UpdateConferenceProvider","UpdateContact","UpdateDevice","UpdateGateway","UpdateGatewayGroup","UpdateNetworkProfile","UpdateProfile","UpdateRoom","UpdateSkillGroup"] | D3: arn:aws:a4b:${Region}:${Account}:${ResourceType}/${ResourceId} | E3: ^arn:aws:a4b:.+:.+:.+ | F3: ["a4b:amazonId","a4b:filters_deviceType","aws:RequestTag/${TagKey}","aws:ResourceTag/${TagKey}","aws:TagKeys"] | G3: TRUE | H3: https://docs.aws.amazon.com/service-authorization/latest/UserGuide/list_alexaforbusiness.html
A4: aiops | B4: Amazon AI Operations | C4: ["CreateInvestigation","CreateInvestigationEvent","CreateInvestigationGroup","CreateInvestigationResource","CreateReport","DeleteInvestigation","DeleteInvestigationGroup","DeleteInvestigationGroupPolicy","GenerateReport","GetEphemeralInvestigationResults","GetFact","GetFactVersions","GetInvestigation","GetInvestigationEvent","GetInvestigationGroup","GetInvestigationGroupPolicy","GetInvestigationResource","GetReport","ListFacts","ListInvestigationEvents","ListInvestigationGroups","ListInvestigations","ListReports","ListTagsForResource","PutFact","PutInvestigationGroupPolicy","TagResource","UntagResource","UpdateInvestigation","UpdateInvestigationEvent","UpdateInvestigationGroup","UpdateReport","ValidateInvestigationGroup"] | D4: arn:aws:aiops:${Region}:${Account}:.+ | E4: ^arn:aws:aiops:.+:.+:.+ | F4: ["aws:RequestTag/${TagKey}","aws:ResourceTag/${TagKey}","aws:TagKeys"] | G4: TRUE | H4: https://docs.aws.amazon.com/service-authorization/latest/UserGuide/list_amazonaioperations.html
A5: execute-api | B5: Amazon API Gateway | C5: ["InvalidateCache","Invoke","ManageConnections"] | D5: arn:aws:execute-api:${Region}:${Account}:${ResourcePath} | E5: ^arn:aws:execute-api:.+ | F5: "execute-api:viaDomainArn" | G5: TRUE | H5: https://docs.aws.amazon.com/service-authorization/latest/UserGuide/list_amazonapigateway.html
A6: apigateway | B6: Amazon API Gateway Management | C6: ["AddCertificateToDomain","CreateAccessAssociation","DELETE","GET","PATCH","POST","PUT","RejectAccessAssociation","RemoveCertificateFromDomain","SetWebACL","UpdateDomainNameManagementPolicy","UpdateDomainNamePolicy","UpdateRestApiPolicy"] | D6: arn:aws:apigateway:${Region}::${ApiGatewayResourcePath} | E6: ^arn:aws:apigateway:.+ | F6: ["apigateway:Request/AccessAssociationSource","apigateway:Request/AccessLoggingDestination","apigateway:Request/AccessLoggingFormat","apigateway:Request/ApiKeyRequired","apigateway:Request/ApiName","apigateway:Request/AuthorizerType","apigateway:Request/DisableExecuteApiEndpoint","apigateway:Request/DomainNameArn","apigateway:Request/EndpointType","apigateway:Request/MtlsTrustStoreUri","apigateway:Request/MtlsTrustStoreVersion","apigateway:Request/RouteAuthorizationType","apigateway:Request/RoutingMode","apigateway:Request/SecurityPolicy","apigateway:Request/StageName","apigateway:Resource/AccessLoggingDestination","apigateway:Resource/AccessLoggingFormat","apigateway:Resource/ApiKeyRequired","apigateway:Resource/ApiName","apigateway:Resource/AuthorizerType","apigateway:Resource/DisableExecuteApiEndpoint","apigateway:Resource/EndpointType","apigateway:Resource/MtlsTrustStoreUri","apigateway:Resource/MtlsTrustStoreVersion","apigateway:Resource/RouteAuthorizationType","apigateway:Resource/RoutingMode","apigateway:Resource/SecurityPolicy","aws:RequestTag/${TagKey}","aws:ResourceTag/${TagKey}","aws:TagKeys"] | G6: TRUE | H6: https://docs.aws.amazon.com/service-authorization/latest/UserGuide/list_amazonapigatewaymanagement.html
A7: apigateway | B7: Amazon API Gateway Management V2 | C7: ["CreatePortal","CreatePortalProduct","CreateProductPage","CreateProductRestEndpointPage","CreateRoutingRule","DELETE","DeletePortal","DeletePortalProduct","DeletePortalProductSharingPolicy","DeleteProductPage","DeleteProductRestEndpointPage","DeleteRoutingRule","DisablePortal","GET","GetPortal","GetPortalProduct","GetPortalProductSharingPolicy","GetProductPage","GetProductRestEndpointPage","GetRoutingRule","ListPortalProducts","ListPortals","ListProductPages","ListProductRestEndpointPages","ListRoutingRules","PATCH","POST","PUT","PreviewPortal","PublishPortal","PutPortalProductSharingPolicy","UpdatePortal","UpdatePortalProduct","UpdateProductPage","UpdateProductRestEndpointPage","UpdateRoutingRule"] | D7: arn:aws:apigateway:${Region}::${ApiGatewayResourcePath} | E7: ^arn:aws:apigateway:.+ | F7: ["apigateway:Request/AccessLoggingDestination","apigateway:Request/AccessLoggingFormat","apigateway:Request/ApiKeyRequired","apigateway:Request/ApiName","apigateway:Request/AuthorizerType","apigateway:Request/AuthorizerUri","apigateway:Request/CognitoUserPoolArn","apigateway:Request/ConditionBasePaths","apigateway:Request/DisableExecuteApiEndpoint","apigateway:Request/EndpointType","apigateway:Request/Method","apigateway:Request/MtlsTrustStoreUri","apigateway:Request/MtlsTrustStoreVersion","apigateway:Request/PortalDisplayName","apigateway:Request/PortalDomainName","apigateway:Request/PortalProductDisplayName","apigateway:Request/Priority","apigateway:Request/ProductPageTitle","apigateway:Request/ProductRestEndpointPageEndpointPrefix","apigateway:Request/RestApiId","apigateway:Request/RouteAuthorizationType","apigateway:Request/RoutingMode","apigateway:Request/SecurityPolicy","apigateway:Request/Stage","apigateway:Request/StageName","apigateway:Resource/AccessLoggingDestination","apigateway:Resource/AccessLoggingFormat","apigateway:Resource/ApiKeyRequired","apigateway:Resource/ApiName","apigateway:Resource/AuthorizerType","apigateway:Resource/AuthorizerUri","apigateway:Resource/CognitoUserPoolArn","apigateway:Resource/ConditionBasePaths","apigateway:Resource/DisableExecuteApiEndpoint","apigateway:Resource/EndpointType","apigateway:Resource/Method","apigateway:Resource/MtlsTrustStoreUri","apigateway:Resource/MtlsTrustStoreVersion","apigateway:Resource/PortalDisplayName","apigateway:Resource/PortalDomainName","apigateway:Resource/PortalProductDisplayName","apigateway:Resource/PortalPublishStatus","apigateway:Resource/Priority","apigateway:Resource/ProductPageTitle","apigateway:Resource/ProductRestEndpointPageEndpointPrefix","apigateway:Resource/RestApiId","apigateway:Resource/RouteAuthorizationType","apigateway:Resource/RoutingMode","apigateway:Resource/SecurityPolicy","apigateway:Resource/Stage","aws:RequestTag/${TagKey}","aws:ResourceTag/${TagKey}","aws:TagKeys"] | G7: TRUE | H7: https://docs.aws.amazon.com/service-authorization/latest/UserGuide/list_amazonapigatewaymanagementv2.html
A8: appflow | B8: Amazon AppFlow | C8: ["CancelFlowExecutions","CreateConnectorProfile","CreateFlow","DeleteConnectorProfile","DeleteFlow","DescribeConnector","DescribeConnectorEntity","DescribeConnectorFields","DescribeConnectorProfiles","DescribeConnectors","DescribeFlow","DescribeFlowExecution","DescribeFlowExecutionRecords","DescribeFlows","ListConnectorEntities","ListConnectorFields","ListConnectors","ListFlows","ListTagsForResource","RegisterConnector","ResetConnectorMetadataCache","RunFlow","StartFlow","StopFlow","TagResource","UnRegisterConnector","UntagResource","UpdateConnectorProfile","UpdateConnectorRegistration","UpdateFlow","UseConnectorProfile"] | D8: arn:aws:appflow:${Region}:${Account}:${ResourceType}/${ResourceName} | E8: ^arn:aws:appflow:.+:.+:.+ | F8: ["aws:RequestTag/${TagKey}","aws:ResourceTag/${TagKey}","aws:TagKeys"] | G8: TRUE | H8: https://docs.aws.amazon.com/service-authorization/latest/UserGuide/list_amazonappflow.html
A9: app-integrations | B9: Amazon AppIntegrations | C9: ["CreateApplication","CreateApplicationAssociation","CreateDataIntegration","CreateDataIntegrationAssociation","CreateDataIntegrationSchedule","CreateEventIntegration","CreateEventIntegrationAssociation","DeleteApplication","DeleteApplicationAssociation","DeleteDataIntegration","DeleteDataIntegrationAssociation","DeleteEventIntegration","DeleteEventIntegrationAssociation","GetApplication","GetDataIntegration","GetDataIntegrationExecution","GetDataIntegrationSchedule","GetEventIntegration","ListApplicationAssociations","ListApplications","ListDataIntegrationAssociations","ListDataIntegrationExecutions","ListDataIntegrationSchedules","ListDataIntegrations","ListEventIntegrationAssociations","ListEventIntegrations","ListTagsForResource","StartDataIntegrationExecution","TagResource","UntagResource","UpdateApplication","UpdateDataIntegration","UpdateDataIntegrationAssociation","UpdateDataIntegrationSchedule","UpdateEventIntegration"] | D9: arn:aws:app-integrations:${Region}:${Account}:${ResourceType}/${ResourceName} | E9: ^arn:aws:app-integrations:.+:.+:.+ | F9: ["aws:RequestTag/${TagKey}","aws:ResourceTag/${TagKey}","aws:TagKeys"] | G9: TRUE | H9: https://docs.aws.amazon.com/service-authorization/latest/UserGuide/list_amazonappintegrations.html
A10: arc-zonal-shift | B10: Amazon Application Recovery Controller - Zonal Shift | C10: ["CancelPracticeRun","CancelZonalShift","CreatePracticeRunConfiguration","DeletePracticeRunConfiguration","GetAutoshiftObserverNotificationStatus","GetManagedResource","ListAutoshifts","ListManagedResources","ListZonalShifts","StartPracticeRun","StartZonalShift","UpdateAutoshiftObserverNotificationStatus","UpdatePracticeRunConfiguration","UpdateZonalAutoshiftConfiguration","UpdateZonalShift"] | D10: arn:aws:arc-zonal-shift:${Region}:${Account}:${ResourceType}/${ResourceName} | E10: ^arn:aws:arc-zonal-shift:.+:.+:.+ | F10: ["arc-zonal-shift:ResourceIdentifier","aws:ResourceTag/${TagKey}","elasticloadbalancing:ResourceTag/${TagKey}"] | G10: TRUE | H10: https://docs.aws.amazon.com/service-authorization/latest/UserGuide/list_amazonapplicationrecoverycontroller-zonalshift.html
A11: appstream | B11: Amazon AppStream 2.0 | C11: ["AssociateAppBlockBuilderAppBlock","AssociateApplicationFleet","AssociateApplicationToEntitlement","AssociateFleet","AssociateSoftwareToImageBuilder","BatchAssociateUserStack","BatchDisassociateUserStack","CopyImage","CreateAppBlock","CreateAppBlockBuilder","CreateAppBlockBuilderStreamingURL","CreateApplication","CreateDirectoryConfig","CreateEntitlement","CreateExportImageTask","CreateFleet","CreateImageBuilder","CreateImageBuilderStreamingURL","CreateImportedImage","CreateStack","CreateStreamingURL","CreateThemeForStack","CreateUpdatedImage","CreateUsageReportSubscription","CreateUser","DeleteAppBlock","DeleteAppBlockBuilder","DeleteApplication","DeleteDirectoryConfig","DeleteEntitlement","DeleteFleet","DeleteImage","DeleteImageBuilder","DeleteImagePermissions","DeleteStack","DeleteThemeForStack","DeleteUsageReportSubscription","DeleteUser","DescribeAppBlockBuilderAppBlockAssociations","DescribeAppBlockBuilders","DescribeAppBlocks","DescribeAppLicenseUsage","DescribeApplicationFleetAssociations","DescribeApplications","DescribeDirectoryConfigs","DescribeEntitlements","DescribeFleets","DescribeImageBuilders","DescribeImagePermissions","DescribeImages","DescribeSessions","DescribeSoftwareAssociations","DescribeStacks","DescribeThemeForStack","DescribeUsageReportSubscriptions","DescribeUserStackAssociations","DescribeUsers","DisableUser","DisassociateAppBlockBuilderAppBlock","DisassociateApplicationFleet","DisassociateApplicationFromEntitlement","DisassociateFleet","DisassociateSoftwareFromImageBuilder","EnableUser","ExpireSession","GetExportImageTask","ListAssociatedFleets","ListAssociatedStacks","ListEntitledApplications","ListExportImageTasks","ListTagsForResource","StartAppBlockBuilder","StartFleet","StartImageBuilder","StartSoftwareDeploymentToImageBuilder","StopAppBlockBuilder","StopFleet","StopImageBuilder","Stream","TagResource","UntagResource","UpdateAppBlockBuilder","UpdateApplication","UpdateDirectoryConfig","UpdateEntitlement","UpdateFleet","UpdateImagePermissions","UpdateStack","UpdateThemeForStack"] | D11: arn:aws:appstream:${Region}:${Account}:${ResourceType}/${ResourcePath} | E11: ^arn:aws:appstream:.+ | F11: ["appstream:userId","aws:RequestTag/${TagKey}","aws:ResourceTag/${TagKey}","aws:TagKeys"] | G11: TRUE | H11: https://docs.aws.amazon.com/service-authorization/latest/UserGuide/list_amazonappstream2.0.html
A12: arc-region-switch | B12: Amazon ARC Region switch | C12: ["ApprovePlanExecutionStep","CancelPlanExecution","CreatePlan","DeletePlan","DeleteResourcePolicy","GetPlan","GetPlanEvaluationStatus","GetPlanExecution","GetPlanInRegion","GetResourcePolicy","ListPlanExecutionEvents","ListPlanExecutions","ListPlans","ListPlansInRegion","ListRoute53HealthChecks","ListRoute53HealthChecksInRegion","ListServiceQuotaWarnings","ListTagsForResource","PutResourcePolicy","StartPlanExecution","TagResource","UntagResource","UpdatePlan","UpdatePlanExecution","UpdatePlanExecutionStep"] | D12: arn:aws:arc-region-switch::${Account}:${ResourceType} | E12: ^arn:aws:arc-region-switch::.+:.+ | F12: ["aws:RequestTag/${TagKey}","aws:ResourceTag/${TagKey}","aws:TagKeys"] | G12: TRUE | H12: https://docs.aws.amazon.com/service-authorization/latest/UserGuide/list_amazonarcregionswitch.html
A13: athena | B13: Amazon Athena | C13: ["BatchGetNamedQuery","BatchGetPreparedStatement","BatchGetQueryExecution","CancelCapacityReservation","CancelQueryExecution","CreateCapacityReservation","CreateDataCatalog","CreateNamedQuery","CreateNotebook","CreatePreparedStatement","CreatePresignedNotebookUrl","CreateWorkGroup","DeleteCapacityReservation","DeleteDataCatalog","DeleteNamedQuery","DeleteNotebook","DeletePreparedStatement","DeleteWorkGroup","ExportNotebook","GetCalculationExecution","GetCalculationExecutionCode","GetCalculationExecutionStatus","GetCapacityAssignmentConfiguration","GetCapacityReservation","GetCatalogs","GetDataCatalog","GetDatabase","GetExecutionEngine","GetExecutionEngines","GetNamedQuery","GetNamespace","GetNamespaces","GetNotebookMetadata","GetPreparedStatement","GetQueryExecution","GetQueryExecutions","GetQueryResults","GetQueryResultsStream","GetQueryRuntimeStatistics","GetResourceDashboard","GetSession","GetSessionEndpoint","GetSessionStatus","GetTable","GetTableMetadata","GetTables","GetWorkGroup","ImportNotebook","ListApplicationDPUSizes","ListCalculationExecutions","ListCapacityReservations","ListDataCatalogs","ListDatabases","ListEngineVersions","ListExecutors","ListNamedQueries","ListNotebookMetadata","ListNotebookSessions","ListPreparedStatements","ListQueryExecutions","ListSessions","ListTableMetadata","ListTagsForResource","ListWorkGroups","PutCapacityAssignmentConfiguration","RunQuery","StartCalculationExecution","StartQueryExecution","StartSession","StopCalculationExecution","StopQueryExecution","TagResource","TerminateSession","UntagResource","UpdateCapacityReservation","UpdateDataCatalog","UpdateNamedQuery","UpdateNotebook","UpdateNotebookMetadata","UpdatePreparedStatement","UpdateWorkGroup"] | D13: arn:aws:athena:${Region}:${Account}:${ResourceType}/${ResourcePath} | E13: ^arn:aws:athena:.+ | F13: ["aws:RequestTag/${TagKey}","aws:ResourceTag/${TagKey}","aws:TagKeys"] | G13: TRUE | H13: https://docs.aws.amazon.com/service-authorization/latest/UserGuide/list_amazonathena.html
... A18: bedrock-websearch | B18: Amazon Bedrock Web Search | C18: ["ExternalWebAccess","InvokeFetch","InvokeSearch"] | D18: arn:aws:bedrock-websearch:${Region}:${Account}:${ResourceType}/${ResourceName} | E18: ^arn:aws:bedrock-websearch:.+ | F18: null | G18: TRUE | H18: https://docs.aws.amazon.com/service-authorization/latest/UserGuide/list_amazonbedrockwebsearch.html
A19: researchstudio | B19: Amazon Bio Discovery | C19: ["AssignPrincipal","CreateApplication","DeleteApplication","DeletePrincipal","GetApplication","ListApplications"] | E19: ^arn:${Partition}:researchstudio:.+:.+:.+ | F19: null | G19: FALSE | H19: https://docs.aws.amazon.com/service-authorization/latest/UserGuide/list_amazonbiodiscovery.html
A20: braket | B20: Amazon Braket | C20: ["AcceptUserAgreement","CancelJob","CancelQuantumTask","CreateJob","CreateQuantumTask","CreateSpendingLimit","DeleteSpendingLimit","GetDevice","GetJob","GetQuantumTask","GetServiceLinkedRoleStatus","GetUserAgreementStatus","ListTagsForResource","SearchDevices","SearchJobs","SearchQuantumTasks","SearchSpendingLimits","TagResource","UntagResource","UpdateSpendingLimit"] | D20: arn:aws:braket:${Region}:${Account}:.+ | E20: ^arn:aws:braket:${Region}:${Account}:.+ | F20: ["aws:RequestTag/${TagKey}","aws:ResourceTag/${TagKey}","aws:TagKeys"] | G20: TRUE | H20: https://docs.aws.amazon.com/service-authorization/latest/UserGuide/list_amazonbraket.html
A21: chime | B21: Amazon Chime | C21: ["AcceptDelegate","ActivateUsers","AddDomain","AddOrUpdateGroups","AssociateChannelFlow","AssociatePhoneNumberWithUser","AssociatePhoneNumbersWithVoiceConnector","AssociatePhoneNumbersWithVoiceConnectorGroup","AssociateSigninDelegateGroupsWithAccount","AssociateVoiceConnectorConnect","AuthorizeDirectory","BatchCreateAttendee","BatchCreateChannelMembership","BatchCreateRoomMembership","BatchDeletePhoneNumber","BatchSuspendUser","BatchUnsuspendUser","BatchUpdateAttendeeCapabilitiesExcept","BatchUpdatePhoneNumber","BatchUpdateUser","ChannelFlowCallback","Connect","ConnectDirectory","CreateAccount","CreateApiKey","CreateAppInstance","CreateAppInstanceAdmin","CreateAppInstanceBot","CreateAppInstanceUser","CreateAttendee","CreateBot","CreateCDRBucket","CreateChannel","CreateChannelBan","CreateChannelFlow","CreateChannelMembership","CreateChannelModerator","CreateConnectAnalyticsConnector","CreateConnectCallTransferConnector","CreateMediaCapturePipeline","CreateMediaConcatenationPipeline","CreateMediaInsightsPipeline","CreateMediaInsightsPipelineConfiguration","CreateMediaLiveConnectorPipeline","CreateMediaPipelineKinesisVideoStreamPool","CreateMediaStreamPipeline","CreateMeeting","CreateMeetingDialOut","CreateMeetingWithAttendees","CreatePhoneNumberOrder","CreateProxySession","CreateRoom","CreateRoomMembership","CreateSipMediaApplication","CreateSipMediaApplicationCall","CreateSipRule","CreateUser","CreateVoiceConnector","CreateVoiceConnectorGroup","CreateVoiceProfile","CreateVoiceProfileDomain","DeleteAccount","DeleteAccountOpenIdConfig","DeleteApiKey","DeleteAppInstance","DeleteAppInstanceAdmin","DeleteAppInstanceBot","DeleteAppInstanceStreamingConfigurations","DeleteAppInstanceUser","DeleteAttendee","DeleteCDRBucket","DeleteChannel","DeleteChannelBan","DeleteChannelFlow","DeleteChannelMembership","DeleteChannelMessage","DeleteChannelModerator","DeleteDelegate","DeleteDomain","DeleteEventsConfiguration","DeleteGroups","DeleteMediaCapturePipeline","DeleteMediaInsightsPipelineConfiguration","DeleteMediaPipeline","DeleteMediaPipelineKinesisVideoStreamPool","DeleteMeeting","DeleteMessagingStreamingConfigurations","DeletePhoneNumber","DeleteProxySession","DeleteRoom","DeleteRoomMembership","DeleteSipMediaApplication","DeleteSipRule","DeleteVoiceConnector","DeleteVoiceConnectorEmergencyCallingConfiguration","DeleteVoiceConnectorExternalSystemsConfiguration","DeleteVoiceConnectorGroup","DeleteVoiceConnectorOrigination","DeleteVoiceConnectorProxy","DeleteVoiceConnectorStreamingConfiguration","DeleteVoiceConnectorTermination","DeleteVoiceConnectorTerminationCredentials","DeleteVoiceProfile","DeleteVoiceProfileDomain","DeregisterAppInstanceUserEndpoint","DescribeAppInstance","DescribeAppInstanceAdmin","DescribeAppInstanceBot","DescribeAppInstanceUser","DescribeAppInstanceUserEndpoint","DescribeChannel","DescribeChannelBan","DescribeChannelFlow","DescribeChannelMembership","DescribeChannelMembershipForAppInstanceUser","DescribeChannelModeratedByAppInstanceUser","DescribeChannelModerator","DisassociateChannelFlow","DisassociatePhoneNumberFromUser","DisassociatePhoneNumbersFromVoiceConnector","DisassociatePhoneNumbersFromVoiceConnectorGroup","DisassociateSigninDelegateGroupsFromAccount","DisassociateVoiceConnectorConnect","DisconnectDirectory","GetAccount","GetAccountResource","GetAccountSettings","GetAccountWithOpenIdConfig","GetAppInstanceRetentionSettings","GetAppInstanceStreamingConfigurations","GetAttendee","GetBot","GetCDRBucket","GetChannelMembershipPreferences","GetChannelMessage","GetChannelMessageStatus","GetDomain","GetEventsConfiguration","GetGlobalSettings","GetMediaCapturePipeline","GetMediaInsightsPipelineConfiguration","GetMediaPipeline","GetMediaPipelineKinesisVideoStreamPool","GetMeeting","GetMeetingDetail","GetMessagingSessionEndpoint","GetMessagingStreamingConfigurations","GetPhoneNumber","GetPhoneNumberOrder","GetPhoneNumberSettings","GetProxySession","GetRetentionSettings","GetRoom","GetSipMediaApplication","GetSipMediaApplicationAlexaSkillConfiguration","GetSipMediaApplicationLoggingConfiguration","GetSipRule","GetSpeakerSearchTask","GetTelephonyLimits","GetUser","GetUserActivityReportData","GetUserByEmail","GetUserSettings","GetVoiceConnector","GetVoiceConnectorEmergencyCallingConfiguration","GetVoiceConnectorExternalSystemsConfiguration","GetVoiceConnectorGroup","GetVoiceConnectorLoggingConfiguration","GetVoiceConnectorOrigination","GetVoiceConnectorProxy","GetVoiceConnectorStreamingConfiguration","GetVoiceConnectorTermination","GetVoiceConnectorTerminationHealth","GetVoiceProfile","GetVoiceProfileDomain","GetVoiceToneAnalysisTask","InviteDelegate","InviteUsers","InviteUsersFromProvider","ListAccountUsageReportData","ListAccounts","ListApiKeys","ListAppInstanceAdmins","ListAppInstanceBots","ListAppInstanceUserEndpoints","ListAppInstanceUsers","ListAppInstances","ListAttendeeTags","ListAttendees","ListAvailableVoiceConnectorRegions","ListBots","ListCDRBucket","ListCallingRegions","ListChannelBans","ListChannelFlows","ListChannelMemberships","ListChannelMembershipsForAppInstanceUser","ListChannelMessages","ListChannelModerators","ListChannels","ListChannelsAssociatedWithChannelFlow","ListChannelsModeratedByAppInstanceUser","ListDelegates","ListDirectories","ListDomains","ListGroups","ListMediaCapturePipelines","ListMediaInsightsPipelineConfigurations","ListMediaPipelineKinesisVideoStreamPools","ListMediaPipelines","ListMeetingEvents","ListMeetingTags","ListMeetings","ListMeetingsReportData","ListPhoneNumberOrders","ListPhoneNumbers","ListProxySessions","ListRoomMemberships","ListRooms","ListSipMediaApplications","ListSipRules","ListSubChannels","ListSupportedPhoneNumberCountries","ListTagsForResource","ListUsers","ListVoiceConnectorGroups","ListVoiceConnectorTerminationCredentials","ListVoiceConnectors","ListVoiceProfileDomains","ListVoiceProfiles","LogoutUser","PutAppInstanceRetentionSettings","PutAppInstanceStreamingConfigurations","PutAppInstanceUserExpirationSettings","PutChannelExpirationSettings","PutChannelMembershipPreferences","PutEventsConfiguration","PutMessagingStreamingConfigurations","PutRetentionSettings","PutSipMediaApplicationAlexaSkillConfiguration","PutSipMediaApplicationLoggingConfiguration","PutVoiceConnectorEmergencyCallingConfiguration","PutVoiceConnectorExternalSystemsConfiguration","PutVoiceConnectorLoggingConfiguration","PutVoiceConnectorOrigination","PutVoiceConnectorProxy","PutVoiceConnectorStreamingConfiguration","PutVoiceConnectorTermination","PutVoiceConnectorTerminationCredentials","RedactChannelMessage","RedactConversationMessage","RedactRoomMessage","RegenerateSecurityToken","RegisterAppInstanceUserEndpoint","RenameAccount","RenewDelegate","ResetAccountResource","ResetPersonalPIN","RestorePhoneNumber","RetrieveDataExports","SearchAvailablePhoneNumbers","SearchChannels","SendChannelMessage","StartDataExport","StartMeetingTranscription","StartSpeakerSearchTask","StartVoiceToneAnalysisTask","StopMeetingTranscription","StopSpeakerSearchTask","StopVoiceToneAnalysisTask","SubmitSupportRequest","SuspendUsers","TagAttendee","TagMeeting","TagResource","UnauthorizeDirectory","UntagAttendee","UntagMeeting","UntagResource","UpdateAccount","UpdateAccountOpenIdConfig","UpdateAccountResource","UpdateAccountSettings","UpdateAppInstance","UpdateAppInstanceBot","UpdateAppInstanceUser","UpdateAppInstanceUserEndpoint","UpdateAttendeeCapabilities","UpdateBot","UpdateCDRSettings","UpdateChannel","UpdateChannelFlow","UpdateChannelMessage","UpdateChannelReadMarker","UpdateGlobalSettings","UpdateMediaInsightsPipelineConfiguration","UpdateMediaInsightsPipelineStatus","UpdateMediaPipelineKinesisVideoStreamPool","UpdatePhoneNumber","UpdatePhoneNumberSettings","UpdateProxySession","UpdateRoom","UpdateRoomMembership","UpdateSipMediaApplication","UpdateSipMediaApplicationCall","UpdateSipRule","UpdateSupportedLicenses","UpdateUser","UpdateUserLicenses","UpdateUserSettings","UpdateVoiceConnector","UpdateVoiceConnectorGroup","UpdateVoiceProfile","UpdateVoiceProfileDomain","ValidateAccountResource","ValidateE911Address"] | D21: arn:aws:chime:${Region}:${Account}:${ResourceType}/${ResourceID} | E21: ^arn:aws:chime:.+ | F21: ["aws:RequestTag/${TagKey}","aws:ResourceTag/${TagKey}","aws:TagKeys"] | G21: TRUE | H21: https://docs.aws.amazon.com/service-authorization/latest/UserGuide/list_amazonchime.html
A22: clouddirectory | B22: Amazon Cloud Directory | C22: ["AddFacetToObject","ApplySchema","AttachObject","AttachPolicy","AttachToIndex","AttachTypedLink","BatchRead","BatchWrite","CreateDirectory","CreateFacet","CreateIndex","CreateObject","CreateSchema","CreateTypedLinkFacet","DeleteDirectory","DeleteFacet","DeleteObject","DeleteSchema","DeleteTypedLinkFacet","DetachFromIndex","DetachObject","DetachPolicy","DetachTypedLink","DisableDirectory","EnableDirectory","GetAppliedSchemaVersion","GetDirectory","GetFacet","GetLinkAttributes","GetObjectAttributes","GetObjectInformation","GetSchemaAsJson","GetTypedLinkFacetInformation","ListAppliedSchemaArns","ListAttachedIndices","ListDevelopmentSchemaArns","ListDirectories","ListFacetAttributes","ListFacetNames","ListIncomingTypedLinks","ListIndex","ListManagedSchemaArns","ListObjectAttributes","ListObjectChildren","ListObjectParentPaths","ListObjectParents","ListObjectPolicies","ListOutgoingTypedLinks","ListPolicyAttachments","ListPublishedSchemaArns","ListTagsForResource","ListTypedLinkFacetAttributes","ListTypedLinkFacetNames","LookupPolicy","PublishSchema","PutSchemaFromJson","RemoveFacetFromObject","TagResource","UntagResource","UpdateFacet","UpdateLinkAttributes","UpdateObjectAttributes","UpdateSchema","UpdateTypedLinkFacet","UpgradeAppliedSchema","UpgradePublishedSchema"] | D22: arn:aws:clouddirectory:${Region}:${Account}:${RelativeId} | E22: ^arn:aws:clouddirectory:.+:[0-9]+:(directory|schema)/.+ | F22: null | G22: TRUE | H22: https://docs.aws.amazon.com/service-authorization/latest/UserGuide/list_amazonclouddirectory.html
A23: cloudfront | B23: Amazon CloudFront | C23: ["AllowVendedLogDeliveryForResource","AssociateAlias","AssociateDistributionTenantWebACL","AssociateDistributionWebACL","CopyDistribution","CreateAnycastIpList","CreateCachePolicy","CreateCloudFrontOriginAccessIdentity","CreateConnectionFunction","CreateConnectionGroup","CreateContinuousDeploymentPolicy","CreateDistribution","CreateDistributionTenant","CreateFieldLevelEncryptionConfig","CreateFieldLevelEncryptionProfile","CreateFunction","CreateInvalidation","CreateInvalidationForDistributionTenant","CreateKeyGroup","CreateKeyValueStore","CreateMonitoringSubscription","CreateOriginAccessControl","CreateOriginRequestPolicy","CreatePublicKey","CreateRealtimeLogConfig","CreateResponseHeadersPolicy","CreateSavingsPlan","CreateStreamingDistribution","CreateStreamingDistributionWithTags","CreateTrustStore","CreateVpcOrigin","DeleteAnycastIpList","DeleteCachePolicy","DeleteCloudFrontOriginAccessIdentity","DeleteConnectionFunction","DeleteConnectionGroup","DeleteContinuousDeploymentPolicy","DeleteDistribution","DeleteDistributionTenant","DeleteFieldLevelEncryptionConfig","DeleteFieldLevelEncryptionProfile","DeleteFunction","DeleteKeyGroup","DeleteKeyValueStore","DeleteMonitoringSubscription","DeleteOriginAccessControl","DeleteOriginRequestPolicy","DeletePublicKey","DeleteRealtimeLogConfig","DeleteResourcePolicy","DeleteResponseHeadersPolicy","DeleteStreamingDistribution","DeleteTrustStore","DeleteVpcOrigin","DescribeConnectionFunction","DescribeFunction","DescribeKeyValueStore","DisassociateDistributionTenantWebACL","DisassociateDistributionWebACL","GetAnycastIpList","GetCachePolicy","GetCachePolicyConfig","GetCloudFrontOriginAccessIdentity","GetCloudFrontOriginAccessIdentityConfig","GetConnectionFunction","GetConnectionGroup","GetConnectionGroupByRoutingEndpoint","GetContinuousDeploymentPolicy","GetContinuousDeploymentPolicyConfig","GetDistribution","GetDistributionConfig","GetDistributionTenant","GetDistributionTenantByDomain","GetFieldLevelEncryption","GetFieldLevelEncryptionConfig","GetFieldLevelEncryptionProfile","GetFieldLevelEncryptionProfileConfig","GetFunction","GetInvalidation","GetInvalidationForDistributionTenant","GetKeyGroup","GetKeyGroupConfig","GetManagedCertificateDetails","GetMonitoringSubscription","GetOriginAccessControl","GetOriginAccessControlConfig","GetOriginRequestPolicy","GetOriginRequestPolicyConfig","GetPublicKey","GetPublicKeyConfig","GetRealtimeLogConfig","GetResourcePolicy","GetResponseHeadersPolicy","GetResponseHeadersPolicyConfig","GetSavingsPlan","GetStreamingDistribution","GetStreamingDistributionConfig","GetTrustStore","GetVpcOrigin","ListAnycastIpLists","ListCachePolicies","ListCloudFrontOriginAccessIdentities","ListConflictingAliases","ListConnectionFunctions","ListConnectionGroups","ListContinuousDeploymentPolicies","ListDistributionTenants","ListDistributionTenantsByCustomization","ListDistributions","ListDistributionsByAnycastIpListId","ListDistributionsByCachePolicyId","ListDistributionsByConnectionFunction","ListDistributionsByConnectionMode","ListDistributionsByKeyGroup","ListDistributionsByLambdaFunction","ListDistributionsByOriginRequestPolicyId","ListDistributionsByRealtimeLogConfig","ListDistributionsByResponseHeadersPolicyId","ListDistributionsByTrustStore","ListDistributionsByVpcOriginId","ListDistributionsByWebACLId","ListDomainConflicts","ListFieldLevelEncryptionConfigs","ListFieldLevelEncryptionProfiles","ListFunctions","ListInvalidations","ListInvalidationsForDistributionTenant","ListKeyGroups","ListKeyValueStores","ListOriginAccessControls","ListOriginRequestPolicies","ListPublicKeys","ListRateCards","ListRealtimeLogConfigs","ListResponseHeadersPolicies","ListSavingsPlans","ListStreamingDistributions","ListTagsForResource","ListTrustStores","ListUsages","ListVpcOrigins","PublishConnectionFunction","PublishFunction","PutResourcePolicy","TagResource","TestConnectionFunction","TestFunction","UntagResource","UpdateAnycastIpList","UpdateCachePolicy","UpdateCloudFrontOriginAccessIdentity","UpdateConnectionFunction","UpdateConnectionGroup","UpdateContinuousDeploymentPolicy","UpdateDistribution","UpdateDistributionTenant","UpdateDistributionWithStagingConfig","UpdateDomainAssociation","UpdateFieldLevelEncryptionConfig","UpdateFieldLevelEncryptionProfile","UpdateFunction","UpdateKeyGroup","UpdateKeyValueStore","UpdateOriginAccessControl","UpdateOriginRequestPolicy","UpdatePublicKey","UpdateRealtimeLogConfig","UpdateResponseHeadersPolicy","UpdateSavingsPlan","UpdateStreamingDistribution","UpdateTrustStore","UpdateVpcOrigin","VerifyDnsConfiguration"] | D23: arn:aws:cloudfront:${Region}:${Account}:${ResourceType}/${ResourceId} | E23: ^arn:aws:cloudfront:.+:[0-9]+:.+ | F23: ["aws:RequestTag/${TagKey}","aws:ResourceTag/${TagKey}","aws:TagKeys"] | G23: TRUE | H23: https://docs.aws.amazon.com/service-authorization/latest/UserGuide/list_amazoncloudfront.html
A24: cloudfront-keyvaluestore | B24: Amazon CloudFront KeyValueStore | C24: ["DeleteKey","DescribeKeyValueStore","GetKey","ListKeys","PutKey","UpdateKeys"] | D24: arn:aws:cloudfront:${Region}:${Account}:key-value-store/${ResourceId} | E24: ^arn:aws:cloudfront:.+:[0-9]+:.+ | F24: null | G24: TRUE | H24: https://docs.aws.amazon.com/service-authorization/latest/UserGuide/list_amazoncloudfrontkeyvaluestore.html
A25: cloudsearch | B25: Amazon CloudSearch | C25: ["AddTags","BuildSuggesters","CreateDomain","DefineAnalysisScheme","DefineExpression","DefineIndexField","DefineSuggester","DeleteAnalysisScheme","DeleteDomain","DeleteExpression","DeleteIndexField","DeleteSuggester","DescribeAnalysisSchemes","DescribeAvailabilityOptions","DescribeDomainEndpointOptions","DescribeDomains","DescribeExpressions","DescribeIndexFields","DescribeScalingParameters","DescribeServiceAccessPolicies","DescribeSuggesters","IndexDocuments","ListDomainNames","ListTags","RemoveTags","UpdateAvailabilityOptions","UpdateDomainEndpointOptions","UpdateScalingParameters","UpdateServiceAccessPolicies","document","search","suggest"] | D25: arn:aws:cloudsearch:${Region}:${Account}:${ResourceType}/${ResourceName} | E25: ^arn:aws:cloudsearch:.+:.+:.+ | F25: null | G25: TRUE | H25: https://docs.aws.amazon.com/service-authorization/latest/UserGuide/list_amazoncloudsearch.html
A26: cloudwatch | B26: Amazon CloudWatch | C26: ["AssumeAccessProfile","BatchGetServiceLevelIndicatorReport","BatchGetServiceLevelObjectiveBudgetReport","CallWithBearerToken","CreateAccessGrant","CreateAccessProfile","CreateAlert","CreateDomain","CreateDomainAccessGrantForOrganization","CreateDomainForOrganization","CreateIngestionEndpoint","CreateIntegration","CreateOmniDashboard","CreateOmniThread","CreateOneTimeDeepLinkCode","CreateServiceLevelObjective","CreateSpace","CreateView","DeleteAccessGrant","DeleteAccessProfile","DeleteAlarmMuteRule","DeleteAlarms","DeleteAlert","DeleteAnomalyDetector","DeleteDashboards","DeleteDomain","DeleteDomainAccessGrantForOrganization","DeleteDomainForOrganization","DeleteIngestionEndpoint","DeleteInsightRules","DeleteIntegration","DeleteMetricStream","DeleteOmniDashboard","DeleteOmniThread","DeletePipelineRule","DeleteServiceLevelObjective","DeleteSpace","DeleteView","DescribeAlarmHistory","DescribeAlarms","DescribeAlarmsForMetric","DescribeAnomalyDetectors","DescribeInsightRules","DisableAlarmActions","DisableInsightRules","EnableAlarmActions","EnableInsightRules","EnableTopologyDiscovery","GenerateQuery","GenerateQueryResultsSummary","GetAccessGrant","GetAccessProfile","GetAgentGraph","GetAlarmMuteRule","GetAlert","GetContextGraph","GetDashboard","GetDataset","GetDomain","GetDomainAccessGrantForOrganization","GetDomainForOrganization","GetIngestionEndpoint","GetInsightRuleReport","GetIntegration","GetIntelligenceConfiguration","GetMetricData","GetMetricStatistics","GetMetricStream","GetMetricWidgetImage","GetOTelEnrichment","GetOmniDashboard","GetOmniThread","GetPreferences","GetRecords","GetService","GetServiceData","GetServiceLevelObjective","GetSpace","GetSpaceCredentials","GetSpaceCredentialsForOrganization","GetTelemetryQueryResults","GetTopologyDiscoveryStatus","GetTopologyMap","GetView","InvokeIntegration","Link","ListAccessGrants","ListAccessProfiles","ListAlarmMuteRules","ListAlertContributors","ListAlerts","ListDashboards","ListDomainAccessGrantsForOrganization","ListDomains","ListEntitiesForMetric","ListIngestionEndpoints","ListIntegrations","ListManagedInsightRules","ListMetricStreams","ListMetrics","ListOmniDashboards","ListOmniThreads","ListServiceLevelObjectives","ListServices","ListSpaceAccess","ListSpaces","ListSpacesForOrganization","ListTagsForResource","ListTelemetryFields","ListTelemetryQuerySessions","ListViews","PutAlarmMuteRule","PutAnomalyDetector","PutCompositeAlarm","PutDashboard","PutInsightRule","PutIntelligenceConfiguration","PutLogAlarm","PutManagedInsightRules","PutMetricAlarm","PutMetricData","PutMetricStream","PutPipelineRule","QueryTraces","SearchPrincipals","SetAlarmState","StartMetricStreams","StartOTelEnrichment","StartOmniThreadSession","StartTelemetryQuery","StartTelemetryQuerySession","StopMetricStreams","StopOTelEnrichment","StopTelemetryQuery","StopTelemetryQuerySession","SubmitFeedback","TagResource","UntagResource","UpdateAccessProfile","UpdateAlert","UpdateDomain","UpdateDomainForOrganization","UpdateIngestionEndpoint","UpdateIntegration","UpdateOmniDashboard","UpdateOmniThread","UpdatePreferences","UpdateServiceLevelObjective","UpdateSpace","UpdateView"] | D26: arn:aws:cloudwatch:${Region}:${Account}:${ResourceType}/${ResourcePath} | E26: ^arn:aws:cloudwatch:.+ | F26: ["aws:RequestTag/${TagKey}","aws:ResourceTag/${TagKey}","aws:TagKeys","cloudwatch:AlarmActions","cloudwatch:HasAccessGrant","cloudwatch:namespace","cloudwatch:requestInsightRuleLogGroups","cloudwatch:requestManagedResourceARNs"] | G26: TRUE | H26: https://docs.aws.amazon.com/service-authorization/latest/UserGuide/list_amazoncloudwatch.html
A27: applicationinsights | B27: Amazon CloudWatch Application Insights | C27: ["AddWorkload","CreateApplication","CreateComponent","CreateLogPattern","DeleteApplication","DeleteComponent","DeleteLogPattern","DescribeApplication","DescribeComponent","DescribeComponentConfiguration","DescribeComponentConfigurationRecommendation","DescribeLogPattern","DescribeObservation","DescribeProblem","DescribeProblemObservations","DescribeWorkload","Link","ListApplications","ListComponents","ListConfigurationHistory","ListLogPatternSets","ListLogPatterns","ListProblems","ListTagsForResource","ListWorkloads","RemoveWorkload","TagResource","UntagResource","UpdateApplication","UpdateComponent","UpdateComponentConfiguration","UpdateLogPattern","UpdateProblem","UpdateWorkload"] | F27: ["aws:RequestTag/${TagKey}","aws:ResourceTag/${TagKey}","aws:TagKeys"] | G27: FALSE | H27: https://docs.aws.amazon.com/service-authorization/latest/UserGuide/list_amazoncloudwatchapplicationinsights.html
A28: application-signals | B28: Amazon CloudWatch Application Signals | C28: ["BatchDeleteInstrumentationConfigurations","BatchGetServiceLevelObjectiveBudgetReport","BatchUpdateExclusionWindows","CreateInstrumentationConfiguration","CreateServiceLevelObjective","DeleteGroupingConfiguration","DeleteInstrumentationConfiguration","DeleteServiceLevelObjective","GetInstrumentationConfiguration","GetInstrumentationConfigurationStatus","GetService","GetServiceLevelObjective","Link","ListAuditFindings","ListEntityEvents","ListGroupingAttributeDefinitions","ListInstrumentationConfigurations","ListObservedEntities","ListServiceDependencies","ListServiceDependents","ListServiceLevelObjectiveExclusionWindows","ListServiceLevelObjectives","ListServiceOperations","ListServiceStates","ListServices","ListTagsForResource","PutGroupingConfiguration","ReportInstrumentationConfigurationStatus","StartDiscovery","TagResource","UntagResource","UpdateServiceLevelObjective"] | D28: arn:aws:application-signals:${Region}:${Account}:slo/{ServiceLevelObjectivesName} | E28: ^arn:aws:application-signals:.+:.+:.+ | F28: ["aws:RequestTag/${TagKey}","aws:ResourceTag/${TagKey}","aws:TagKeys"] | G28: TRUE | H28: https://docs.aws.amazon.com/service-authorization/latest/UserGuide/list_amazoncloudwatchapplicationsignals.html
A29: application-signals-mcp | B29: Amazon CloudWatch Application Signals MCP Server | C29: ["CallReadOnlyTool","InvokeMcp"] | D29: arn:aws:application-signals-mcp:${Region}:${Account}:mcp-server/${ResourceId} | E29: ^arn:aws:application-signals-mcp:.+:.+:.+ | F29: "aws:ResourceTag/${TagKey}" | G29: TRUE | H29: https://docs.aws.amazon.com/service-authorization/latest/UserGuide/list_amazoncloudwatchapplicationsignalsmcpserver.html
A30: evidently | B30: Amazon CloudWatch Evidently | C30: ["BatchEvaluateFeature","CreateExperiment","CreateFeature","CreateLaunch","CreateProject","CreateSegment","DeleteExperiment","DeleteFeature","DeleteLaunch","DeleteProject","DeleteSegment","EvaluateFeature","GetExperiment","GetExperimentResults","GetFeature","GetLaunch","GetProject","GetSegment","ListExperiments","ListFeatures","ListLaunches","ListProjects","ListSegmentReferences","ListSegments","ListTagsForResource","PutProjectEvents","StartExperiment","StartLaunch","StopExperiment","StopLaunch","TagResource","TestSegmentPattern","UntagResource","UpdateExperiment","UpdateFeature","UpdateLaunch","UpdateProject","UpdateProjectDataDelivery"] | D30: arn:aws:evidently:${Region}:${Account}:${ResourceType}/${ResourceName} | E30: ^arn:aws:evidently:.+:.+:.+ | F30: ["aws:RequestTag/${TagKey}","aws:ResourceTag/${TagKey}","aws:TagKeys"] | G30: TRUE | H30: https://docs.aws.amazon.com/service-authorization/latest/UserGuide/list_amazoncloudwatchevidently.html
A31: internetmonitor | B31: Amazon CloudWatch Internet Monitor | C31: ["CreateMonitor","DeleteMonitor","GetHealthEvent","GetInternetEvent","GetMonitor","GetQueryResults","GetQueryStatus","Link","ListHealthEvents","ListInternetEvents","ListMonitors","ListTagsForResource","StartQuery","StopQuery","TagResource","UntagResource","UpdateMonitor"] | D31: arn:aws:internetmonitor:${Region}:${Account}:${ResourceType}/${ResourcePath} | E31: ^arn:aws:internetmonitor:.+:.+:.+ | F31: ["aws:RequestTag/${TagKey}","aws:ResourceTag/${TagKey}","aws:TagKeys"] | G31: TRUE | H31: https://docs.aws.amazon.com/service-authorization/latest/UserGuide/list_amazoncloudwatchinternetmonitor.html
A32: logs | B32: Amazon CloudWatch Logs | C32: ["AssociateKmsKey","AssociateSourceToS3TableIntegration","CallWithBearerToken","CancelExportTask","CancelImportTask","CreateDelivery","CreateExportTask","CreateImportTask","CreateLogAnomalyDetector","CreateLogDelivery","CreateLogGroup","CreateLogStream","CreateLookupTable","CreateScheduledQuery","DeleteAccountPolicy","DeleteDataProtectionPolicy","DeleteDelivery","DeleteDeliveryDestination","DeleteDeliveryDestinationPolicy","DeleteDeliverySource","DeleteDestination","DeleteIndexPolicy","DeleteIntegration","DeleteLogAnomalyDetector","DeleteLogDelivery","DeleteLogGroup","DeleteLogStream","DeleteLookupTable","DeleteMetricFilter","DeletePipelineRule","DeleteQueryDefinition","DeleteResourcePolicy","DeleteRetentionPolicy","DeleteScheduledQuery","DeleteSubscriptionFilter","DeleteSyslogConfiguration","DeleteTransformer","DescribeAccountPolicies","DescribeConfigurationTemplates","DescribeDeliveries","DescribeDeliveryDestinations","DescribeDeliverySources","DescribeDestinations","DescribeExportTasks","DescribeFieldIndexes","DescribeImportTaskBatches","DescribeImportTasks","DescribeIndexPolicies","DescribeLogGroups","DescribeLogStreams","DescribeLookupTables","DescribeMetricFilters","DescribeQueries","DescribeQueryDefinitions","DescribeResourcePolicies","DescribeSubscriptionFilters","DisassociateKmsKey","DisassociateSourceFromS3TableIntegration","FilterLogEvents","GetDataProtectionPolicy","GetDelivery","GetDeliveryDestination","GetDeliveryDestinationPolicy","GetDeliverySource","GetIntegration","GetLogAnomalyDetector","GetLogDelivery","GetLogEvents","GetLogFields","GetLogGroupFields","GetLogRecord","GetLookupTable","GetQueryResults","GetScheduledQuery","GetScheduledQueryHistory","GetStorageTierPolicy","GetTransformer","IntegrateWithDataset","IntegrateWithS3Table","Link","ListAggregateLogGroupSummaries","ListAnomalies","ListEntitiesForLogGroup","ListIntegrations","ListLogAnomalyDetectors","ListLogDeliveries","ListLogGroups","ListLogGroupsForEntity","ListLogGroupsForQuery","ListScheduledQueries","ListSourcesForS3TableIntegration","ListSyslogConfigurations","ListTagsForResource","ListTagsLogGroup","ProcessWithPipeline","PutAccountPolicy","PutBearerTokenAuthentication","PutDataProtectionPolicy","PutDeliveryDestination","PutDeliveryDestinationPolicy","PutDeliverySource","PutDestination","PutDestinationPolicy","PutIndexPolicy","PutIntegration","PutLogEvents","PutLogGroupDeletionProtection","PutMetricFilter","PutPipelineRule","PutQueryDefinition","PutResourcePolicy","PutRetentionPolicy","PutStorageTierPolicy","PutSubscriptionFilter","PutSyslogConfiguration","PutTransformer","StartLiveTail","StartQuery","StopLiveTail","StopQuery","TagLogGroup","TagResource","TestMetricFilter","TestTransformer","Unmask","UntagLogGroup","UntagResource","UpdateAnomaly","UpdateDeliveryConfiguration","UpdateLogAnomalyDetector","UpdateLogDelivery","UpdateLookupTable","UpdateScheduledQuery"] | D32: arn:aws:logs:${Region}:${Account}:.+ | E32: ^arn:aws:logs:.+ | F32: ["aws:RequestTag/${TagKey}","aws:ResourceTag/${TagKey}","aws:TagKeys","logs:DeliveryDestinationResourceArn","logs:LogGeneratingResourceArns","logs:data_source_name","logs:data_source_type"] | G32: TRUE | H32: https://docs.aws.amazon.com/service-authorization/latest/UserGuide/list_amazoncloudwatchlogs.html
A33: networkmonitor | B33: Amazon CloudWatch Network Synthetic Monitor | C33: ["CreateMonitor","CreateProbe","DeleteMonitor","DeleteProbe","GetMonitor","GetProbe","ListMonitors","ListTagsForResource","TagResource","UntagResource","UpdateMonitor","UpdateProbe"] | D33: arn:aws:networkmonitor:${Region}:${Account}:${ResourceType}/${ResourcePath} | E33: ^arn:aws:networkmonitor:.+:.+:.+ | F33: ["aws:RequestTag/${TagKey}","aws:ResourceTag/${TagKey}","aws:TagKeys"] | G33: TRUE | H33: https://docs.aws.amazon.com/service-authorization/latest/UserGuide/list_amazoncloudwatchnetworksyntheticmonitor.html
A34: oam | B34: Amazon CloudWatch Observability Access Manager | C34: ["CreateLink","CreateSink","DeleteLink","DeleteSink","GetLink","GetSink","GetSinkPolicy","ListAttachedLinks","ListLinks","ListSinks","ListTagsForResource","PutSinkPolicy","TagResource","UntagResource","UpdateLink"] | D34: arn:aws:oam:${Region}:${Account}:${ResourceType}/${ResourceId} | E34: ^arn:aws:oam:.+:.+:.+ | F34: ["aws:RequestTag/${TagKey}","aws:ResourceTag/${TagKey}","aws:TagKeys","oam:ResourceTypes"] | G34: TRUE | H34: https://docs.aws.amazon.com/service-authorization/latest/UserGuide/list_amazoncloudwatchobservabilityaccessmanager.html
A35: observabilityadmin | B35: Amazon CloudWatch Observability Admin Service | C35: ["CreateCentralizationRuleForOrganization","CreateDatasetIntegration","CreateS3TableIntegration","CreateTelemetryPipeline","CreateTelemetryRule","CreateTelemetryRuleForOrganization","DeleteCentralizationRuleForOrganization","DeleteDatasetIntegration","DeleteS3TableIntegration","DeleteTelemetryPipeline","DeleteTelemetryRule","DeleteTelemetryRuleForOrganization","GetCentralizationRuleForOrganization","GetDatasetIntegration","GetS3TableIntegration","GetTelemetryEnrichmentStatus","GetTelemetryEvaluationStatus","GetTelemetryEvaluationStatusForOrganization","GetTelemetryPipeline","GetTelemetryRule","GetTelemetryRuleForOrganization","ListCentralizationRulesForOrganization","ListDatasetIntegrations","ListResourceTelemetry","ListResourceTelemetryForOrganization","ListS3TableIntegrations","ListTagsForResource","ListTelemetryPipelines","ListTelemetryRules","ListTelemetryRulesForOrganization","StartTelemetryEnrichment","StartTelemetryEvaluation","StartTelemetryEvaluationForOrganization","StopTelemetryEnrichment","StopTelemetryEvaluation","StopTelemetryEvaluationForOrganization","TagResource","TestTelemetryPipeline","UntagResource","UpdateCentralizationRuleForOrganization","UpdateDatasetIntegration","UpdateTelemetryPipeline","UpdateTelemetryRule","UpdateTelemetryRuleForOrganization","ValidateTelemetryPipelineConfiguration"] | D35: arn:aws:observabilityadmin:${Region}:${Account}:${ResourceType} | E35: ^arn:aws:observabilityadmin:.+:.+:.+ | F35: ["aws:RequestTag/${TagKey}","aws:ResourceTag/${TagKey}","aws:TagKeys","observabilityadmin:CentralizationBackupRegion","observabilityadmin:CentralizationDestinationAccount","observabilityadmin:CentralizationDestinationRegion","observabilityadmin:CentralizationRuleName","observabilityadmin:CentralizationSourceId","observabilityadmin:CentralizationSourceRegions","observabilityadmin:SourceType","observabilityadmin:TargetRegions"] | G35: TRUE | H35: https://docs.aws.amazon.com/service-authorization/latest/UserGuide/list_amazoncloudwatchobservabilityadminservice.html
A36: synthetics | B36: Amazon CloudWatch Synthetics | C36: ["AssociateResource","CreateCanary","CreateGroup","DeleteCanary","DeleteGroup","DescribeCanaries","DescribeCanariesLastRun","DescribeRuntimeVersions","DisassociateResource","GetCanary","GetCanaryRuns","GetGroup","ListAssociatedGroups","ListGroupResources","ListGroups","ListTagsForResource","StartCanary","StartCanaryDryRun","StopCanary","TagResource","UntagResource","UpdateCanary"] | D36: arn:aws:synthetics:${Region}:${Account}:${ResourceType}:${ResourceName} | E36: ^arn:aws:synthetics:.+ | F36: ["aws:RequestTag/${TagKey}","aws:ResourceTag/${TagKey}","aws:TagKeys","synthetics:Names"] | G36: TRUE | H36: https://docs.aws.amazon.com/service-authorization/latest/UserGuide/list_amazoncloudwatchsynthetics.html
A37: codecatalyst | B37: Amazon CodeCatalyst | C37: ["AcceptConnection","AssociateIamRoleToConnection","AssociateIdentityCenterApplicationToSpace","AssociateIdentityToIdentityCenterApplication","BatchAssociateIdentitiesToIdentityCenterApplication","BatchDisassociateIdentitiesFromIdentityCenterApplication","CreateIdentityCenterApplication","CreateSpace","CreateSpaceAdminRoleAssignment","DeleteConnection","DeleteIdentityCenterApplication","DisassociateIamRoleFromConnection","DisassociateIdentityCenterApplicationFromSpace","DisassociateIdentityFromIdentityCenterApplication","GetBillingAuthorization","GetConnection","GetIdentityCenterApplication","GetPendingConnection","ListConnections","ListIamRolesForConnection","ListIdentityCenterApplications","ListIdentityCenterApplicationsForSpace","ListSpacesForIdentityCenterApplication","ListTagsForResource","PutBillingAuthorization","RejectConnection","SynchronizeIdentityCenterApplication","TagResource","UntagResource","UpdateIdentityCenterApplication"] | D37: arn:aws:codecatalyst:${Region}:${Account}:${RelativeId} | E37: ^arn:aws:codecatalyst:.+ | F37: ["aws:RequestTag/${TagKey}","aws:ResourceTag/${TagKey}","aws:TagKeys"] | G37: TRUE | H37: https://docs.aws.amazon.com/service-authorization/latest/UserGuide/list_amazoncodecatalyst.html
A38: codeguru | B38: Amazon CodeGuru | C38: "GetCodeGuruFreeTrialSummary" | D38: arn:${Partition}:codeguru:${Region}:${Account}:${ResourceType}/${ResourceName} | E38: ^arn:${Partition}:codeguru:.+:.+:.+ | F38: null | G38: FALSE | H38: https://docs.aws.amazon.com/service-authorization/latest/UserGuide/list_amazoncodeguru.html
A39: codeguru-profiler | B39: Amazon CodeGuru Profiler | C39: ["AddNotificationChannels","BatchGetFrameMetricData","ConfigureAgent","CreateProfilingGroup","DeleteProfilingGroup","DescribeProfilingGroup","GetFindingsReportAccountSummary","GetNotificationConfiguration","GetPolicy","GetProfile","GetRecommendations","ListFindingsReports","ListProfileTimes","ListProfilingGroups","ListTagsForResource","PostAgentProfile","PutPermission","RemoveNotificationChannel","RemovePermission","SubmitFeedback","TagResource","UntagResource","UpdateProfilingGroup"] | D39: arn:aws:codeguru-profiler:${Region}:${Account}:${ResourceType}/${ResourceName} | E39: ^arn:aws:codeguru-profiler:.+:.+:.+ | F39: ["aws:RequestTag/${TagKey}","aws:ResourceTag/${TagKey}","aws:TagKeys"] | G39: TRUE | H39: https://docs.aws.amazon.com/service-authorization/latest/UserGuide/list_amazoncodeguruprofiler.html
... A64: ec2-instance-connect | B64: Amazon EC2 Instance Connect | C64: ["OpenTunnel","SendSSHPublicKey","SendSerialConsoleSSHPublicKey"] | D64: arn:aws:ec2:${Region}:${Account}:${ResourceType}/${ResourcePath} | E64: ^arn:aws:ec2:.+ | F64: ["aws:ResourceTag/${TagKey}","ec2-instance-connect:maxTunnelDuration","ec2-instance-connect:privateIpAddress","ec2-instance-connect:remotePort","ec2:ResourceTag/${TagKey}","ec2:osuser"] | G64: TRUE | H64: https://docs.aws.amazon.com/service-authorization/latest/UserGuide/list_amazonec2instanceconnect.html
A65: ecs-mcp | B65: Amazon ECS MCP Service | C65: ["InvokeReadOnlyTools","UseMcp"] | F65: null | G65: FALSE | H65: https://docs.aws.amazon.com/service-authorization/latest/UserGuide/list_amazonecsmcpservice.html
A66: eks-auth | B66: Amazon EKS Auth | C66: "AssumeRoleForPodIdentity" | D66: arn:aws:eks:${Region}:${Account}:${ResourceType}/${RelativeId} | E66: ^arn:aws:eks:.+ | F66: "aws:ResourceTag/${TagKey}" | G66: TRUE | H66: https://docs.aws.amazon.com/service-authorization/latest/UserGuide/list_amazoneksauth.html
A67: eks-mcp | B67: Amazon EKS MCP Server | C67: ["CallPrivilegedTool","CallReadOnlyTool","InvokeMcp"] | D67: arn:${Partition}:eks-mcp:${Region}:${Account}:${ResourceType}/${ResourcePath} | E67: ^arn:${Partition}:eks:. | F67: null | G67: FALSE | H67: https://docs.aws.amazon.com/service-authorization/latest/UserGuide/list_amazoneksmcpserver.html
A68: ebs | B68: Amazon Elastic Block Store | C68: ["CompleteSnapshot","GetSnapshotBlock","ListChangedBlocks","ListSnapshotBlocks","PutSnapshotBlock","StartSnapshot"] | D68: arn:aws:ebs:${Region}:${Account}:${ResourceType}/${ResourcePath} | E68: ^arn:aws:ebs:.+ | F68: ["aws:RequestTag/${TagKey}","aws:ResourceTag/${TagKey}","aws:TagKeys","ebs:Description","ebs:ParentSnapshot","ebs:VolumeSize"] | G68: TRUE | H68: https://docs.aws.amazon.com/service-authorization/latest/UserGuide/list_amazonelasticblockstore.html
A69: ecr | B69: Amazon Elastic Container Registry | C69: ["BatchCheckLayerAvailability","BatchDeleteImage","BatchGetImage","BatchGetRepositoryScanningConfiguration","BatchImportUpstreamImage","CompleteLayerUpload","CreatePullThroughCacheRule","CreateRepository","CreateRepositoryCreationTemplate","DeleteLifecyclePolicy","DeletePullThroughCacheRule","DeleteRegistryPolicy","DeleteRepository","DeleteRepositoryCreationTemplate","DeleteRepositoryPolicy","DeleteSigningConfiguration","DeregisterPullTimeUpdateExclusion","DescribeImageReplicationStatus","DescribeImageScanFindings","DescribeImageSigningStatus","DescribeImages","DescribePullThroughCacheRules","DescribeRegistry","DescribeRepositories","DescribeRepositoryCreationTemplates","GetAccountSetting","GetAuthorizationToken","GetDownloadUrlForLayer","GetImageCopyStatus","GetLifecyclePolicy","GetLifecyclePolicyPreview","GetRegistryPolicy","GetRegistryScanningConfiguration","GetRepositoryPolicy","GetSigningConfiguration","InitiateLayerUpload","ListImages","ListPullTimeUpdateExclusions","ListTagsForResource","PutAccountSetting","PutImage","PutImageScanningConfiguration","PutImageTagMutability","PutLifecyclePolicy","PutRegistryPolicy","PutRegistryScanningConfiguration","PutReplicationConfiguration","PutSigningConfiguration","RegisterPullTimeUpdateExclusion","ReplicateImage","SetRepositoryPolicy","StartImageScan","StartLifecyclePolicyPreview","TagResource","UntagResource","UpdateImageStorageClass","UpdatePullThroughCacheRule","UpdateRepositoryCreationTemplate","UploadLayerPart","ValidatePullThroughCacheRule"] | D69: arn:aws:ecr:${Region}:${Account}:repository/${RepositoryName} | E69: ^arn:aws:ecr:.+ | F69: ["aws:RequestTag/${TagKey}","aws:ResourceTag/${TagKey}","aws:TagKeys","ecr:AccountSetting","ecr:ResourceTag/${TagKey}"] | G69: TRUE | H69: https://docs.aws.amazon.com/service-authorization/latest/UserGuide/list_amazonelasticcontainerregistry.html
A70: ecr-public | B70: Amazon Elastic Container Registry Public | C70: ["BatchCheckLayerAvailability","BatchDeleteImage","CompleteLayerUpload","CreateRepository","DeleteRepository","DeleteRepositoryPolicy","DescribeImageTags","DescribeImages","DescribeRegistries","DescribeRepositories","GetAuthorizationToken","GetRegistryCatalogData","GetRepositoryCatalogData","GetRepositoryPolicy","InitiateLayerUpload","ListTagsForResource","PutImage","PutRegistryCatalogData","PutRepositoryCatalogData","SetRepositoryPolicy","TagResource","UntagResource","UploadLayerPart"] | D70: arn:aws:ecr-public::${Account}:${RepositoryOrRegistry}/${RepositoryNameOrAccountId} | E70: ^arn:aws:ecr-public::.+ | F70: ["aws:RequestTag/${TagKey}","aws:ResourceTag/${TagKey}","aws:TagKeys","ecr-public:ResourceTag/${TagKey}"] | G70: TRUE | H70: https://docs.aws.amazon.com/service-authorization/latest/UserGuide/list_amazonelasticcontainerregistrypublic.html
A71: ecs | B71: Amazon Elastic Container Service | C71: ["AllowVendedLogDeliveryForResource","ContinueServiceDeployment","CreateCapacityProvider","CreateCluster","CreateDaemon","CreateExpressGatewayService","CreateService","CreateTaskSet","DeleteAccountSetting","DeleteAttributes","DeleteCapacityProvider","DeleteCluster","DeleteDaemon","DeleteDaemonTaskDefinition","DeleteExpressGatewayService","DeleteService","DeleteTaskDefinitions","DeleteTaskSet","DeregisterContainerInstance","DeregisterTaskDefinition","DescribeCapacityProviders","DescribeClusters","DescribeContainerInstances","DescribeDaemon","DescribeDaemonDeployments","DescribeDaemonRevisions","DescribeDaemonTaskDefinition","DescribeExpressGatewayService","DescribeServiceDeployments","DescribeServiceRevisions","DescribeServices","DescribeTaskDefinition","DescribeTaskSets","DescribeTasks","DiscoverPollEndpoint","ExecuteCommand","GetTaskProtection","ListAccountSettings","ListAttributes","ListClusters","ListContainerInstances","ListDaemonDeployments","ListDaemonTaskDefinitions","ListDaemons","ListServiceDeployments","ListServices","ListServicesByNamespace","ListTagsForResource","ListTaskDefinitionFamilies","ListTaskDefinitions","ListTasks","Poll","PutAccountSetting","PutAccountSettingDefault","PutAttributes","PutClusterCapacityProviders","PutSystemLogEvents","RegisterContainerInstance","RegisterDaemonTaskDefinition","RegisterTaskDefinition","RunTask","StartTask","StartTelemetrySession","StopServiceDeployment","StopTask","SubmitAttachmentStateChanges","SubmitContainerStateChange","SubmitTaskStateChange","TagResource","UntagResource","UpdateCapacityProvider","UpdateCluster","UpdateClusterSettings","UpdateContainerAgent","UpdateContainerInstancesState","UpdateDaemon","UpdateExpressGatewayService","UpdateService","UpdateServicePrimaryTaskSet","UpdateTaskProtection","UpdateTaskSet"] | D71: arn:aws:ecs:${Region}:${Account}:${ResourceType}/${ResourcePath} | E71: ^arn:aws:ecs:.+:.+:.+ | F71: ["aws:RequestTag/${TagKey}","aws:ResourceTag/${TagKey}","aws:TagKeys","ecs:CreateAction","ecs:ResourceTag/${TagKey}","ecs:account-setting","ecs:auto-assign-public-ip","ecs:capacity-provider","ecs:cluster","ecs:compute-compatibility","ecs:container-instances","ecs:container-name","ecs:daemon","ecs:daemon-task-definition","ecs:enable-ebs-volumes","ecs:enable-ecs-managed-tags","ecs:enable-execute-command","ecs:enable-service-connect","ecs:enable-vpc-lattice","ecs:fargate-ephemeral-storage-kms-key","ecs:gateway","ecs:instance-metadata-tags-propagation","ecs:namespace","ecs:privileged","ecs:propagate-tags","ecs:service","ecs:subnet","ecs:task","ecs:task-cpu","ecs:task-definition","ecs:task-memory"] | G71: TRUE | H71: https://docs.aws.amazon.com/service-authorization/latest/UserGuide/list_amazonelasticcontainerservice.html
A72: elasticfilesystem | B72: Amazon Elastic File System | C72: ["Backup","ClientMount","ClientRootAccess","ClientWrite","CreateAccessPoint","CreateFileSystem","CreateMountTarget","CreateReplicationConfiguration","CreateTags","DeleteAccessPoint","DeleteFileSystem","DeleteFileSystemPolicy","DeleteMountTarget","DeleteReplicationConfiguration","DeleteTags","DescribeAccessPoints","DescribeAccountPreferences","DescribeBackupPolicy","DescribeFileSystemPolicy","DescribeFileSystems","DescribeLifecycleConfiguration","DescribeMountTargetSecurityGroups","DescribeMountTargets","DescribeReplicationConfigurations","DescribeTags","ListTagsForResource","ModifyMountTargetSecurityGroups","PutAccountPreferences","PutBackupPolicy","PutFileSystemPolicy","PutLifecycleConfiguration","ReplicationRead","ReplicationWrite","Restore","TagResource","UntagResource","UpdateFileSystem","UpdateFileSystemProtection"] | D72: arn:aws:elasticfilesystem:${Region}:${Account}:${ResourceType}/${ResourcePath} | E72: ^arn:aws:elasticfilesystem:.+ | F72: ["aws:RequestTag/${TagKey}","aws:ResourceTag/${TagKey}","aws:TagKeys","elasticfilesystem:AccessPointArn","elasticfilesystem:AccessedViaMountTarget","elasticfilesystem:CreateAction","elasticfilesystem:Encrypted"] | G72: TRUE | H72: https://docs.aws.amazon.com/service-authorization/latest/UserGuide/list_amazonelasticfilesystem.html
A73: eks | B73: Amazon Elastic Kubernetes Service | C73: ["AccessKubernetesApi","ActivateCertificateAuthority","AssociateAccessPolicy","AssociateEncryptionConfig","AssociateIdentityProviderConfig","CancelUpdate","CreateAccessEntry","CreateAddon","CreateCapability","CreateCertificateAuthority","CreateCluster","CreateEksAnywhereSubscription","CreateFargateProfile","CreateNodegroup","CreatePodIdentityAssociation","DeleteAccessEntry","DeleteAddon","DeleteCapability","DeleteCertificateAuthority","DeleteCluster","DeleteEksAnywhereSubscription","DeleteFargateProfile","DeleteNodegroup","DeletePodIdentityAssociation","DeregisterCluster","DescribeAccessEntry","DescribeAddon","DescribeAddonConfiguration","DescribeAddonVersions","DescribeCapability","DescribeCertificateAuthority","DescribeCluster","DescribeClusterVersions","DescribeEksAnywhereSubscription","DescribeFargateProfile","DescribeIdentityProviderConfig","DescribeInsight","DescribeInsightsRefresh","DescribeNodegroup","DescribePodIdentityAssociation","DescribeUpdate","DisassociateAccessPolicy","DisassociateIdentityProviderConfig","ListAccessEntries","ListAccessPolicies","ListAddons","ListAssociatedAccessPolicies","ListCapabilities","ListCertificateAuthorities","ListClusters","ListDashboardData","ListDashboardResources","ListEksAnywhereSubscriptions","ListFargateProfiles","ListIdentityProviderConfigs","ListInsights","ListNodegroups","ListPodIdentityAssociations","ListTagsForResource","ListUpdates","MutateViaKubernetesApi","RegisterCluster","StartInsightsRefresh","TagResource","UntagResource","UpdateAccessEntry","UpdateAddon","UpdateCapability","UpdateClusterConfig","UpdateClusterVersion","UpdateEksAnywhereSubscription","UpdateNodegroupConfig","UpdateNodegroupVersion","UpdatePodIdentityAssociation"] | D73: arn:aws:eks:${Region}:${Account}:${ResourceType}/${RelativeId} | E73: ^arn:aws:eks:.+ | F73: ["aws:RequestTag/${TagKey}","aws:ResourceTag/${TagKey}","aws:TagKeys","eks:accessEntryType","eks:accessScope","eks:authenticationMode","eks:blockStorageEnabled","eks:bootstrapClusterCreatorAdminPermissions","eks:bootstrapSelfManagedAddons","eks:clientId","eks:clusterName","eks:computeConfigEnabled","eks:controlPlaneEgressMode","eks:controlPlaneScalingTier","eks:deletionProtection","eks:elasticLoadBalancingEnabled","eks:encryptionConfigProviderKeyArns","eks:endpointPrivateAccess","eks:endpointPublicAccess","eks:issuerUrl","eks:kubeApiServerConfig","eks:kubeControllerManagerConfig","eks:kubeSchedulerConfig","eks:kubernetesGroups","eks:kubernetesVersion","eks:loggingType/${type}","eks:namespaces","eks:policyArn","eks:principalArn","eks:supportType","eks:username","eks:zonalShiftEnabled"] | G73: TRUE | H73: https://docs.aws.amazon.com/service-authorization/latest/UserGuide/list_amazonelastickubernetesservice.html
A74: elasticmapreduce | B74: Amazon Elastic MapReduce | C74: ["AccessAllEventLogs","AddInstanceFleet","AddInstanceGroups","AddJobFlowSteps","AddTags","AttachEditor","CancelSteps","CreateEditor","CreatePersistentAppUI","CreateRepository","CreateSecurityConfiguration","CreateStudio","CreateStudioPresignedUrl","CreateStudioSessionMapping","DeleteEditor","DeleteRepository","DeleteSecurityConfiguration","DeleteStudio","DeleteStudioSessionMapping","DeleteWorkspaceAccess","DescribeCluster","DescribeEditor","DescribeJobFlows","DescribeNotebookExecution","DescribePersistentAppUI","DescribeReleaseLabel","DescribeRepository","DescribeSecurityConfiguration","DescribeStep","DescribeStudio","DetachEditor","GetAutoTerminationPolicy","GetBlockPublicAccessConfiguration","GetClusterSessionCredentials","GetManagedScalingPolicy","GetOnClusterAppUIPresignedURL","GetPersistentAppUIPresignedURL","GetSession","GetSessionEndpoint","GetStudioSessionMapping","LinkRepository","ListBootstrapActions","ListClusters","ListEditors","ListInstanceFleets","ListInstanceGroups","ListInstances","ListNotebookExecutions","ListReleaseLabels","ListRepositories","ListSecurityConfigurations","ListSessions","ListSteps","ListStudioSessionMappings","ListStudios","ListSupportedInstanceTypes","ListWorkspaceAccessIdentities","ModifyCluster","ModifyInstanceFleet","ModifyInstanceGroups","OpenEditorInConsole","PutAutoScalingPolicy","PutAutoTerminationPolicy","PutBlockPublicAccessConfiguration","PutManagedScalingPolicy","PutWorkspaceAccess","RemoveAutoScalingPolicy","RemoveAutoTerminationPolicy","RemoveManagedScalingPolicy","RemoveTags","RunJobFlow","SetKeepJobFlowAliveWhenNoSteps","SetTerminationProtection","SetUnhealthyNodeReplacement","SetVisibleToAllUsers","StartEditor","StartNotebookExecution","StartSession","StopEditor","StopNotebookExecution","TerminateJobFlows","TerminateSession","UnlinkRepository","UpdateEditor","UpdateRepository","UpdateStudio","UpdateStudioSessionMapping","ViewEventsFromAllClustersInConsole"] | D74: arn:aws:elasticmapreduce:${Region}:${Account}:${ResourceType}/${ResourceId} | E74: ^arn:aws:elasticmapreduce:.+ | F74: ["aws:RequestTag/${TagKey}","aws:ResourceTag/${TagKey}","aws:TagKeys","elasticmapreduce:ExecutionRoleArn","elasticmapreduce:RequestTag/${TagKey}","elasticmapreduce:ResourceTag/${TagKey}"] | G74: TRUE | H74: https://docs.aws.amazon.com/service-authorization/latest/UserGuide/list_amazonelasticmapreduce.html
A75: elastictranscoder | B75: Amazon Elastic Transcoder | C75: ["CancelJob","CreateJob","CreatePipeline","CreatePreset","DeletePipeline","DeletePreset","ListJobsByPipeline","ListJobsByStatus","ListPipelines","ListPresets","ReadJob","ReadPipeline","ReadPreset","TestRole","UpdatePipeline","UpdatePipelineNotifications","UpdatePipelineStatus"] | D75: arn:aws:elastictranscoder:${Region}:${Account}:${ResourceType}/${ResourceId} | E75: ^arn:aws:elastictranscoder:.+ | F75: null | G75: TRUE | H75: https://docs.aws.amazon.com/service-authorization/latest/UserGuide/list_amazonelastictranscoder.html
A76: evs | B76: Amazon Elastic VMware Service | C76: ["AssociateEipToVlan","CreateEntitlement","CreateEnvironment","CreateEnvironmentConnector","CreateEnvironmentHost","DeleteEntitlement","DeleteEnvironment","DeleteEnvironmentConnector","DeleteEnvironmentHost","DisassociateEipFromVlan","GetAccountSettings","GetDepotUrl","GetEnvironment","GetVersions","ListEnvironmentConnectors","ListEnvironmentHosts","ListEnvironmentVlans","ListEnvironments","ListTagsForResource","ListVmEntitlements","PutAccountSettings","TagResource","UntagResource","UpdateEnvironmentConnector"] | D76: arn:aws:evs:${Region}:${Account}:${ResourceType}/${ResourcePath} | E76: ^arn:aws:evs:.+:.+:.+ | F76: ["aws:RequestTag/${TagKey}","aws:ResourceTag/${TagKey}","aws:TagKeys"] | G76: TRUE | H76: https://docs.aws.amazon.com/service-authorization/latest/UserGuide/list_amazonelasticvmwareservice.html
A77: elasticache | B77: Amazon ElastiCache | C77: ["AddTagsToResource","AuthorizeCacheSecurityGroupIngress","BatchApplyUpdateAction","BatchStopUpdateAction","CompleteMigration","Connect","CopyServerlessCacheSnapshot","CopySnapshot","CreateCacheCluster","CreateCacheParameterGroup","CreateCacheSecurityGroup","CreateCacheSubnetGroup","CreateGlobalReplicationGroup","CreateReplicationGroup","CreateServerlessCache","CreateServerlessCacheSnapshot","CreateSnapshot","CreateUser","CreateUserGroup","DecreaseNodeGroupsInGlobalReplicationGroup","DecreaseReplicaCount","DeleteCacheCluster","DeleteCacheParameterGroup","DeleteCacheSecurityGroup","DeleteCacheSubnetGroup","DeleteGlobalReplicationGroup","DeleteReplicationGroup","DeleteServerlessCache","DeleteServerlessCacheSnapshot","DeleteSnapshot","DeleteUser","DeleteUserGroup","DescribeCacheClusters","DescribeCacheEngineVersions","DescribeCacheParameterGroups","DescribeCacheParameters","DescribeCacheSecurityGroups","DescribeCacheSubnetGroups","DescribeEngineDefaultParameters","DescribeEvents","DescribeGlobalReplicationGroups","DescribeReplicationGroups","DescribeReservedCacheNodes","DescribeReservedCacheNodesOfferings","DescribeServerlessCacheSnapshots","DescribeServerlessCaches","DescribeServiceUpdates","DescribeSnapshots","DescribeUpdateActions","DescribeUserGroups","DescribeUsers","DisassociateGlobalReplicationGroup","ExportServerlessCacheSnapshot","FailoverGlobalReplicationGroup","IncreaseNodeGroupsInGlobalReplicationGroup","IncreaseReplicaCount","InterruptClusterAzPower","ListAllowedNodeTypeModifications","ListTagsForResource","ModifyCacheCluster","ModifyCacheParameterGroup","ModifyCacheSubnetGroup","ModifyGlobalReplicationGroup","ModifyReplicationGroup","ModifyReplicationGroupShardConfiguration","ModifyServerlessCache","ModifyUser","ModifyUserGroup","PurchaseReservedCacheNodesOffering","RebalanceSlotsInGlobalReplicationGroup","RebootCacheCluster","RemoveTagsFromResource","ResetCacheParameterGroup","RevokeCacheSecurityGroupIngress","StartMigration","TestFailover","TestMigration"] | D77: arn:aws:elasticache:${Region}:${Account}:${ResourceType}:${ResourceName} | E77: ^arn:aws:elasticache:.+:.+:.+ | F77: ["aws:RequestTag/${TagKey}","aws:ResourceTag/${TagKey}","aws:TagKeys","elasticache:AtRestEncryptionEnabled","elasticache:AuthTokenEnabled","elasticache:AutomaticFailoverEnabled","elasticache:CacheNodeType","elasticache:CacheParameterGroupName","elasticache:ClusterModeEnabled","elasticache:DataStorageUnit","elasticache:Durability","elasticache:EngineType","elasticache:EngineVersion","elasticache:KmsKeyId","elasticache:MaximumDataStorage","elasticache:MaximumECPUPerSecond","elasticache:MinimumDataStorage","elasticache:MinimumECPUPerSecond","elasticache:MultiAZEnabled","elasticache:NumNodeGroups","elasticache:ReplicasPerNodeGroup","elasticache:SnapshotRetentionLimit","elasticache:TransitEncryptionEnabled","elasticache:UserAuthenticationMode"] | G77: TRUE | H77: https://docs.aws.amazon.com/service-authorization/latest/UserGuide/list_amazonelasticache.html
... A94: honeycode | B94: Amazon Honeycode | C94: ["ApproveTeamAssociation","BatchCreateTableRows","BatchDeleteTableRows","BatchUpdateTableRows","BatchUpsertTableRows","CreateTeam","CreateTenant","DeleteDomains","DeregisterGroups","DescribeTableDataImportJob","DescribeTeam","GetScreenData","InvokeScreenAutomation","ListDomains","ListGroups","ListTableColumns","ListTableRows","ListTables","ListTagsForResource","ListTeamAssociations","ListTenants","QueryTableRows","RegisterDomainForVerification","RegisterGroups","RejectTeamAssociation","RestartDomainVerification","StartTableDataImportJob","TagResource","UntagResource","UpdateTeam"] | D94: arn:aws:honeycode:${Region}:${Account}:${ResourceType}:${ResourcePath} | E94: ^arn:aws:honeycode:.+:.+:.+ | F94: null | G94: TRUE | H94: https://docs.aws.amazon.com/service-authorization/latest/UserGuide/list_amazonhoneycode.html
A95: inspector | B95: Amazon Inspector | C95: ["AddAttributesToFindings","CreateAssessmentTarget","CreateAssessmentTemplate","CreateExclusionsPreview","CreateResourceGroup","DeleteAssessmentRun","DeleteAssessmentTarget","DeleteAssessmentTemplate","DescribeAssessmentRuns","DescribeAssessmentTargets","DescribeAssessmentTemplates","DescribeCrossAccountAccessRole","DescribeExclusions","DescribeFindings","DescribeResourceGroups","DescribeRulesPackages","GetAssessmentReport","GetExclusionsPreview","GetTelemetryMetadata","ListAssessmentRunAgents","ListAssessmentRuns","ListAssessmentTargets","ListAssessmentTemplates","ListEventSubscriptions","ListExclusions","ListFindings","ListRulesPackages","ListTagsForResource","PreviewAgents","RegisterCrossAccountAccessRole","RemoveAttributesFromFindings","SetTagsForResource","StartAssessmentRun","StopAssessmentRun","SubscribeToEvent","UnsubscribeFromEvent","UpdateAssessmentTarget"] | F95: null | G95: FALSE | H95: https://docs.aws.amazon.com/service-authorization/latest/UserGuide/list_amazoninspector.html
A96: inspector2 | B96: Amazon Inspector2 | C96: ["AssociateMember","BatchAssociateCodeSecurityScanConfiguration","BatchDisassociateCodeSecurityScanConfiguration","BatchGetAccountStatus","BatchGetCodeSnippet","BatchGetFindingDetails","BatchGetFreeTrialInfo","BatchGetMemberEc2DeepInspectionStatus","BatchUpdateMemberEc2DeepInspectionStatus","CancelFindingsReport","CancelSbomExport","CreateCisScanConfiguration","CreateCodeSecurityIntegration","CreateCodeSecurityScanConfiguration","CreateConnector","CreateFilter","CreateFindingsReport","CreateSbomExport","DeleteCisScanConfiguration","DeleteCodeSecurityIntegration","DeleteCodeSecurityScanConfiguration","DeleteConnector","DeleteFilter","DescribeOrganizationConfiguration","Disable","DisableDelegatedAdminAccount","DisassociateMember","Enable","EnableDelegatedAdminAccount","GetCisScanReport","GetCisScanResultDetails","GetClustersForImage","GetCodeSecurityIntegration","GetCodeSecurityScan","GetCodeSecurityScanConfiguration","GetConfiguration","GetDelegatedAdminAccount","GetEc2DeepInspectionConfiguration","GetEncryptionKey","GetFindingsReportStatus","GetMember","GetSbomExport","ListAccountPermissions","ListCisScanConfigurations","ListCisScanResultsAggregatedByChecks","ListCisScanResultsAggregatedByTargetResource","ListCisScans","ListCodeSecurityIntegrations","ListCodeSecurityScanConfigurationAssociations","ListCodeSecurityScanConfigurations","ListConnectorScanConfigurations","ListConnectors","ListCoverage","ListCoverageStatistics","ListDelegatedAdminAccounts","ListFilters","ListFindingAggregations","ListFindings","ListMembers","ListTagsForResource","ListUsageTotals","ResetEncryptionKey","SearchVulnerabilities","SendCisSessionHealth","SendCisSessionTelemetry","StartCisSession","StartCodeSecurityScan","StopCisSession","TagResource","UntagResource","UpdateCisScanConfiguration","UpdateCodeSecurityIntegration","UpdateCodeSecurityScanConfiguration","UpdateConfiguration","UpdateConnector","UpdateConnectorScanConfiguration","UpdateEc2DeepInspectionConfiguration","UpdateEncryptionKey","UpdateFilter","UpdateOrgEc2DeepInspectionConfiguration","UpdateOrganizationConfiguration"] | D96: arn:aws:inspector2:${Region}:${Account}:.+ | E96: ^arn:aws:inspector2:.+:.+:.+ | F96: ["aws:RequestTag/${TagKey}","aws:ResourceTag/${TagKey}","aws:TagKeys"] | G96: TRUE | H96: https://docs.aws.amazon.com/service-authorization/latest/UserGuide/list_amazoninspector2.html
A97: inspector2-telemetry | B97: Amazon Inspector2 Telemetry Channel | C97: ["NotifyHeartbeat","SendTelemetry","SendTelemetryEvent","StartSession","StopSession"] | F97: null | G97: FALSE | H97: https://docs.aws.amazon.com/service-authorization/latest/UserGuide/list_amazoninspector2telemetrychannel.html
A98: inspector-scan | B98: Amazon InspectorScan | C98: "ScanSbom" | F98: null | G98: FALSE | H98: https://docs.aws.amazon.com/service-authorization/latest/UserGuide/list_amazoninspectorscan.html
A99: ivs | B99: Amazon Interactive Video Service | C99: ["BatchGetChannel","BatchGetStreamKey","BatchStartViewerSessionRevocation","CreateAdConfiguration","CreateChannel","CreateEncoderConfiguration","CreateIngestConfiguration","CreateParticipantToken","CreatePlaybackRestrictionPolicy","CreateRecordingConfiguration","CreateStage","CreateStorageConfiguration","CreateStreamKey","DeleteAdConfiguration","DeleteChannel","DeleteEncoderConfiguration","DeleteIngestConfiguration","DeletePlaybackKeyPair","DeletePlaybackRestrictionPolicy","DeletePublicKey","DeleteRecordingConfiguration","DeleteStage","DeleteStorageConfiguration","DeleteStreamKey","DisconnectParticipant","GetAdConfiguration","GetChannel","GetComposition","GetEncoderConfiguration","GetIngestConfiguration","GetParticipant","GetPlaybackKeyPair","GetPlaybackRestrictionPolicy","GetPublicKey","GetRecordingConfiguration","GetStage","GetStageSession","GetStorageConfiguration","GetStream","GetStreamKey","GetStreamSession","ImportPlaybackKeyPair","ImportPublicKey","InsertAdBreak","ListAdConfigurations","ListChannels","ListCompositions","ListEncoderConfigurations","ListIngestConfigurations","ListParticipantEvents","ListParticipantReplicas","ListParticipants","ListPlaybackKeyPairs","ListPlaybackRestrictionPolicies","ListPublicKeys","ListRecordingConfigurations","ListStageSessions","ListStages","ListStorageConfigurations","ListStreamKeys","ListStreamSessions","ListStreams","ListTagsForResource","PutMetadata","StartComposition","StartParticipantReplication","StartViewerSessionRevocation","StopComposition","StopParticipantReplication","StopStream","TagResource","UntagResource","UpdateAdConfiguration","UpdateChannel","UpdateIngestConfiguration","UpdatePlaybackRestrictionPolicy","UpdateStage"] | D99: arn:aws:ivs:${Region}:${Account}:${ArnType}/${ResourceId} | E99: ^arn:aws:ivs:.+:.+:.+ | F99: ["aws:RequestTag/${TagKey}","aws:ResourceTag/${TagKey}","aws:TagKeys"] | G99: TRUE | H99: https://docs.aws.amazon.com/service-authorization/latest/UserGuide/list_amazoninteractivevideoservice.html
A100: ivschat | B100: Amazon Interactive Video Service Chat | C100: ["CreateChatToken","CreateLoggingConfiguration","CreateRoom","DeleteLoggingConfiguration","DeleteMessage","DeleteRoom","DisconnectUser","GetLoggingConfiguration","GetRoom","ListLoggingConfigurations","ListRooms","ListTagsForResource","SendEvent","TagResource","UntagResource","UpdateLoggingConfiguration","UpdateRoom"] | D100: arn:aws:ivschat:${Region}:${Account}:${ResourceType}/${ResourceId} | E100: ^arn:aws:ivschat:.+:.+:.+ | F100: ["aws:RequestTag/${TagKey}","aws:ResourceTag/${TagKey}","aws:TagKeys"] | G100: TRUE | H100: https://docs.aws.amazon.com/service-authorization/latest/UserGuide/list_amazoninteractivevideoservicechat.html
A101: kendra | B101: Amazon Kendra | C101: ["AssociateEntitiesToExperience","AssociatePersonasToEntities","BatchDeleteDocument","BatchDeleteFeaturedResultsSet","BatchGetDocumentStatus","BatchPutDocument","ClearQuerySuggestions","CreateAccessControlConfiguration","CreateDataSource","CreateExperience","CreateFaq","CreateFeaturedResultsSet","CreateIndex","CreateQuerySuggestionsBlockList","CreateThesaurus","DeleteAccessControlConfiguration","DeleteDataSource","DeleteExperience","DeleteFaq","DeleteIndex","DeletePrincipalMapping","DeleteQuerySuggestionsBlockList","DeleteThesaurus","DescribeAccessControlConfiguration","DescribeDataSource","DescribeExperience","DescribeFaq","DescribeFeaturedResultsSet","DescribeIndex","DescribePrincipalMapping","DescribeQuerySuggestionsBlockList","DescribeQuerySuggestionsConfig","DescribeThesaurus","DisassociateEntitiesFromExperience","DisassociatePersonasFromEntities","GetQuerySuggestions","GetSnapshots","ListAccessControlConfigurations","ListDataSourceSyncJobs","ListDataSources","ListEntityPersonas","ListExperienceEntities","ListExperiences","ListFaqs","ListFeaturedResultsSets","ListGroupsOlderThanOrderingId","ListIndices","ListQuerySuggestionsBlockLists","ListTagsForResource","ListThesauri","PutPrincipalMapping","Query","Retrieve","StartDataSourceSyncJob","StopDataSourceSyncJob","SubmitFeedback","TagResource","UntagResource","UpdateAccessControlConfiguration","UpdateDataSource","UpdateExperience","UpdateFeaturedResultsSet","UpdateIndex","UpdateQuerySuggestionsBlockList","UpdateQuerySuggestionsConfig","UpdateThesaurus"] | D101: arn:aws:kendra:${Region}:${Account}:${ResourceType}/${ResourceName} | E101: ^arn:aws:kendra:.+:.+:.+ | F101: ["aws:RequestTag/${TagKey}","aws:ResourceTag/${TagKey}","aws:TagKeys"] | G101: TRUE | H101: https://docs.aws.amazon.com/service-authorization/latest/UserGuide/list_amazonkendra.html
A102: kendra-ranking | B102: Amazon Kendra Intelligent Ranking | C102: ["CreateRescoreExecutionPlan","DeleteRescoreExecutionPlan","DescribeRescoreExecutionPlan","ListRescoreExecutionPlans","ListTagsForResource","Rescore","TagResource","UntagResource","UpdateRescoreExecutionPlan"] | D102: arn:aws:kendra-ranking:${Region}:${Account}:${ResourceType}/${ResourceName} | E102: ^arn:aws:kendra-ranking:.+:.+:.+ | F102: ["aws:RequestTag/${TagKey}","aws:ResourceTag/${TagKey}","aws:TagKeys"] | G102: TRUE | H102: https://docs.aws.amazon.com/service-authorization/latest/UserGuide/list_amazonkendraintelligentranking.html
A103: cassandra | B103: Amazon Keyspaces (for Apache Cassandra) | C103: ["Alter","AlterMultiRegionResource","Create","CreateMultiRegionResource","Drop","DropMultiRegionResource","GetRecords","GetShardIterator","GetStream","ListStreams","Modify","ModifyMultiRegionResource","Restore","RestoreMultiRegionTable","Select","SelectMultiRegionResource","TagMultiRegionResource","TagResource","UnTagMultiRegionResource","UntagResource","UpdatePartitioner"] | D103: arn:aws:cassandra:${Region}:${Account}:/${ResourceType}/${ResourcePath}/ | E103: ^arn:aws:cassandra:.+ | F103: ["aws:RequestTag/${TagKey}","aws:ResourceTag/${TagKey}","aws:TagKeys"] | G103: TRUE | H103: https://docs.aws.amazon.com/service-authorization/latest/UserGuide/list_amazonkeyspacesforapachecassandra.html
A104: kinesisanalytics | B104: Amazon Kinesis Analytics | C104: ["AddApplicationInput","AddApplicationOutput","AddApplicationReferenceDataSource","CreateApplication","DeleteApplication","DeleteApplicationOutput","DeleteApplicationReferenceDataSource","DescribeApplication","DiscoverInputSchema","GetApplicationState","ListApplications","ListTagsForResource","StartApplication","StopApplication","TagResource","UntagResource","UpdateApplication"] | D104: arn:aws:kinesisanalytics:${Region}:${Account}:application/${ApplicationName} | E104: ^arn:aws:kinesisanalytics:.+:[0-9]+:application/[a-zA-Z0-9_.-]+ | F104: ["aws:RequestTag/${TagKey}","aws:ResourceTag/${TagKey}","aws:TagKeys"] | G104: TRUE | H104: https://docs.aws.amazon.com/service-authorization/latest/UserGuide/list_amazonkinesisanalytics.html
A105: kinesisanalytics | B105: Amazon Kinesis Analytics V2 | C105: ["AddApplicationCloudWatchLoggingOption","AddApplicationInput","AddApplicationInputProcessingConfiguration","AddApplicationOutput","AddApplicationReferenceDataSource","AddApplicationVpcConfiguration","CreateApplication","CreateApplicationPresignedUrl","CreateApplicationSnapshot","DeleteApplication","DeleteApplicationCloudWatchLoggingOption","DeleteApplicationInputProcessingConfiguration","DeleteApplicationOutput","DeleteApplicationReferenceDataSource","DeleteApplicationSnapshot","DeleteApplicationVpcConfiguration","DescribeApplication","DescribeApplicationOperation","DescribeApplicationSnapshot","DescribeApplicationVersion","DiscoverInputSchema","ListApplicationOperations","ListApplicationSnapshots","ListApplicationVersions","ListApplications","ListTagsForResource","RollbackApplication","StartApplication","StopApplication","TagResource","UntagResource","UpdateApplication","UpdateApplicationMaintenanceConfiguration"] | D105: arn:aws:kinesisanalytics:${Region}:${Account}:application/${ApplicationName} | E105: ^arn:aws:kinesisanalytics:.+:[0-9]+:application/[a-zA-Z0-9_.-]+ | F105: ["aws:RequestTag/${TagKey}","aws:ResourceTag/${TagKey}","aws:TagKeys"] | G105: TRUE | H105: https://docs.aws.amazon.com/service-authorization/latest/UserGuide/list_amazonkinesisanalyticsv2.html
A106: kinesis | B106: Amazon Kinesis Data Streams | C106: ["AddTagsToStream","AssociateStreamsWithChannel","CreateChannel","CreateStream","DecreaseStreamRetentionPeriod","DeleteChannel","DeleteResourcePolicy","DeleteStream","DeregisterStreamConsumer","DescribeAccountSettings","DescribeChannel","DescribeLimits","DescribeStream","DescribeStreamConsumer","DescribeStreamSummary","DisableEnhancedMonitoring","EnableEnhancedMonitoring","GetRecords","GetResourcePolicy","GetShardIterator","IncreaseStreamRetentionPeriod","InjectApiError","ListChannels","ListShards","ListStreamConsumers","ListStreams","ListTagsForResource","ListTagsForStream","MergeShards","PutRecord","PutRecords","PutResourcePolicy","RegisterStreamConsumer","RemoveTagsFromStream","SplitShard","StartStreamEncryption","StopStreamEncryption","SubscribeToShard","TagResource","UntagResource","UpdateAccountSettings","UpdateChannel","UpdateMaxRecordSize","UpdateShardCount","UpdateStreamMode","UpdateStreamRecordDistributionStrategy","UpdateStreamWarmThroughput"] | D106: arn:aws:kinesis:${Region}:${Account}:${ResourceType}/${ResourceName} | E106: ^arn:aws:kinesis:.+ | F106: ["aws:RequestTag/${TagKey}","aws:ResourceTag/${TagKey}","aws:TagKeys","kinesis:FisActionId","kinesis:FisInjectPercentage","kinesis:FisTargetArns"] | G106: TRUE | H106: https://docs.aws.amazon.com/service-authorization/latest/UserGuide/list_amazonkinesisdatastreams.html
A107: firehose | B107: Amazon Kinesis Firehose | C107: ["CreateDeliveryStream","DeleteDeliveryStream","DescribeDeliveryStream","ListDeliveryStreams","ListTagsForDeliveryStream","PutRecord","PutRecordBatch","StartDeliveryStreamEncryption","StopDeliveryStreamEncryption","TagDeliveryStream","UntagDeliveryStream","UpdateDestination"] | D107: arn:aws:firehose:${Region}:${Account}:deliverystream/${DeliveryStreamName} | E107: ^arn:aws:firehose:.+:[0-9]+:deliverystream/.+ | F107: ["aws:RequestTag/${TagKey}","aws:ResourceTag/${TagKey}","aws:TagKeys"] | G107: TRUE | H107: https://docs.aws.amazon.com/service-authorization/latest/UserGuide/list_amazonkinesisfirehose.html
A108: kinesisvideo | B108: Amazon Kinesis Video Streams | C108: ["ConnectAsMaster","ConnectAsViewer","CreateSignalingChannel","CreateStream","DeleteEdgeConfiguration","DeleteSignalingChannel","DeleteStream","DescribeEdgeConfiguration","DescribeImageGenerationConfiguration","DescribeMappedResourceConfiguration","DescribeMediaStorageConfiguration","DescribeNotificationConfiguration","DescribeSignalingChannel","DescribeStream","DescribeStreamStorageConfiguration","GetClip","GetDASHStreamingSessionURL","GetDataEndpoint","GetHLSStreamingSessionURL","GetIceServerConfig","GetImages","GetMedia","GetMediaForFragmentList","GetSignalingChannelEndpoint","JoinStorageSession","JoinStorageSessionAsViewer","ListEdgeAgentConfigurations","ListFragments","ListSignalingChannels","ListStreams","ListTagsForResource","ListTagsForStream","PutMedia","SendAlexaOfferToMaster","StartEdgeConfigurationUpdate","TagResource","TagStream","UntagResource","UntagStream","UpdateDataRetention","UpdateImageGenerationConfiguration","UpdateMediaStorageConfiguration","UpdateNotificationConfiguration","UpdateSignalingChannel","UpdateStream","UpdateStreamStorageConfiguration"] | D108: arn:aws:kinesisvideo:${Region}:${Account}:${ResourceType}/${ResourceName}/${CreationTime} | E108: ^arn:aws:kinesisvideo:.+ | F108: ["aws:RequestTag/${TagKey}","aws:ResourceTag/${TagKey}","aws:TagKeys"] | G108: TRUE | H108: https://docs.aws.amazon.com/service-authorization/latest/UserGuide/list_amazonkinesisvideostreams.html
A109: lex | B109: Amazon Lex | C109: ["CreateBotVersion","CreateIntentVersion","CreateSlotTypeVersion","DeleteBot","DeleteBotAlias","DeleteBotChannelAssociation","DeleteBotVersion","DeleteIntent","DeleteIntentVersion","DeleteSession","DeleteSlotType","DeleteSlotTypeVersion","DeleteUtterances","GetBot","GetBotAlias","GetBotAliases","GetBotChannelAssociation","GetBotChannelAssociations","GetBotVersions","GetBots","GetBuiltinIntent","GetBuiltinIntents","GetBuiltinSlotTypes","GetExport","GetImport","GetIntent","GetIntentVersions","GetIntents","GetMigration","GetMigrations","GetSession","GetSlotType","GetSlotTypeVersions","GetSlotTypes","GetUtterancesView","ListTagsForResource","PostContent","PostText","PutBot","PutBotAlias","PutIntent","PutSession","PutSlotType","StartImport","StartMigration","TagResource","UntagResource"] | D109: arn:aws:lex:${Region}:${Account}:${Type}:${Name} | E109: ^arn:aws:lex:.+:[0-9]+:.+ | F109: ["aws:RequestTag/${TagKey}","aws:ResourceTag/${TagKey}","aws:TagKeys","lex:associatedIntents","lex:associatedSlotTypes","lex:channelType"] | G109: TRUE | H109: https://docs.aws.amazon.com/service-authorization/latest/UserGuide/list_amazonlex.html
A110: lex | B110: Amazon Lex V2 | C110: ["BatchCreateCustomVocabularyItem","BatchDeleteCustomVocabularyItem","BatchUpdateCustomVocabularyItem","BuildBotLocale","CreateBot","CreateBotAlias","CreateBotChannel","CreateBotLocale","CreateBotReplica","CreateBotVersion","CreateCustomVocabulary","CreateExport","CreateIntent","CreateResourcePolicy","CreateResourcePolicyStatement","CreateSlot","CreateSlotType","CreateTestSet","CreateTestSetDiscrepancyReport","CreateUploadUrl","DeleteBot","DeleteBotAlias","DeleteBotAnalyzerRecommendation","DeleteBotChannel","DeleteBotLocale","DeleteBotReplica","DeleteBotVersion","DeleteCustomVocabulary","DeleteExport","DeleteImport","DeleteIntent","DeleteResourcePolicy","DeleteResourcePolicyStatement","DeleteSession","DeleteSlot","DeleteSlotType","DeleteTestSet","DeleteUtterances","DescribeBot","DescribeBotAlias","DescribeBotAnalyzerRecommendation","DescribeBotChannel","DescribeBotLocale","DescribeBotRecommendation","DescribeBotReplica","DescribeBotResourceGeneration","DescribeBotVersion","DescribeCustomVocabulary","DescribeCustomVocabularyMetadata","DescribeExport","DescribeImport","DescribeIntent","DescribeResourcePolicy","DescribeSlot","DescribeSlotType","DescribeTestExecution","DescribeTestSet","DescribeTestSetDiscrepancyReport","DescribeTestSetGeneration","GenerateBotElement","GetSession","GetTestExecutionArtifactsUrl","ListAggregatedUtterances","ListBotAliasReplicas","ListBotAliases","ListBotAnalyzerRecommendations","ListBotChannels","ListBotLocales","ListBotRecommendations","ListBotReplicas","ListBotResourceGenerations","ListBotVersionReplicas","ListBotVersions","ListBots","ListBuiltInIntents","ListBuiltInSlotTypes","ListCustomVocabularyItems","ListExports","ListImports","ListIntentMetrics","ListIntentPaths","ListIntentStageMetrics","ListIntents","ListRecommendedIntents","ListSessionAnalyticsData","ListSessionMetrics","ListSlotTypes","ListSlots","ListTagsForResource","ListTestExecutionResultItems","ListTestExecutions","ListTestSetRecords","ListTestSets","PutSession","RecognizeText","RecognizeUtterance","SearchAssociatedTranscripts","StartBotAnalyzer","StartBotRecommendation","StartBotResourceGeneration","StartConversation","StartImport","StartTestExecution","StartTestSetGeneration","StopBotAnalyzer","StopBotRecommendation","TagResource","UntagResource","UpdateBot","UpdateBotAlias","UpdateBotLocale","UpdateBotRecommendation","UpdateCustomVocabulary","UpdateExport","UpdateIntent","UpdateResourcePolicy","UpdateSlot","UpdateSlotType","UpdateTestSet"] | D110: arn:aws:lex:${Region}:${Account}:${ResourceType}/${ResourceId} | E110: ^arn:aws:lex:.+:[0-9]+:.+ | F110: ["aws:RequestTag/${TagKey}","aws:ResourceTag/${TagKey}","aws:TagKeys"] | G110: TRUE | H110: https://docs.aws.amazon.com/service-authorization/latest/UserGuide/list_amazonlexv2.html
... A127: airflow | B127: Amazon Managed Workflows for Apache Airflow | C127: ["CreateCliToken","CreateEnvironment","CreateWebLoginToken","DeleteEnvironment","GetEnvironment","InvokeRestApi","ListEnvironments","ListTagsForResource","PublishMetrics","TagResource","UntagResource","UpdateEnvironment"] | D127: arn:aws:airflow:${Region}:${Account}:${ResourceType}/${ResourceName} | E127: ^arn:aws:airflow:.+:.+:.+ | F127: ["airflow:DagAccessEntity","airflow:ResourceAction","airflow:ResourceId","airflow:ResourceType","airflow:TeamNames","aws:RequestTag/${TagKey}","aws:ResourceTag/${TagKey}","aws:TagKeys"] | G127: TRUE | H127: https://docs.aws.amazon.com/service-authorization/latest/UserGuide/list_amazonmanagedworkflowsforapacheairflow.html
A128: mechanicalturk | B128: Amazon Mechanical Turk | C128: ["AcceptQualificationRequest","ApproveAssignment","AssociateQualificationWithWorker","CreateAdditionalAssignmentsForHIT","CreateHIT","CreateHITType","CreateHITWithHITType","CreateQualificationType","CreateWorkerBlock","DeleteHIT","DeleteQualificationType","DeleteWorkerBlock","DisassociateQualificationFromWorker","GetAccountBalance","GetAssignment","GetFileUploadURL","GetHIT","GetQualificationScore","GetQualificationType","ListAssignmentsForHIT","ListBonusPayments","ListHITs","ListHITsForQualificationType","ListQualificationRequests","ListQualificationTypes","ListReviewPolicyResultsForHIT","ListReviewableHITs","ListWorkerBlocks","ListWorkersWithQualificationType","NotifyWorkers","RejectAssignment","RejectQualificationRequest","SendBonus","SendTestEventNotification","UpdateExpirationForHIT","UpdateHITReviewStatus","UpdateHITTypeOfHIT","UpdateNotificationSettings","UpdateQualificationType"] | F128: null | G128: FALSE | H128: https://docs.aws.amazon.com/service-authorization/latest/UserGuide/list_amazonmechanicalturk.html
A129: memorydb | B129: Amazon MemoryDB | C129: ["BatchUpdateCluster","Connect","CopySnapshot","CreateAcl","CreateCluster","CreateMultiRegionCluster","CreateParameterGroup","CreateSnapshot","CreateSubnetGroup","CreateUser","DeleteAcl","DeleteCluster","DeleteMultiRegionCluster","DeleteParameterGroup","DeleteSnapshot","DeleteSubnetGroup","DeleteUser","DescribeAcls","DescribeClusters","DescribeEngineVersions","DescribeEvents","DescribeMultiRegionClusters","DescribeMultiRegionParameterGroups","DescribeMultiRegionParameters","DescribeParameterGroups","DescribeParameters","DescribeReservedNodes","DescribeReservedNodesOfferings","DescribeServiceUpdates","DescribeSnapshots","DescribeSubnetGroups","DescribeUsers","FailoverShard","ListAllowedMultiRegionClusterUpdates","ListAllowedNodeTypeUpdates","ListTags","PauseMultiRegionClusterReplication","PurchaseReservedNodesOffering","ResetParameterGroup","TagResource","UntagResource","UpdateAcl","UpdateCluster","UpdateMultiRegionCluster","UpdateParameterGroup","UpdateSubnetGroup","UpdateUser"] | D129: arn:aws:memorydb:${Region}:${Account}:${ResourceType}/${ResourceName} | E129: ^arn:aws:memorydb:.+:.+:.+ | F129: ["aws:RequestTag/${TagKey}","aws:ResourceTag/${TagKey}","aws:TagKeys","memorydb:TLSEnabled","memorydb:UserAuthenticationMode"] | G129: TRUE | H129: https://docs.aws.amazon.com/service-authorization/latest/UserGuide/list_amazonmemorydb.html
A130: ec2messages | B130: Amazon Message Delivery Service | C130: ["AcknowledgeMessage","DeleteMessage","FailMessage","GetEndpoint","GetMessages","SendReply"] | F130: ["ec2:SourceInstanceARN","ssm:SourceInstanceARN"] | G130: FALSE | H130: https://docs.aws.amazon.com/service-authorization/latest/UserGuide/list_amazonmessagedeliveryservice.html
A131: ssmmessages | B131: Amazon Message Gateway Service | C131: ["CreateControlChannel","CreateDataChannel","OpenControlChannel","OpenDataChannel"] | F131: ["ec2:SourceInstanceARN","ssm:SourceInstanceARN"] | G131: FALSE | H131: https://docs.aws.amazon.com/service-authorization/latest/UserGuide/list_amazonmessagegatewayservice.html
A132: mobileanalytics | B132: Amazon Mobile Analytics | C132: ["GetFinancialReports","GetReports","PutEvents"] | F132: null | G132: FALSE | H132: https://docs.aws.amazon.com/service-authorization/latest/UserGuide/list_amazonmobileanalytics.html
A133: monitron | B133: Amazon Monitron | C133: ["AssociateProjectAdminUser","CreateProject","CreateProjectUserAssociation","CreateUserAccessRoleAssociation","DeleteProject","DeleteProjectUserAssociation","DeleteUserAccessRoleAssociation","DisassociateProjectAdminUser","GetProject","GetProjectAdminUser","ListProjectAdminUsers","ListProjectUserAssociations","ListProjects","ListTagsForResource","ListUserAccessRoleAssociations","TagResource","UntagResource","UpdateProject"] | D133: arn:aws:monitron:${Region}:${Account}:${ResourceType}/${ResourceId} | E133: ^arn:aws:monitron:.+:.+:.+ | F133: ["aws:RequestTag/${TagKey}","aws:ResourceTag/${TagKey}","aws:TagKeys"] | G133: TRUE | H133: https://docs.aws.amazon.com/service-authorization/latest/UserGuide/list_amazonmonitron.html
A134: mq | B134: Amazon MQ | C134: ["CreateBroker","CreateConfiguration","CreateReplicaBroker","CreateTags","CreateUser","DeleteBroker","DeleteConfiguration","DeleteTags","DeleteUser","DescribeBroker","DescribeBrokerEngineTypes","DescribeBrokerInstanceOptions","DescribeConfiguration","DescribeConfigurationRevision","DescribeSharedResources","DescribeUser","ListBrokers","ListConfigurationRevisions","ListConfigurations","ListTags","ListUsers","Promote","RebootBroker","UpdateBroker","UpdateBrokerAccessConfiguration","UpdateConfiguration","UpdateUser"] | D134: arn:aws:mq:${Region}:${Account}:.+ | E134: ^arn:aws:mq:.+ | F134: ["aws:RequestTag/${TagKey}","aws:ResourceTag/${TagKey}","aws:TagKeys"] | G134: TRUE | H134: https://docs.aws.amazon.com/service-authorization/latest/UserGuide/list_amazonmq.html
A135: neptune-db | B135: Amazon Neptune | C135: ["CancelLoaderJob","CancelMLDataProcessingJob","CancelMLModelTrainingJob","CancelMLModelTransformJob","CancelQuery","CreateMLEndpoint","DeleteDataViaQuery","DeleteMLEndpoint","DeleteStatistics","GetEngineStatus","GetGraphSummary","GetLoaderJobStatus","GetMLDataProcessingJobStatus","GetMLEndpointStatus","GetMLModelTrainingJobStatus","GetMLModelTransformJobStatus","GetQueryStatus","GetStatisticsStatus","GetStreamRecords","ListLoaderJobs","ListMLDataProcessingJobs","ListMLEndpoints","ListMLModelTrainingJobs","ListMLModelTransformJobs","ManageStatistics","ReadDataViaQuery","ResetDatabase","StartLoaderJob","StartMLDataProcessingJob","StartMLModelTrainingJob","StartMLModelTransformJob","WriteDataViaQuery","connect"] | D135: arn:aws:neptune-db:${Region}:${Account}:${Id}/* | E135: ^arn:aws:neptune-db:.+ | F135: "neptune-db:QueryLanguage" | G135: TRUE | H135: https://docs.aws.amazon.com/service-authorization/latest/UserGuide/list_amazonneptune.html
A136: neptune-graph | B136: Amazon Neptune Analytics | C136: ["CancelExportTask","CancelImportTask","CancelQuery","CreateGraph","CreateGraphSnapshot","CreateGraphUsingImportTask","CreatePrivateGraphEndpoint","DeleteDataViaQuery","DeleteGraph","DeleteGraphSnapshot","DeletePrivateGraphEndpoint","GetEngineStatus","GetExportTask","GetGraph","GetGraphSnapshot","GetGraphSummary","GetImportTask","GetPrivateGraphEndpoint","GetQueryStatus","GetStatisticsStatus","ListExportTasks","ListGraphSnapshots","ListGraphs","ListImportTasks","ListPrivateGraphEndpoints","ListQueries","ListTagsForResource","ReadDataViaQuery","ResetGraph","RestoreGraphFromSnapshot","StartExportTask","StartGraph","StartImportTask","StopGraph","TagResource","UntagResource","UpdateGraph","WriteDataViaQuery"] | D136: arn:aws:neptune-graph:${Region}:${Account}:${ResourceType}/${ResourceId} | E136: ^arn:aws:neptune-graph:.+ | F136: ["aws:RequestTag/${TagKey}","aws:ResourceTag/${TagKey}","aws:TagKeys","neptune-graph:PublicConnectivity"] | G136: TRUE | H136: https://docs.aws.amazon.com/service-authorization/latest/UserGuide/list_amazonneptuneanalytics.html
A137: nimble | B137: Amazon Nimble Studio | C137: ["AcceptEulas","CreateLaunchProfile","CreateStreamingImage","CreateStreamingSession","CreateStreamingSessionStream","CreateStudio","CreateStudioComponent","DeleteLaunchProfile","DeleteLaunchProfileMember","DeleteStreamingImage","DeleteStreamingSession","DeleteStudio","DeleteStudioComponent","DeleteStudioMember","GetEula","GetFeatureMap","GetLaunchProfile","GetLaunchProfileDetails","GetLaunchProfileInitialization","GetLaunchProfileMember","GetStreamingImage","GetStreamingSession","GetStreamingSessionBackup","GetStreamingSessionStream","GetStudio","GetStudioComponent","GetStudioMember","ListEulaAcceptances","ListEulas","ListLaunchProfileMembers","ListLaunchProfiles","ListStreamingImages","ListStreamingSessionBackups","ListStreamingSessions","ListStudioComponents","ListStudioMembers","ListStudios","ListTagsForResource","PutLaunchProfileMembers","PutStudioLogEvents","PutStudioMembers","StartStreamingSession","StartStudioSSOConfigurationRepair","StopStreamingSession","TagResource","UntagResource","UpdateLaunchProfile","UpdateLaunchProfileMember","UpdateStreamingImage","UpdateStudio","UpdateStudioComponent"] | D137: arn:aws:nimble:${Region}:${Account}:${ResourceType}/${ResourcePath} | E137: ^arn:aws:nimble:.+:.+:.+ | F137: ["aws:RequestTag/${TagKey}","aws:ResourceTag/${TagKey}","aws:TagKeys","nimble:createdBy","nimble:ownedBy","nimble:principalId","nimble:requesterPrincipalId","nimble:studioId"] | G137: TRUE | H137: https://docs.aws.amazon.com/service-authorization/latest/UserGuide/list_amazonnimblestudio.html
A138: nova-act | B138: Amazon Nova Act | C138: ["CreateAct","CreateSession","CreateWorkflowDefinition","CreateWorkflowRun","DeleteWorkflowDefinition","DeleteWorkflowRun","GetWorkflowDefinition","GetWorkflowRun","InvokeActStep","ListActs","ListModels","ListSessions","ListWorkflowDefinitions","ListWorkflowRuns","UpdateAct","UpdateWorkflowRun"] | D138: arn:aws:nova-act:${Region}:${Account}:${ResourceType}/${ResourcePath} | E138: ^arn:aws:nova-act:.+:.+:.+ | F138: null | G138: TRUE | H138: https://docs.aws.amazon.com/service-authorization/latest/UserGuide/list_amazonnovaact.html
A139: one | B139: Amazon One Enterprise | C139: ["CreateDeviceActivationQrCode","CreateDeviceConfigurationTemplate","CreateDeviceInstance","CreateDeviceInstanceConfiguration","CreateSite","DeleteAssociatedDevice","DeleteDeviceConfigurationTemplate","DeleteDeviceInstance","DeleteSite","DeleteUserV1","GetDeviceConfigurationTemplate","GetDeviceInstance","GetDeviceInstanceConfiguration","GetSite","GetSiteAddress","ListDeviceConfigurationTemplates","ListDeviceInstances","ListSites","ListTagsForResource","ListUsers","ListUsersV1","RebootDevice","TagResource","UntagResource","UpdateDeviceConfigurationTemplate","UpdateDeviceInstance","UpdateSite","UpdateSiteAddress"] | D139: arn:aws:one:${Region}:${Account}:${ResourceType}:${ResourceId} | E139: ^arn:aws:one:.+ | F139: ["aws:RequestTag/${TagKey}","aws:ResourceTag/${TagKey}","aws:TagKeys"] | G139: TRUE | H139: https://docs.aws.amazon.com/service-authorization/latest/UserGuide/list_amazononeenterprise.html
A140: opensearch | B140: Amazon OpenSearch | C140: ["ApplicationAccessAll","CancelAutoOptimizeJob","CancelDirectQuery","DeleteAutoOptimizeJob","GetAutoOptimizeJob","GetDirectQuery","GetDirectQueryResult","ListAutoOptimizeJobs","StartDirectQuery","SubmitAutoOptimizeJob","ViewLoginPage"] | D140: arn:aws:opensearch:${Region}:${Account}:${Resource} | E140: ^arn:aws:opensearch:.+ | F140: null | G140: TRUE | H140: https://docs.aws.amazon.com/service-authorization/latest/UserGuide/list_amazonopensearch.html
A141: osis | B141: Amazon OpenSearch Ingestion | C141: ["CreatePipeline","CreatePipelineEndpoint","DeletePipeline","DeletePipelineEndpoint","DeleteResourcePolicy","GetPipeline","GetPipelineBlueprint","GetPipelineChangeProgress","GetResourcePolicy","Ingest","ListPipelineBlueprints","ListPipelineEndpointConnections","ListPipelineEndpoints","ListPipelines","ListTagsForResource","PutResourcePolicy","RevokePipelineEndpointConnections","StartPipeline","StopPipeline","TagResource","UntagResource","UpdatePipeline","ValidatePipeline"] | D141: arn:aws:osis:${Region}:${Account}:${ResourceType}/${ResourceName} | E141: ^arn:aws:osis:.+:.+:.+ | F141: ["aws:RequestTag/${TagKey}","aws:ResourceTag/${TagKey}","aws:TagKeys"] | G141: TRUE | H141: https://docs.aws.amazon.com/service-authorization/latest/UserGuide/list_amazonopensearchingestion.html
A142: aoss | B142: Amazon OpenSearch Serverless | C142: ["APIAccessAll","AddCollectionToCollectionGroup","BatchGetCollection","BatchGetCollectionGroup","BatchGetEffectiveLifecyclePolicy","BatchGetLifecyclePolicy","BatchGetVpcEndpoint","CreateAccessPolicy","CreateCollection","CreateCollectionGroup","CreateIndex","CreateLifecyclePolicy","CreateSecurityConfig","CreateSecurityPolicy","CreateVpcEndpoint","DashboardsAccessAll","DeleteAccessPolicy","DeleteCollection","DeleteCollectionGroup","DeleteIndex","DeleteLifecyclePolicy","DeleteSecurityConfig","DeleteSecurityPolicy","DeleteVpcEndpoint","GetAccessPolicy","GetAccountSettings","GetIndex","GetPoliciesStats","GetSecurityConfig","GetSecurityPolicy","ListAccessPolicies","ListCollectionGroups","ListCollections","ListLifecyclePolicies","ListSecurityConfigs","ListSecurityPolicies","ListTagsForResource","ListVpcEndpoints","TagResource","UntagResource","UpdateAccessPolicy","UpdateAccountSettings","UpdateCollection","UpdateCollectionGroup","UpdateIndex","UpdateLifecyclePolicy","UpdateSecurityConfig","UpdateSecurityPolicy","UpdateVpcEndpoint"] | D142: arn:aws:aoss:${Region}:${Account}:${Resource} | E142: ^arn:aws:aoss:.+ | F142: ["aoss:CollectionId","aoss:collection","aoss:collection-group","aoss:index","aws:RequestTag/${TagKey}","aws:ResourceTag/${TagKey}","aws:TagKeys"] | G142: TRUE | H142: https://docs.aws.amazon.com/service-authorization/latest/UserGuide/list_amazonopensearchserverless.html
A143: es | B143: Amazon OpenSearch Service | C143: ["AcceptInboundConnection","AcceptInboundCrossClusterSearchConnection","AddDataSource","AddDirectQueryDataSource","AddTags","AssociatePackage","AssociatePackages","AttachDataSource","AuthorizeVpcEndpointAccess","CancelDomainConfigChange","CancelElasticsearchServiceSoftwareUpdate","CancelServiceSoftwareUpdate","CreateApplication","CreateDomain","CreateElasticsearchDomain","CreateElasticsearchServiceRole","CreateIndex","CreateOutboundConnection","CreateOutboundCrossClusterSearchConnection","CreatePackage","CreateServiceRole","CreateVpcEndpoint","DeleteApplication","DeleteDataSource","DeleteDirectQueryDataSource","DeleteDomain","DeleteElasticsearchDomain","DeleteElasticsearchServiceRole","DeleteInboundConnection","DeleteInboundCrossClusterSearchConnection","DeleteIndex","DeleteOutboundConnection","DeleteOutboundCrossClusterSearchConnection","DeletePackage","DeleteVpcEndpoint","DeregisterCapability","DescribeDataSourceAttachment","DescribeDomain","DescribeDomainAutoTunes","DescribeDomainChangeProgress","DescribeDomainConfig","DescribeDomainHealth","DescribeDomainNodes","DescribeDomains","DescribeDryRunProgress","DescribeElasticsearchDomain","DescribeElasticsearchDomainConfig","DescribeElasticsearchDomains","DescribeElasticsearchInstanceTypeLimits","DescribeInboundConnections","DescribeInboundCrossClusterSearchConnections","DescribeInsightDetails","DescribeInstanceTypeLimits","DescribeOutboundConnections","DescribeOutboundCrossClusterSearchConnections","DescribePackages","DescribeReservedElasticsearchInstanceOfferings","DescribeReservedElasticsearchInstances","DescribeReservedInstanceOfferings","DescribeReservedInstances","DescribeVpcEndpoints","DetachDataSource","DissociatePackage","DissociatePackages","ESCrossClusterGet","ESHttpDelete","ESHttpGet","ESHttpHead","ESHttpPatch","ESHttpPost","ESHttpPut","GetApplication","GetCapability","GetCompatibleElasticsearchVersions","GetCompatibleVersions","GetDataSource","GetDefaultApplicationSetting","GetDirectQueryDataSource","GetDomainMaintenanceStatus","GetIndex","GetMigration","GetPackageVersionHistory","GetUpgradeHistory","GetUpgradeStatus","InsightFeedback","ListApplications","ListDataSourceAttachments","ListDataSources","ListDirectQueryDataSources","ListDomainMaintenances","ListDomainNames","ListDomainsForPackage","ListElasticsearchInstanceTypeDetails","ListElasticsearchInstanceTypes","ListElasticsearchVersions","ListInsights","ListInstanceTypeDetails","ListMigrations","ListPackagesForDomain","ListScheduledActions","ListTags","ListVersions","ListVpcEndpointAccess","ListVpcEndpoints","ListVpcEndpointsForDomain","PurchaseReservedElasticsearchInstanceOffering","PurchaseReservedInstanceOffering","PutDefaultApplicationSetting","RegisterCapability","RejectInboundConnection","RejectInboundCrossClusterSearchConnection","RemoveTags","RevokeVpcEndpointAccess","RollbackElasticsearchServiceSoftwareUpdate","RollbackServiceSoftwareUpdate","StartDomainMaintenance","StartElasticsearchServiceSoftwareUpdate","StartMigration","StartServiceSoftwareUpdate","UpdateApplication","UpdateDataSource","UpdateDirectQueryDataSource","UpdateDomainConfig","UpdateElasticsearchDomainConfig","UpdateIndex","UpdatePackage","UpdatePackageScope","UpdateScheduledAction","UpdateVpcEndpoint","UpgradeDomain","UpgradeElasticsearchDomain"] | D143: arn:aws:es:${Region}:${Account}:${Resource} | E143: ^arn:aws:es:.+ | F143: ["aws:RequestTag/${TagKey}","aws:ResourceTag/${TagKey}","aws:TagKeys"] | G143: TRUE | H143: https://docs.aws.amazon.com/service-authorization/latest/UserGuide/list_amazonopensearchservice.html
A144: personalize | B144: Amazon Personalize | C144: ["CreateBatchInferenceJob","CreateBatchSegmentJob","CreateCampaign","CreateDataDeletionJob","CreateDataInsightsJob","CreateDataset","CreateDatasetExportJob","CreateDatasetGroup","CreateDatasetImportJob","CreateEventTracker","CreateFilter","CreateMetricAttribution","CreateRecommender","CreateSchema","CreateSolution","CreateSolutionVersion","DeleteCampaign","DeleteDataset","DeleteDatasetGroup","DeleteEventTracker","DeleteFilter","DeleteMetricAttribution","DeleteRecommender","DeleteSchema","DeleteSolution","DescribeAlgorithm","DescribeBatchInferenceJob","DescribeBatchSegmentJob","DescribeCampaign","DescribeDataDeletionJob","DescribeDataInsightsJob","DescribeDataset","DescribeDatasetExportJob","DescribeDatasetGroup","DescribeDatasetImportJob","DescribeEventTracker","DescribeFeatureTransformation","DescribeFilter","DescribeMetricAttribution","DescribeRecipe","DescribeRecommender","DescribeSchema","DescribeSolution","DescribeSolutionVersion","GetActionRecommendations","GetDataInsights","GetPersonalizedRanking","GetRecommendations","GetSolutionMetrics","ListBatchInferenceJobs","ListBatchSegmentJobs","ListCampaigns","ListDataDeletionJobs","ListDataInsightsJobs","ListDatasetExportJobs","ListDatasetGroups","ListDatasetImportJobs","ListDatasets","ListEventTrackers","ListFilters","ListMetricAttributionMetrics","ListMetricAttributions","ListRecipes","ListRecommenders","ListSchemas","ListSolutionVersions","ListSolutions","ListTagsForResource","PutActionInteractions","PutActions","PutEvents","PutItems","PutUsers","StartRecommender","StopRecommender","StopSolutionVersionCreation","TagResource","UntagResource","UpdateCampaign","UpdateDataset","UpdateMetricAttribution","UpdateRecommender","UpdateSolution"] | D144: arn:aws:personalize:${Region}:${Account}:${Resourcename}/${ResourceId} | E144: ^arn:aws:personalize:.+:.+:.+ | F144: ["aws:RequestTag/${TagKey}","aws:ResourceTag/${TagKey}","aws:TagKeys"] | G144: TRUE | H144: https://docs.aws.amazon.com/service-authorization/latest/UserGuide/list_amazonpersonalize.html
... A162: rekognition | B162: Amazon Rekognition | C162: ["AssociateFaces","CompareFaces","CopyProjectVersion","CreateCollection","CreateDataset","CreateFaceLivenessSession","CreateProject","CreateProjectVersion","CreateStreamProcessor","CreateUser","DeleteCollection","DeleteDataset","DeleteFaces","DeleteProject","DeleteProjectPolicy","DeleteProjectVersion","DeleteStreamProcessor","DeleteUser","DescribeCollection","DescribeDataset","DescribeProjectVersions","DescribeProjects","DescribeStreamProcessor","DetectCustomLabels","DetectFaces","DetectLabels","DetectModerationLabels","DetectProtectiveEquipment","DetectText","DisassociateFaces","DistributeDatasetEntries","GetCelebrityInfo","GetCelebrityRecognition","GetContentModeration","GetFaceDetection","GetFaceLivenessSessionResults","GetFaceSearch","GetLabelDetection","GetMediaAnalysisJob","GetPersonTracking","GetSegmentDetection","GetTextDetection","IndexFaces","ListCollections","ListDatasetEntries","ListDatasetLabels","ListFaces","ListMediaAnalysisJobs","ListProjectPolicies","ListStreamProcessors","ListTagsForResource","ListUsers","PutProjectPolicy","RecognizeCelebrities","SearchFaces","SearchFacesByImage","SearchUsers","SearchUsersByImage","StartCelebrityRecognition","StartContentModeration","StartFaceDetection","StartFaceLivenessSession","StartFaceSearch","StartLabelDetection","StartMediaAnalysisJob","StartPersonTracking","StartProjectVersion","StartSegmentDetection","StartStreamProcessor","StartTextDetection","StopProjectVersion","StopStreamProcessor","TagResource","UntagResource","UpdateDatasetEntries","UpdateStreamProcessor"] | D162: arn:aws:rekognition:${Region}:${Account}:${RelativeId} | E162: ^arn:aws:rekognition:.+ | F162: ["aws:RequestTag/${TagKey}","aws:ResourceTag/${TagKey}","aws:TagKeys"] | G162: TRUE | H162: https://docs.aws.amazon.com/service-authorization/latest/UserGuide/list_amazonrekognition.html
A163: tag | B163: Amazon Resource Group Tagging API | C163: ["DescribeReportCreation","GetComplianceSummary","GetResources","GetTagKeys","GetTagValues","ListRequiredTags","StartReportCreation","TagResources","UntagResources"] | F163: null | G163: FALSE | H163: https://docs.aws.amazon.com/service-authorization/latest/UserGuide/list_amazonresourcegrouptaggingapi.html
A164: rhelkb | B164: Amazon RHEL Knowledgebase Portal | C164: "GetRhelURL" | D164: arn:${Partition}:rhelkb:${Region}:${Account}:${ResourceType}/${ResourceName} | E164: ^arn:${Partition}:rhelkb:.+ | F164: null | G164: FALSE | H164: https://docs.aws.amazon.com/service-authorization/latest/UserGuide/list_amazonrhelknowledgebaseportal.html
A165: route53 | B165: Amazon Route 53 | C165: ["ActivateKeySigningKey","AssociateVPCWithHostedZone","ChangeCidrCollection","ChangeResourceRecordSets","ChangeTagsForResource","CreateCidrCollection","CreateHealthCheck","CreateHostedZone","CreateKeySigningKey","CreateQueryLoggingConfig","CreateReusableDelegationSet","CreateTrafficPolicy","CreateTrafficPolicyInstance","CreateTrafficPolicyVersion","CreateVPCAssociationAuthorization","DeactivateKeySigningKey","DeleteCidrCollection","DeleteHealthCheck","DeleteHostedZone","DeleteKeySigningKey","DeleteQueryLoggingConfig","DeleteReusableDelegationSet","DeleteTrafficPolicy","DeleteTrafficPolicyInstance","DeleteVPCAssociationAuthorization","DisableHostedZoneDNSSEC","DisassociateVPCFromHostedZone","EnableHostedZoneDNSSEC","GetAccountLimit","GetChange","GetCheckerIpRanges","GetDNSSEC","GetGeoLocation","GetHealthCheck","GetHealthCheckCount","GetHealthCheckLastFailureReason","GetHealthCheckStatus","GetHostedZone","GetHostedZoneCount","GetHostedZoneLimit","GetQueryLoggingConfig","GetReusableDelegationSet","GetReusableDelegationSetLimit","GetTrafficPolicy","GetTrafficPolicyInstance","GetTrafficPolicyInstanceCount","ListCidrBlocks","ListCidrCollections","ListCidrLocations","ListGeoLocations","ListHealthChecks","ListHostedZones","ListHostedZonesByName","ListHostedZonesByVPC","ListQueryLoggingConfigs","ListResourceRecordSets","ListReusableDelegationSets","ListTagsForResource","ListTagsForResources","ListTrafficPolicies","ListTrafficPolicyInstances","ListTrafficPolicyInstancesByHostedZone","ListTrafficPolicyInstancesByPolicy","ListTrafficPolicyVersions","ListVPCAssociationAuthorizations","TestDNSAnswer","UpdateHealthCheck","UpdateHostedZoneComment","UpdateHostedZoneFeatures","UpdateTrafficPolicyComment","UpdateTrafficPolicyInstance"] | D165: arn:aws:route53:::${Resource}/{$Id} | E165: ^arn:aws:route53:::.+ | F165: ["route53:ChangeResourceRecordSetsActions","route53:ChangeResourceRecordSetsNormalizedRecordNames","route53:ChangeResourceRecordSetsRecordTypes","route53:VPCs"] | G165: TRUE | H165: https://docs.aws.amazon.com/service-authorization/latest/UserGuide/list_amazonroute53.html
A166: route53domains | B166: Amazon Route 53 Domains | C166: ["AcceptDomainTransferFromAnotherAwsAccount","AssociateDelegationSignerToDomain","CancelDomainTransferToAnotherAwsAccount","CheckDomainAvailability","CheckDomainTransferability","DeleteDomain","DeleteTagsForDomain","DisableDomainAutoRenew","DisableDomainTransferLock","DisassociateDelegationSignerFromDomain","EnableDomainAutoRenew","EnableDomainTransferLock","GetContactReachabilityStatus","GetDomainDetail","GetDomainSuggestions","GetOperationDetail","ListDomains","ListOperations","ListPrices","ListTagsForDomain","PushDomain","RegisterDomain","RejectDomainTransferFromAnotherAwsAccount","RenewDomain","ResendContactReachabilityEmail","ResendOperationAuthorization","RetrieveDomainAuthCode","TransferDomain","TransferDomainToAnotherAwsAccount","UpdateDomainContact","UpdateDomainContactPrivacy","UpdateDomainNameservers","UpdateTagsForDomain","ViewBilling"] | F166: null | G166: FALSE | H166: https://docs.aws.amazon.com/service-authorization/latest/UserGuide/list_amazonroute53domains.html
A167: route53profiles | B167: Amazon Route 53 Profiles | C167: ["AssociateProfile","AssociateResourceToProfile","CreateProfile","DeleteProfile","DisassociateProfile","DisassociateResourceFromProfile","GetProfile","GetProfileAssociation","GetProfilePolicy","GetProfileResourceAssociation","ListProfileAssociations","ListProfileResourceAssociations","ListProfiles","ListTagsForResource","PutProfilePolicy","TagResource","UntagResource","UpdateProfileResourceAssociation"] | D167: arn:aws:route53profiles:${Region}:${Account}:${ResourceType}/${ResourceId} | E167: ^arn:aws:route53profiles:.+:.+:.+ | F167: ["aws:RequestTag/${TagKey}","aws:ResourceTag/${TagKey}","aws:TagKeys","route53profiles:FirewallRuleGroupPriority","route53profiles:HostedZoneDomains","route53profiles:ResolverRuleDomains","route53profiles:ResourceArns","route53profiles:ResourceIds","route53profiles:ResourceTypes"] | G167: TRUE | H167: https://docs.aws.amazon.com/service-authorization/latest/UserGuide/list_amazonroute53profiles.html
A168: route53-recovery-cluster | B168: Amazon Route 53 Recovery Cluster | C168: ["GetRoutingControlState","ListRoutingControls","UpdateRoutingControlState","UpdateRoutingControlStates"] | D168: arn:aws:route53-recovery-control::${Account}:${ResourceType}/${ResourceName} | E168: ^arn:aws:route53-recovery-control::.+:.+ | F168: "route53-recovery-cluster:AllowSafetyRulesOverrides" | G168: TRUE | H168: https://docs.aws.amazon.com/service-authorization/latest/UserGuide/list_amazonroute53recoverycluster.html
A169: route53-recovery-control-config | B169: Amazon Route 53 Recovery Controls | C169: ["CreateCluster","CreateControlPanel","CreateRoutingControl","CreateSafetyRule","DeleteCluster","DeleteControlPanel","DeleteResourcePolicy","DeleteRoutingControl","DeleteSafetyRule","DescribeCluster","DescribeControlPanel","DescribeRoutingControl","DescribeSafetyRule","GetResourcePolicy","ListAssociatedRoute53HealthChecks","ListClusters","ListControlPanels","ListRoutingControls","ListSafetyRules","ListTagsForResource","PutResourcePolicy","TagResource","UntagResource","UpdateCluster","UpdateControlPanel","UpdateRoutingControl","UpdateSafetyRule"] | D169: arn:aws:route53-recovery-control::${Account}:${ResourceType}/${ResourceName} | E169: ^arn:aws:route53-recovery-control::.+:.+ | F169: ["aws:RequestTag/${TagKey}","aws:ResourceTag/${TagKey}","aws:TagKeys"] | G169: TRUE | H169: https://docs.aws.amazon.com/service-authorization/latest/UserGuide/list_amazonroute53recoverycontrols.html
A170: route53-recovery-readiness | B170: Amazon Route 53 Recovery Readiness | C170: ["CreateCell","CreateCrossAccountAuthorization","CreateReadinessCheck","CreateRecoveryGroup","CreateResourceSet","DeleteCell","DeleteCrossAccountAuthorization","DeleteReadinessCheck","DeleteRecoveryGroup","DeleteResourceSet","GetArchitectureRecommendations","GetCell","GetCellReadinessSummary","GetReadinessCheck","GetReadinessCheckResourceStatus","GetReadinessCheckStatus","GetRecoveryGroup","GetRecoveryGroupReadinessSummary","GetResourceSet","ListCells","ListCrossAccountAuthorizations","ListReadinessChecks","ListRecoveryGroups","ListResourceSets","ListRules","ListTagsForResources","TagResource","UntagResource","UpdateCell","UpdateReadinessCheck","UpdateRecoveryGroup","UpdateResourceSet"] | D170: arn:aws:route53-recovery-readiness::${Account}:${ResourceType}/${ResourceName} | E170: ^arn:aws:route53-recovery-readiness::.+:.+ | F170: ["aws:RequestTag/${TagKey}","aws:ResourceTag/${TagKey}","aws:TagKeys"] | G170: TRUE | H170: https://docs.aws.amazon.com/service-authorization/latest/UserGuide/list_amazonroute53recoveryreadiness.html
A171: route53resolver | B171: Amazon Route 53 Resolver | C171: ["AssociateFirewallRuleGroup","AssociateResolverEndpointIpAddress","AssociateResolverQueryLogConfig","AssociateResolverRule","CreateFirewallDomainList","CreateFirewallRule","CreateFirewallRuleGroup","CreateOutpostResolver","CreateResolverEndpoint","CreateResolverQueryLogConfig","CreateResolverRule","DeleteFirewallDomainList","DeleteFirewallRule","DeleteFirewallRuleGroup","DeleteOutpostResolver","DeleteResolverEndpoint","DeleteResolverQueryLogConfig","DeleteResolverRule","DisassociateFirewallRuleGroup","DisassociateResolverEndpointIpAddress","DisassociateResolverQueryLogConfig","DisassociateResolverRule","GetFirewallConfig","GetFirewallDomainList","GetFirewallRuleGroup","GetFirewallRuleGroupAssociation","GetFirewallRuleGroupPolicy","GetOutpostResolver","GetResolverConfig","GetResolverDnssecConfig","GetResolverEndpoint","GetResolverQueryLogConfig","GetResolverQueryLogConfigAssociation","GetResolverQueryLogConfigPolicy","GetResolverRule","GetResolverRuleAssociation","GetResolverRulePolicy","ImportFirewallDomains","ListFirewallConfigs","ListFirewallDomainLists","ListFirewallDomains","ListFirewallRuleGroupAssociations","ListFirewallRuleGroups","ListFirewallRuleTypes","ListFirewallRules","ListOutpostResolvers","ListResolverConfigs","ListResolverDnssecConfigs","ListResolverEndpointIpAddresses","ListResolverEndpoints","ListResolverQueryLogConfigAssociations","ListResolverQueryLogConfigs","ListResolverRuleAssociations","ListResolverRules","ListTagsForResource","PutFirewallRuleGroupPolicy","PutResolverQueryLogConfigPolicy","PutResolverRulePolicy","TagResource","UntagResource","UpdateFirewallConfig","UpdateFirewallDomains","UpdateFirewallRule","UpdateFirewallRuleGroupAssociation","UpdateOutpostResolver","UpdateResolverConfig","UpdateResolverDnssecConfig","UpdateResolverEndpoint","UpdateResolverRule"] | D171: arn:aws:route53resolver:${Region}:${Account}:${ResourceType}/${ResourceId} | E171: ^arn:aws:route53resolver:.+:.+:.+ | F171: ["aws:RequestTag/${TagKey}","aws:ResourceTag/${TagKey}","aws:TagKeys"] | G171: TRUE | H171: https://docs.aws.amazon.com/service-authorization/latest/UserGuide/list_amazonroute53resolver.html
